Workbook
Name Z_0111E7B5_3E0B_11D4_8303_000102284B93_.wvu.PrintArea: #REF!
Name Z_011E7B5_3E0B_11D4_8303_000102284B94: #REF!
Name Z_EC51EC7F_3C0B_4CF9_8F20_C7FD08174DA8_.wvu.PrintArea: 'Entsorgung Déchets'!$B$1:$S$10
Name Z_EC51EC7F_3C0B_4CF9_8F20_C7FD08174DA8_.wvu.PrintArea: 'Gebäudetechnik Technique'!$B$1:$W$48
Name Z_EC51EC7F_3C0B_4CF9_8F20_C7FD08174DA8_.wvu.PrintArea: 'Baumaterialien Matériaux'!$B$1:$V$271
Name Z_011E7B5_3E0B_11D4_8303_000102284B94: #REF!
Name Z_EC51EC7F_3C0B_4CF9_8F20_C7FD08174DA8_.wvu.PrintArea: 'Energie Énergie'!$B$1:$L$95
Name Z_EC51EC7F_3C0B_4CF9_8F20_C7FD08174DA8_.wvu.PrintTitles: 'Erläuterung Explication'!$1:$2
Name Z_EC51EC7F_3C0B_4CF9_8F20_C7FD08174DA8_.wvu.PrintTitles: 'Energie Énergie'!$1:$7
Name Z_011E7B5_3E0B_11D4_8303_000102284B94: #REF!
Name Z_EC51EC7F_3C0B_4CF9_8F20_C7FD08174DA8_.wvu.PrintTitles: 'Transporte Transports'!$1:$9
Name Z_EC51EC7F_3C0B_4CF9_8F20_C7FD08174DA8_.wvu.PrintTitles: 'Entsorgung Déchets'!$1:$10
Name Z_0111E7B5_3E0B_11D4_8303_000102284B93_.wvu.PrintArea: #REF!
Name Z_0111E7B5_3E0B_11D4_8303_000102284B93_.wvu.PrintArea: #REF!
Name Z_EC51EC7F_3C0B_4CF9_8F20_C7FD08174DA8_.wvu.PrintTitles: 'Gebäudetechnik Technique'!$1:$9
Name Z_0111E7B5_3E0B_11D4_8303_000102284B93_.wvu.PrintArea: #REF!
Name Z_011E7B5_3E0B_11D4_8303_000102284B94: #REF!
Name Z_011E7B5_3E0B_11D4_8303_000102284B94: #REF!
Name Z_EC51EC7F_3C0B_4CF9_8F20_C7FD08174DA8_.wvu.PrintTitles: 'Baumaterialien Matériaux'!$1:$9
Name Z_0111E7B5_3E0B_11D4_8303_000102284B93_.wvu.PrintArea: #REF!
Name Z_0111E7B5_3E0B_11D4_8303_000102284B93_.wvu.PrintArea: #REF!
Name Z_011E7B5_3E0B_11D4_8303_000102284B94: #REF!
Name Z_EC51EC7F_3C0B_4CF9_8F20_C7FD08174DA8_.wvu.PrintArea: 'Transporte Transports'!$B$1:$Z$73
Name Z_0111E7B5_3E0B_11D4_8303_000102284B93_.wvu.PrintArea: #REF!
Name Z_0111E7B5_3E0B_11D4_8303_000102284B93_.wvu.PrintArea: #REF!
Name Z_EC51EC7F_3C0B_4CF9_8F20_C7FD08174DA8_.wvu.PrintArea: 'Erläuterung Explication'!$A$1:$D$18

Sheet Overview
A1: Overview
A3: This sheet transforms KBOB v5 into CSV so that it can be imported into the vyzn platform.
A5: 1. Open Sheet "Consolidated Energy"
A6: 2. Copy all contents to sheet "Import Energy" without formatting (ctrl+shift+v)
A7: 3. Go to sheet "Import Energy"
A8: 4. Delete all rows that are no actual records such as that subtexts, legends or explanations
A9: 5. Select all number columns, then choose Edit->Format->Number->Plain Text
A10: 6. Then choose Edit->Find and replace, then replace "," by ""
A11: 7. Click File->Download->CSV
A12: 8. Run vyzn-import-cli as follows:
A13: npx tsc && node dist/main.js import-products --input data/kbob_2022_v5_energy.csv --url https://dbs-gateway-service-dev.azurewebsites.net --auth data/auth.txt --category none
A14: 9 Repeat the same for the other tabs: transports, baumaterialien, gebäudetechnik, entsorgung
... A22: Be super careful when changing "Consolidated Gebäudtechnik" as it the rows contains gaps, so you can not simply update formulas accross all rows. To be improved.

Sheet RefDimensions
A1: Name | B1: EnumValue
A2: EBF | B2: energyReferenceArea
A3: Masse | B3: mass
A4: Sondenlänge | B4: probeLength
A5: Gerät | B5: device
A6: Kollektorfläche | B6: collectorArea
A7: Speicherkap. | B7: storageCapacity
A8: Max. Leistung | B8: maxPower
A9: Panelfläche | B9: panelArea
A10: Endenergie | B10: finalEnergy
A11: Nutzwärme | B11: usefulHeat
A12: Aushubvolumen | B12: excavationVolume
... A16: Nutzwärme2 | B16: usefulHeat

Sheet MepClassificationAndLifecycle
A1: Key | B1: vyzn.catalogue.ch.minergie.eco.MepClassification | C1: vyzn.catalogue.lifeCycle | E1: backported from KBOB 2022 v5
A2: 31.001 | B2: heatGeneration | C2: 20
A3: 31.002 | B3: heatGeneration | C3: 20
A4: 31.003 | B4: heatGeneration | C4: 20
A5: 31.027 | B5: heatGeneration | C5: 20
A6: 31.021 | B6: heatDistribution | C6: 30
A7: 31.022 | B7: heatDistribution | C7: 30
A8: 31.023 | B8: heatEmission | C8: 30
A9: 31.024 | B9: heatEmission | C9: 30
A10: 31.025 | B10: heatEmission | C10: 30
A11: 31.015 | B11: heatDistribution | C11: 30
A12: 31.016 | B12: geothermalProbe | C12: 40
A13: 31.026 | B13: heatGeneration | C13: 20
... A68: 34.036 | B68: photovoltaicSystem | C68: 30

Sheet Erläuterung  Explication
A1: Ökobilanzdaten im Baubereich KBOB / eco-bau / IPB 2009/1:2016 | D1: Données écobilans dans la construction
A3: Die Ökobilanz-Kennwerte wurden mit aktualisierten Hintergrunddaten (KBOB-Datenbestand 2016, basierend auf dem ecoinvent-Datenbestand v2.2) gerechnet. Neu wird in der pdf-Datei der Indikator "Primärenergie erneuerbar" anstelle des Indikators "Primärenergie, gesamt" aufgeführt. Zudem wurden die Sachbilanzen einzelner Baumaterialien (Durchschnitt und herstellerspezifische), Gebäudetechnikelemente, Energiesysteme und Transportsysteme aktualisiert beziehungsweise neu hinzugefügt. Legende: schwarz: aktualisierte Hintergrunddaten (Sachbilanzdaten unverändert) rot: - Zahlen in rot: Sachbilanz- und Hintergrunddaten bei bestehenden Datensätzen aktualisiert (z.B. ID-Nr. 06.001) - ganze Zeile rot: Datensatz neu in die KBOB-Ökobilanzdaten 2016 aufgenommen (z.B. ID-Nr. 00.001) blau schattiert (nur in der Excel-Datei verfügbar): hersteller- oder herstellerregionenspezifische Datensätze Sortierkriterien für die KBOB-Ökobilanzdaten 2016: 1. Gruppe gemäss vorderem Teil der ID-Nummer (z.B. ID-Nr. 06.xxx) 2. innerhalb Gruppe alphabetisch nach Name in deutscher Sprache | C3: Auf www.kbob.ch > Publikationen > Nachhaltiges Bauen, sind zwei Dateien platziert: Die pdf-Datei «Ökobilanzdaten im Baubereich 2009/1:2016» soll den Planenden den Einstieg in diese Thematik erleichtern. Sie enthält für die Schweiz repräsentative Daten für Baumaterialien und Gebäudetechnik (Herstellung, Entsorgung), Energie sowie Transporte (Betrieb, Fahrzeug, Infrastruktur). Die Excel-Datei «Ökobilanzdaten im Baubereich 2009/1:2016» enthält zusätzlich die Ergebnisse des Indikators "Primärenergie, gesamt", herstellerspezifische Daten sowie die Daten zu den bauspezifischen Entsorgungsprozessen. Die Excel-Datei wird in zwei Versionen angeboten, in denen die Primärenergie in MJ bzw. in kWh gezeigt wird. Ab 2017 wird nur noch die Einheit kWh verwendet. Die Excel-Datei stellt ein Arbeitsinstrument dar.
A4: Gesamtbewertung | B4: Teilbewertung
A5: UBP'13 | B5: Primärenergie (PE) | D5: Treibhausgasemissionen (THG-E)
B6: erneuerbar | C6: nicht erneuerbar (Graue Energie)
A7: Die Umweltbelastungspunkte 2013 (UBP'13) quantifizieren die Umweltbelastungen durch die Nutzung von Energie- und stofflichen Ressourcen, von Land und Süsswasser, durch Emissionen in Luft, Gewässer und Boden, durch die Ablagerung von Rückständen aus der Abfallbehandlung sowie durch Verkehrslärm. | B7: Die erneuerbare Primärenergie quantifiziert den kumulierten Energieaufwand der erneuerbaren Energieträger. Die erneuerbaren Energieträger umfassen Wasserkraft, Holz / Biomasse (ohne Kahlschlag von Primärwäldern), Sonnen-, Wind-, geothermische Energie und Umgebungswärme. Primärenergie erneuerbar und nicht erneuerbar bilden addiert die Primärenergie gesamt. | C7: Die nicht erneuerbare Primärenergie (Graue Energie) quantifiziert den kumulierten Energieaufwand der fossilen und nuklearen Energieträger sowie Holz aus Kahlschlag von Primärwäldern. Primärenergie erneuerbar und nicht erneuerbar bilden addiert die Primärenergie gesamt. | D7: Die Treibhausgasemissionen quantifizieren die kumulierten Wirkungen verschiedener Treibhausgase bezogen auf die Leitsubstanz CO2. Die Treibhauswirkung wird auf Basis der Treibhauspotenziale des 5. Sachstandberichts des IPCC (2013) quantifiziert.
A8: Die Umweltauswirkungen der Teilbewertungen sind in der Gesamtbewertung UBP enthalten. | B8: Diese Kenngrösse ist Teil der Betrachtung gemäss 2000 Watt Gesellschaft. Mit der Summe aus Primärenergie erneuerbar und nicht erneuerbar wird die dem Gebäude zugeführte Energiemenge (Endenergie) gemäss Merkblatt SIA 2031 «Energieausweis für Gebäude» bewertet. | C8: Mit dieser Kenngrösse wird die Bezugsgrösse gemäss Merkblatt SIA 2032 «Graue Energie von Gebäuden» und gemäss Merkblatt SIA 2040 „SIA-Effizienzpfad Gebäude“ bewertet. | D8: Mit dieser Kenngrösse werden die dem Gebäude zugeführte Energiemenge gemäss Merkblatt SIA 2031 «Energieausweis für Gebäude», die Bezugsgrösse gemäss Merkblatt SIA 2032 «Graue Energie von Gebäuden» sowie der Energieverbrauch gemäss Merkblatt SIA 2040 «Effizienzpfad Energie» bewertet.
A9: Die Beurteilung mit der Methode der ökologischen Knappheit zeigt in Umweltbelastungspunkten (UBP'13) ein vollständiges Bild der Umweltauswirkungen auf und basiert auf der Schweizerischen Umweltpolitik. Sie entspricht den Anforderungen eines „true and fair view“ bezüglich Umweltinformationen. | C9: Die nicht erneuerbare Primärenergie (Graue Energie) ist ein im Baubereich etablierter Kennwert. Die Instrumente des Vereins eco-bau (eco-devis, Eco-BKP-Merkblätter) stützen sich für eine gesamtheitliche Beurteilung neben zusätzlichen ökologischen Merkmalen auf diese Teilbewertung ab. | D9: Die in dieser Empfehlung ausgewiesenen Treibhausgasemissionen sind ein Kennwert für die Klimaerwärmung. Sie sind nicht gleichbedeutend mit dem standortgebundenen CO2-Ausstoss, welcher Gegenstand von Zielvereinbarungen zwischen Emittenten und der Eidgenossenschaft im Rahmen des CO2-Gesetzes ist.
A10: Ökobilanzen basieren auf Modellen, die von Wertvorstellungen geprägt sind. Somit sind die Ergebnisse nicht wertfrei. In dieser Empfehlung wurde für alle Materialien dieselbe Modellierungsmethode verwendet. Werden andere Modellierungsmethoden verwendet, können die Ergebnisse anders aussehen. Diese Informationen stammen aus zuverlässigen Quellen. Die Autoren oder ihre Organisationen lehnen jedoch jegliche Haftung für Schäden oder Verluste ab, die durch die Verwendung dieser Angaben entstehen könnten. Die Verantwortung für die Nutzung der Informationen liegt ausschliesslich bei den sie Verwendenden.
A11: Les valeurs relatives aux écobilans ont été calculées sur la base des données fondamentales actuelles (données 2016 de la KBOB fondées sur la base de données ecoinvent v2.2). L'indice «énergie primaire, renouvelable» remplace dorénavant l'indice «énergie primaire, totale» dans le fichier pdf. En outre, les données des écobilans de tous les matériaux (valeur moyenne et indice de fabrication), de la technique du bâtiment, de l'énergie, des transports et des déchets ont été mises à jour ou complétées. Légende: noir: données fondamentales actualisées (bilans inchangés) rouge: - chiffres en rouge: données fondamentales et données des écobilans actualisées pour les groupes de données existants (par ex. no ID 06.001). - toute la cellule en rouge: groupe de données ajouté à la liste (par ex. no ID 00.001) bleu: données spécifiques aux fabricants et aux régions de production (disponibles en format Excel uniquement) Critères de tri pour la liste des écobilans de la KBOB 2016: 1. groupes selon la première partie du no d'identification (par ex. no ID 06.xxx) 2. au sein des groupes, désignations en allemand par ordre alphabétique | C11: A l’adresse www.kbob.ch > Publications > Construction durable, se trouvent deux fichiers: Le fichier pdf «Données des écobilans dans la construction 2009/1:2016» doit permettre aux planificateurs de mieux aborder ce thème. Il contient des données pertinentes pour la Suisse sur les matériaux de construction et la technique du bâtiment (fabrication, élimination) ainsi que sur l'énergie et les transports (exploitation, véhicule, infrastructure). Le fichier excel «Liste Oekobilanzdaten im Baubereich 2009/1:2016» contient en outre des données concernant le fabricant ainsi que des données sur les processus d'élimination dans le domaine de la construction. Il sert d'instrument de travail.
A12: Evaluation globale | B12: Evaluation partielle
A13: UBP'13 | B13: Energie primaire | D13: Emissions de gaz à effet de serre
B14: renouvelable | C14: non renouvelable énergie grise
A15: Les Ecopoints (UBP) 2013 quantifient les charges environnementales résultant de l'utilisation des ressources matérielles et énergétiques, de la terre et de l'eau douce, des émissions dans l'air, l'eau et le sol, du dépôt de résidus découlant du traitement des déchêts ainsi que du bruit de la circulation. | B15: L'énergie primaire renouvelable indique l'énergie cumulée des sources renouvelables. Les sources d'énergie renouvelables comprennent la force hydraulique, le bois/la biomasse (sans déboisement de forêts primaires), l'énergie solaire, éolienne et géothermique ainsi que la chaleur ambiante. L'énergie primaire se compose de l'énergie primaire renouvelable et de l'énergie primaire non renouvelable. | C15: L'énergie non renouvelable (énergie grise) indique l'énergie cumulée de la consommation énergétique fossile et nucléaire ainsi que le bois issu du déboisement de forêts primaires. L'énergie primaire se compose de l'énergie primaire renouvelable et de l'énergie primaire non renouvelable. | D15: L'effet de serre évalue les effets cumulés de différents gaz à effet de serre par rapport à la substance principale qu'est le CO2. L'effet de serre est quantifié sur la base du potentiel de réchauffement évoqué dans le cinquième rapport d'évaluation (2013) du GIEC.
A16: Les répercussions sur l'environnement des évaluations partielles sont prises en compte dans l'évaluation globale UPB. | B16: Cette valeur fait partie des observations contenues dans le projet Société à 2000 watts. La consommation d'énergie du bâtiment (énergie finale) est évaluée conformément à la fiche technique SIA 2031 «Certificat énergétique des bâtiments». | C16: Cette valeur permet d'évaluer l'énergie grise selon la fiche technique SIA 2031 «Energie grise» et la fiche technique SIA 2040 «En route pour l'efficacité énergétique». | D16: Cette valeur permet d'évaluer la consommation totale d'un bâtiment selon la fiche technique SIA 2031 «Certificat énergétique des bâtiments», les émissions de gaz à effet de serre des matériaux selon la fiche technique SIA 2032 «Energie grise des bâtiments» ainsi que la consommation d'énergie selon la fiche technique SIA 2040 «La voie SIA vers l'efficacité énergétique».
A17: L'évaluation fondée sur la méthode de la raréfaction des ressources fournit une récapitulation complète des répercussions sur l'environnement à l'aide d'écopoints (UBP) et se fonde sur la politique environnementale suisse. Elle répond au principe de l'image fidèle («True and Fair View») en ce qui concerne l'information en matière d'environnement. | C17: L'énergie primaire non renouvelable (énergie grise) est une valeur connue dans la construction, elle est indiquée séparément. Plusieurs instruments de l'association eco-bau (eco-devis, feuilles CFC-Eco) s'appuient aujourd'hui, pour une évaluation générale, sur cette évaluation partielle, en plus des caractéristiques écologiques. | D17: L'effet de serre dont il est question dans la présente recommandation est un indice du réchauffement climatique. Il n'est pas comparable avec l'émission de CO2 liée à l'emplacement et dont les objectifs doivent être fixés, en relation avec la loi sur le CO2, dans le cadre d'une négociation entre les émetteurs et la Confédération.
A18: Les éco-bilans se fondent sur des modèles empreints de valeurs. Par conséquent, les résultats ne sont pas neutres. Dans la présente recommandation, tous les matériaux se basent sur la même méthode de modélisation. Si d'autres méthodes sont utilisées, les résultats peuvent différer. Ces informations ont été obtenues de sources jugées fiables. Toutefois, les auteurs ou leurs organisations déclinent toute responsabilité pour des dégâts ou pertes résultant de l'utilisation de celles-ci. Vous êtes entièrement responsables de l'utilisation de ces informations.

Sheet ImportBaumaterialien
A1: Name | B1: ProductKey | C1: Description | D1: Picture | E1: Product sections | F1: Type | G1: SubType | H1: hatchingPattern | I1: vyzn.catalogue.Density | J1: vyzn.catalogue.ch.KBOB2022.UBPTotal | K1: vyzn.catalogue.ch.KBOB2022.UBPProduction | L1: vyzn.catalogue.ch.KBOB2022.UBPDisposal | M1: vyzn.catalogue.ch.KBOB2022.RenewableEnergyTotal | N1: vyzn.catalogue.ch.KBOB2022.RenewableEnergyProduction | O1: vyzn.catalogue.ch.KBOB2022.RenewableEnergyDisposal | P1: vyzn.catalogue.ch.KBOB2022.GreyEnergyTotal | Q1: vyzn.catalogue.ch.KBOB2022.GreyEnergyProduction | R1: vyzn.catalogue.ch.KBOB2022.GreyEnergyDisposal | S1: vyzn.catalogue.ch.KBOB2022.GHGEmissionsTotal | T1: vyzn.catalogue.ch.KBOB2022.GHGEmissionsProduction | U1: vyzn.catalogue.ch.KBOB2022.GHGEmissionsDisposal | V1: vyzn.catalogue.ch.KBOB2022.LCARefUnit | W1: vyzn.catalogue.ch.KBOB2022.LCARefDimension | X1: vyzn.catalogue.ch.KBOB2022.BiogenicCarbon | Y1: KBOB REF | Z1: vyzn.catalogue.SourceENV | AA1: categoryPath | AB1: vyzn.catalogue.lifeCycle
A2: 00.001 Baugrubensicherung, Bohrpfahlwand, gespriesst (KBOB.2016) | B2: 00.001 Baugrubensicherung, Bohrpfahlwand, gespriesst (KBOB.2016) | F2: OTHER_RESOURCE | G2: OTHER_RESOURCE_CONSTRUCTION_MATERIAL_PREPARATION_WORK | J2: 1010000.000000 | K2: 877000.000000 | L2: 130000.000000 | M2: 110.000000 | N2: 101.000000 | O2: 9.570000 | P2: 2280.000000 | Q2: 2020.000000 | R2: 258.000000 | S2: 828.000000 | T2: 778.000000 | U2: 50.200000 | V2: m2 | W2: area | Y2: 00.001 | Z2: KBOB 2016 | AA2: Alle > RESSOURCEN > kbob.admin.ch > KBOB / ecobau / IPB 2009/1:2016 | AB2: 60
A3: 00.002 Baugrubensicherung, Bohrpfahlwand, unverankert (KBOB.2016) | B3: 00.002 Baugrubensicherung, Bohrpfahlwand, unverankert (KBOB.2016) | F3: OTHER_RESOURCE | G3: OTHER_RESOURCE_CONSTRUCTION_MATERIAL_PREPARATION_WORK | J3: 952000.000000 | K3: 822000.000000 | L3: 130000.000000 | M3: 94.300000 | N3: 84.800000 | O3: 9.570000 | P3: 2090.000000 | Q3: 1830.000000 | R3: 258.000000 | S3: 788.000000 | T3: 738.000000 | U3: 50.200000 | V3: m2 | W3: area | Y3: 00.002 | Z3: KBOB 2016 | AA3: Alle > RESSOURCEN > kbob.admin.ch > KBOB / ecobau / IPB 2009/1:2016 | AB3: 60
A4: 00.003 Baugrubensicherung, Bohrpfahlwand, verankert (KBOB.2016) | B4: 00.003 Baugrubensicherung, Bohrpfahlwand, verankert (KBOB.2016) | F4: OTHER_RESOURCE | G4: OTHER_RESOURCE_CONSTRUCTION_MATERIAL_PREPARATION_WORK | J4: 778000.000000 | K4: 692000.000000 | L4: 86200.000000 | M4: 82.800000 | N4: 76.400000 | O4: 6.320000 | P4: 1510.000000 | Q4: 1340.000000 | R4: 170.000000 | S4: 512.000000 | T4: 478.000000 | U4: 33.100000 | V4: m2 | W4: area | Y4: 00.003 | Z4: KBOB 2016 | AA4: Alle > RESSOURCEN > kbob.admin.ch > KBOB / ecobau / IPB 2009/1:2016 | AB4: 60
A5: 00.004 Baugrubensicherung, Nagelwand (KBOB.2016) | B5: 00.004 Baugrubensicherung, Nagelwand (KBOB.2016) | F5: OTHER_RESOURCE | G5: OTHER_RESOURCE_CONSTRUCTION_MATERIAL_PREPARATION_WORK | J5: 171000.000000 | K5: 152000.000000 | L5: 18900.000000 | M5: 17.900000 | N5: 16.600000 | O5: 1.390000 | P5: 324.000000 | Q5: 286.000000 | R5: 37.500000 | S5: 116.000000 | T5: 109.000000 | U5: 7.280000 | V5: m2 | W5: area | Y5: 00.004 | Z5: KBOB 2016 | AA5: Alle > RESSOURCEN > kbob.admin.ch > KBOB / ecobau / IPB 2009/1:2016 | AB5: 60
A6: 00.005 Baugrubensicherung, Rühlwand, auskragend (KBOB.2016) | B6: 00.005 Baugrubensicherung, Rühlwand, auskragend (KBOB.2016) | F6: OTHER_RESOURCE | G6: OTHER_RESOURCE_CONSTRUCTION_MATERIAL_PREPARATION_WORK | J6: 332000.000000 | K6: 302000.000000 | L6: 30100.000000 | M6: 108.000000 | N6: 106.000000 | O6: 2.200000 | P6: 934.000000 | Q6: 874.000000 | R6: 59.500000 | S6: 266.000000 | T6: 254.000000 | U6: 11.600000 | V6: m2 | W6: area | Y6: 00.005 | Z6: KBOB 2016 | AA6: Alle > RESSOURCEN > kbob.admin.ch > KBOB / ecobau / IPB 2009/1:2016 | AB6: 60
A7: 00.006 Baugrubensicherung, Rühlwand, gespriesst (KBOB.2016) | B7: 00.006 Baugrubensicherung, Rühlwand, gespriesst (KBOB.2016) | F7: OTHER_RESOURCE | G7: OTHER_RESOURCE_CONSTRUCTION_MATERIAL_PREPARATION_WORK | J7: 240000.000000 | K7: 222000.000000 | L7: 17800.000000 | M7: 46.700000 | N7: 45.400000 | O7: 1.310000 | P7: 677.000000 | Q7: 642.000000 | R7: 35.200000 | S7: 184.000000 | T7: 177.000000 | U7: 6.840000 | V7: m2 | W7: area | Y7: 00.006 | Z7: KBOB 2016 | AA7: Alle > RESSOURCEN > kbob.admin.ch > KBOB / ecobau / IPB 2009/1:2016 | AB7: 60
A8: 00.007 Baugrubensicherung, Rühlwand, verankert (KBOB.2016) | B8: 00.007 Baugrubensicherung, Rühlwand, verankert (KBOB.2016) | F8: OTHER_RESOURCE | G8: OTHER_RESOURCE_CONSTRUCTION_MATERIAL_PREPARATION_WORK | J8: 259000.000000 | K8: 238000.000000 | L8: 20600.000000 | M8: 43.900000 | N8: 42.400000 | O8: 1.510000 | P8: 681.000000 | Q8: 640.000000 | R8: 40.700000 | S8: 192.000000 | T8: 184.000000 | U8: 7.900000 | V8: m2 | W8: area | Y8: 00.007 | Z8: KBOB 2016 | AA8: Alle > RESSOURCEN > kbob.admin.ch > KBOB / ecobau / IPB 2009/1:2016 | AB8: 60
A9: 00.008 Baugrubensicherung, Schlitzwand, 400 mm (KBOB.2016) | B9: 00.008 Baugrubensicherung, Schlitzwand, 400 mm (KBOB.2016) | F9: OTHER_RESOURCE | G9: OTHER_RESOURCE_CONSTRUCTION_MATERIAL_PREPARATION_WORK | J9: 648000.000000 | K9: 583000.000000 | L9: 65500.000000 | M9: 73.300000 | N9: 68.600000 | O9: 4.760000 | P9: 1250.000000 | Q9: 1120.000000 | R9: 130.000000 | S9: 407.000000 | T9: 382.000000 | U9: 25.200000 | V9: m2 | W9: area | Y9: 00.008 | Z9: KBOB 2016 | AA9: Alle > RESSOURCEN > kbob.admin.ch > KBOB / ecobau / IPB 2009/1:2016 | AB9: 60
A10: 00.009 Baugrubensicherung, Schlitzwand, 800 mm (KBOB.2016) | B10: 00.009 Baugrubensicherung, Schlitzwand, 800 mm (KBOB.2016) | F10: OTHER_RESOURCE | G10: OTHER_RESOURCE_CONSTRUCTION_MATERIAL_PREPARATION_WORK | J10: 1230000.000000 | K10: 1100000.000000 | L10: 129000.000000 | M10: 136.000000 | N10: 126.000000 | O10: 9.430000 | P10: 2270.000000 | Q10: 2010.000000 | R10: 256.000000 | S10: 777.000000 | T10: 728.000000 | U10: 49.600000 | V10: m2 | W10: area | Y10: 00.009 | Z10: KBOB 2016 | AA10: Alle > RESSOURCEN > kbob.admin.ch > KBOB / ecobau / IPB 2009/1:2016 | AB10: 60
A11: 00.010 Baugrubensicherung, Spundwand, auskragend (KBOB.2016) | B11: 00.010 Baugrubensicherung, Spundwand, auskragend (KBOB.2016) | F11: OTHER_RESOURCE | G11: OTHER_RESOURCE_CONSTRUCTION_MATERIAL_PREPARATION_WORK | J11: 228000.000000 | K11: 228000.000000 | L11: 0.000000 | M11: 46.200000 | N11: 46.200000 | O11: 0.000000 | P11: 747.000000 | Q11: 747.000000 | R11: 0.000000 | S11: 163.000000 | T11: 163.000000 | U11: 0.000000 | V11: m2 | W11: area | Y11: 00.010 | Z11: KBOB 2016 | AA11: Alle > RESSOURCEN > kbob.admin.ch > KBOB / ecobau / IPB 2009/1:2016 | AB11: 60
A12: 00.011 Baugrubensicherung, Spundwand, gespriesst (KBOB.2016) | B12: 00.011 Baugrubensicherung, Spundwand, gespriesst (KBOB.2016) | F12: OTHER_RESOURCE | G12: OTHER_RESOURCE_CONSTRUCTION_MATERIAL_PREPARATION_WORK | J12: 129000.000000 | K12: 129000.000000 | L12: 0.000000 | M12: 25.300000 | N12: 25.300000 | O12: 0.000000 | P12: 421.000000 | Q12: 421.000000 | R12: 0.000000 | S12: 92.300000 | T12: 92.300000 | U12: 0.000000 | V12: m2 | W12: area | Y12: 00.011 | Z12: KBOB 2016 | AA12: Alle > RESSOURCEN > kbob.admin.ch > KBOB / ecobau / IPB 2009/1:2016 | AB12: 60
A13: 00.012 Baugrubensicherung, Spundwand, verankert (KBOB.2016) | B13: 00.012 Baugrubensicherung, Spundwand, verankert (KBOB.2016) | F13: OTHER_RESOURCE | G13: OTHER_RESOURCE_CONSTRUCTION_MATERIAL_PREPARATION_WORK | J13: 255000.000000 | K13: 255000.000000 | L13: 0.000000 | M13: 55.300000 | N13: 55.300000 | O13: 0.000000 | P13: 813.000000 | Q13: 813.000000 | R13: 0.000000 | S13: 181.000000 | T13: 181.000000 | U13: 0.000000 | V13: m2 | W13: area | Y13: 00.012 | Z13: KBOB 2016 | AA13: Alle > RESSOURCEN > kbob.admin.ch > KBOB / ecobau / IPB 2009/1:2016 | AB13: 60
... A25: 00.024 Wasserhaltung, Pumphöhe 10 m (KBOB.2016) | B25: 00.024 Wasserhaltung, Pumphöhe 10 m (KBOB.2016) | F25: OTHER_RESOURCE | G25: OTHER_RESOURCE_CONSTRUCTION_MATERIAL_PREPARATION_WORK | J25: 22.500000 | K25: 22.500000 | L25: 0.000000 | M25: 0.030900 | N25: 0.030900 | O25: 0.000000 | P25: 0.159000 | Q25: 0.159000 | R25: 0.000000 | S25: 0.006560 | T25: 0.006560 | U25: 0.000000 | V25: m3 | W25: volume | Y25: 00.024 | Z25: KBOB 2016 | AA25: Alle > RESSOURCEN > kbob.admin.ch > KBOB / ecobau / IPB 2009/1:2016 | AB25: 60

Sheet ConsolidatedBaumaterialien
A1: Name | B1: ProductKey | C1: Description | D1: Picture | E1: Product sections | F1: Type | G1: SubType | H1: hatchingPattern | I1: vyzn.catalogue.Density | J1: vyzn.catalogue.ch.KBOB2022.UBPTotal | K1: vyzn.catalogue.ch.KBOB2022.UBPProduction | L1: vyzn.catalogue.ch.KBOB2022.UBPDisposal | M1: vyzn.catalogue.ch.KBOB2022.RenewableEnergyTotal | N1: vyzn.catalogue.ch.KBOB2022.RenewableEnergyProduction | O1: vyzn.catalogue.ch.KBOB2022.RenewableEnergyDisposal | P1: vyzn.catalogue.ch.KBOB2022.GreyEnergyTotal | Q1: vyzn.catalogue.ch.KBOB2022.GreyEnergyProduction | R1: vyzn.catalogue.ch.KBOB2022.GreyEnergyDisposal | S1: vyzn.catalogue.ch.KBOB2022.GHGEmissionsTotal | T1: vyzn.catalogue.ch.KBOB2022.GHGEmissionsProduction | U1: vyzn.catalogue.ch.KBOB2022.GHGEmissionsDisposal | V1: vyzn.catalogue.ch.KBOB2022.LCARefUnit | W1: vyzn.catalogue.ch.KBOB2022.LCARefDimension | X1: vyzn.catalogue.ch.KBOB2022.BiogenicCarbon | Y1: KBOB REF | Z1: vyzn.catalogue.SourceENV | AA1: categoryPath | AB1: vyzn.catalogue.lifeCycle
A2: ='Baumaterialien Matériaux'!A11 & " " & 'Baumaterialien Matériaux'!B11 & " (KBOB.2016)" -> 00.001 Baugrubensicherung, Bohrpfahlwand, gespriesst (KBOB.2016) | B2: =A2 -> 00.001 Baugrubensicherung, Bohrpfahlwand, gespriesst (KBOB.2016) | F2: OTHER_RESOURCE | G2: =SWITCH(LEFT(A2,2), "00", "OTHER_RESOURCE_CONSTRUCTION_MATERIAL_PREPARATION_WORK", "") -> OTHER_RESOURCE_CONSTRUCTION_MATERIAL_PREPARATION_WORK | J2: ='Baumaterialien Matériaux'!G11 -> 1010000 | K2: ='Baumaterialien Matériaux'!H11 -> 877000 | L2: ='Baumaterialien Matériaux'!I11 -> 130000 | M2: ='Baumaterialien Matériaux'!M11 -> 110 | N2: ='Baumaterialien Matériaux'!N11 -> 101 | O2: ='Baumaterialien Matériaux'!O11 -> 9.57 | P2: ='Baumaterialien Matériaux'!P11 -> 2280 | Q2: ='Baumaterialien Matériaux'!Q11 -> 2020 | R2: ='Baumaterialien Matériaux'!R11 -> 258 | S2: ='Baumaterialien Matériaux'!S11 -> 828 | T2: ='Baumaterialien Matériaux'!T11 -> 778 | U2: ='Baumaterialien Matériaux'!U11 -> 50.2 | V2: ='Baumaterialien Matériaux'!F11 -> m2 | W2: =SWITCH('Baumaterialien Matériaux'!F11, "m", "probeLength", "m2", "area", "m3", "volume", "kg", "mass", "Stk.", "device") -> area | X2: ='Baumaterialien Matériaux'!AC11 | Y2: =LEFT(A2,6) -> 00.001 | Z2: KBOB 2016 | AA2: ="Alle > " & SWITCH(F2, "COMPONENT","BAUTEILE", "OTHER_RESOURCE", "RESSOURCEN", "BUILDING_TECHNOLOGY", "GEBÄUDETECHNIK", "MATERIAL", "MATERIALIEN") & " > kbob.admin.ch > KBOB / ecobau / IPB 2009/1:2016" -> Alle > RESSOURCEN > kbob.admin.ch > KBOB / ecobau / IPB 2009/1:2016 | AB2: 60
A3: ='Baumaterialien Matériaux'!A12 & " " & 'Baumaterialien Matériaux'!B12 & " (KBOB.2016)" -> 00.002 Baugrubensicherung, Bohrpfahlwand, unverankert (KBOB.2016) | B3: =A3 -> 00.002 Baugrubensicherung, Bohrpfahlwand, unverankert (KBOB.2016) | F3: OTHER_RESOURCE | G3: =SWITCH(LEFT(A3,2), "00", "OTHER_RESOURCE_CONSTRUCTION_MATERIAL_PREPARATION_WORK", "") -> OTHER_RESOURCE_CONSTRUCTION_MATERIAL_PREPARATION_WORK | J3: ='Baumaterialien Matériaux'!G12 -> 952000 | K3: ='Baumaterialien Matériaux'!H12 -> 822000 | L3: ='Baumaterialien Matériaux'!I12 -> 130000 | M3: ='Baumaterialien Matériaux'!M12 -> 94.3 | N3: ='Baumaterialien Matériaux'!N12 -> 84.8 | O3: ='Baumaterialien Matériaux'!O12 -> 9.57 | P3: ='Baumaterialien Matériaux'!P12 -> 2090 | Q3: ='Baumaterialien Matériaux'!Q12 -> 1830 | R3: ='Baumaterialien Matériaux'!R12 -> 258 | S3: ='Baumaterialien Matériaux'!S12 -> 788 | T3: ='Baumaterialien Matériaux'!T12 -> 738 | U3: ='Baumaterialien Matériaux'!U12 -> 50.2 | V3: ='Baumaterialien Matériaux'!F12 -> m2 | W3: =SWITCH('Baumaterialien Matériaux'!F12, "m", "probeLength", "m2", "area", "m3", "volume", "kg", "mass", "Stk.", "device") -> area | X3: ='Baumaterialien Matériaux'!AC12 | Y3: =LEFT(A3,6) -> 00.002 | Z3: KBOB 2016 | AA3: ="Alle > " & SWITCH(F3, "COMPONENT","BAUTEILE", "OTHER_RESOURCE", "RESSOURCEN", "BUILDING_TECHNOLOGY", "GEBÄUDETECHNIK", "MATERIAL", "MATERIALIEN") & " > kbob.admin.ch > KBOB / ecobau / IPB 2009/1:2016" -> Alle > RESSOURCEN > kbob.admin.ch > KBOB / ecobau / IPB 2009/1:2016 | AB3: 60
A4: ='Baumaterialien Matériaux'!A13 & " " & 'Baumaterialien Matériaux'!B13 & " (KBOB.2016)" -> 00.003 Baugrubensicherung, Bohrpfahlwand, verankert (KBOB.2016) | B4: =A4 -> 00.003 Baugrubensicherung, Bohrpfahlwand, verankert (KBOB.2016) | F4: OTHER_RESOURCE | G4: =SWITCH(LEFT(A4,2), "00", "OTHER_RESOURCE_CONSTRUCTION_MATERIAL_PREPARATION_WORK", "") -> OTHER_RESOURCE_CONSTRUCTION_MATERIAL_PREPARATION_WORK | J4: ='Baumaterialien Matériaux'!G13 -> 778000 | K4: ='Baumaterialien Matériaux'!H13 -> 692000 | L4: ='Baumaterialien Matériaux'!I13 -> 86200 | M4: ='Baumaterialien Matériaux'!M13 -> 82.8 | N4: ='Baumaterialien Matériaux'!N13 -> 76.4 | O4: ='Baumaterialien Matériaux'!O13 -> 6.32 | P4: ='Baumaterialien Matériaux'!P13 -> 1510 | Q4: ='Baumaterialien Matériaux'!Q13 -> 1340 | R4: ='Baumaterialien Matériaux'!R13 -> 170 | S4: ='Baumaterialien Matériaux'!S13 -> 512 | T4: ='Baumaterialien Matériaux'!T13 -> 478 | U4: ='Baumaterialien Matériaux'!U13 -> 33.1 | V4: ='Baumaterialien Matériaux'!F13 -> m2 | W4: =SWITCH('Baumaterialien Matériaux'!F13, "m", "probeLength", "m2", "area", "m3", "volume", "kg", "mass", "Stk.", "device") -> area | X4: ='Baumaterialien Matériaux'!AC13 | Y4: =LEFT(A4,6) -> 00.003 | Z4: KBOB 2016 | AA4: ="Alle > " & SWITCH(F4, "COMPONENT","BAUTEILE", "OTHER_RESOURCE", "RESSOURCEN", "BUILDING_TECHNOLOGY", "GEBÄUDETECHNIK", "MATERIAL", "MATERIALIEN") & " > kbob.admin.ch > KBOB / ecobau / IPB 2009/1:2016" -> Alle > RESSOURCEN > kbob.admin.ch > KBOB / ecobau / IPB 2009/1:2016 | AB4: 60
A5: ='Baumaterialien Matériaux'!A14 & " " & 'Baumaterialien Matériaux'!B14 & " (KBOB.2016)" -> 00.004 Baugrubensicherung, Nagelwand (KBOB.2016) | B5: =A5 -> 00.004 Baugrubensicherung, Nagelwand (KBOB.2016) | F5: OTHER_RESOURCE | G5: =SWITCH(LEFT(A5,2), "00", "OTHER_RESOURCE_CONSTRUCTION_MATERIAL_PREPARATION_WORK", "") -> OTHER_RESOURCE_CONSTRUCTION_MATERIAL_PREPARATION_WORK | J5: ='Baumaterialien Matériaux'!G14 -> 171000 | K5: ='Baumaterialien Matériaux'!H14 -> 152000 | L5: ='Baumaterialien Matériaux'!I14 -> 18900 | M5: ='Baumaterialien Matériaux'!M14 -> 17.9 | N5: ='Baumaterialien Matériaux'!N14 -> 16.6 | O5: ='Baumaterialien Matériaux'!O14 -> 1.39 | P5: ='Baumaterialien Matériaux'!P14 -> 324 | Q5: ='Baumaterialien Matériaux'!Q14 -> 286 | R5: ='Baumaterialien Matériaux'!R14 -> 37.5 | S5: ='Baumaterialien Matériaux'!S14 -> 116 | T5: ='Baumaterialien Matériaux'!T14 -> 109 | U5: ='Baumaterialien Matériaux'!U14 -> 7.28 | V5: ='Baumaterialien Matériaux'!F14 -> m2 | W5: =SWITCH('Baumaterialien Matériaux'!F14, "m", "probeLength", "m2", "area", "m3", "volume", "kg", "mass", "Stk.", "device") -> area | X5: ='Baumaterialien Matériaux'!AC14 | Y5: =LEFT(A5,6) -> 00.004 | Z5: KBOB 2016 | AA5: ="Alle > " & SWITCH(F5, "COMPONENT","BAUTEILE", "OTHER_RESOURCE", "RESSOURCEN", "BUILDING_TECHNOLOGY", "GEBÄUDETECHNIK", "MATERIAL", "MATERIALIEN") & " > kbob.admin.ch > KBOB / ecobau / IPB 2009/1:2016" -> Alle > RESSOURCEN > kbob.admin.ch > KBOB / ecobau / IPB 2009/1:2016 | AB5: 60
A6: ='Baumaterialien Matériaux'!A15 & " " & 'Baumaterialien Matériaux'!B15 & " (KBOB.2016)" -> 00.005 Baugrubensicherung, Rühlwand, auskragend (KBOB.2016) | B6: =A6 -> 00.005 Baugrubensicherung, Rühlwand, auskragend (KBOB.2016) | F6: OTHER_RESOURCE | G6: =SWITCH(LEFT(A6,2), "00", "OTHER_RESOURCE_CONSTRUCTION_MATERIAL_PREPARATION_WORK", "") -> OTHER_RESOURCE_CONSTRUCTION_MATERIAL_PREPARATION_WORK | J6: ='Baumaterialien Matériaux'!G15 -> 332000 | K6: ='Baumaterialien Matériaux'!H15 -> 302000 | L6: ='Baumaterialien Matériaux'!I15 -> 30100 | M6: ='Baumaterialien Matériaux'!M15 -> 108 | N6: ='Baumaterialien Matériaux'!N15 -> 106 | O6: ='Baumaterialien Matériaux'!O15 -> 2.2 | P6: ='Baumaterialien Matériaux'!P15 -> 934 | Q6: ='Baumaterialien Matériaux'!Q15 -> 874 | R6: ='Baumaterialien Matériaux'!R15 -> 59.5 | S6: ='Baumaterialien Matériaux'!S15 -> 266 | T6: ='Baumaterialien Matériaux'!T15 -> 254 | U6: ='Baumaterialien Matériaux'!U15 -> 11.6 | V6: ='Baumaterialien Matériaux'!F15 -> m2 | W6: =SWITCH('Baumaterialien Matériaux'!F15, "m", "probeLength", "m2", "area", "m3", "volume", "kg", "mass", "Stk.", "device") -> area | X6: ='Baumaterialien Matériaux'!AC15 | Y6: =LEFT(A6,6) -> 00.005 | Z6: KBOB 2016 | AA6: ="Alle > " & SWITCH(F6, "COMPONENT","BAUTEILE", "OTHER_RESOURCE", "RESSOURCEN", "BUILDING_TECHNOLOGY", "GEBÄUDETECHNIK", "MATERIAL", "MATERIALIEN") & " > kbob.admin.ch > KBOB / ecobau / IPB 2009/1:2016" -> Alle > RESSOURCEN > kbob.admin.ch > KBOB / ecobau / IPB 2009/1:2016 | AB6: 60
A7: ='Baumaterialien Matériaux'!A16 & " " & 'Baumaterialien Matériaux'!B16 & " (KBOB.2016)" -> 00.006 Baugrubensicherung, Rühlwand, gespriesst (KBOB.2016) | B7: =A7 -> 00.006 Baugrubensicherung, Rühlwand, gespriesst (KBOB.2016) | F7: OTHER_RESOURCE | G7: =SWITCH(LEFT(A7,2), "00", "OTHER_RESOURCE_CONSTRUCTION_MATERIAL_PREPARATION_WORK", "") -> OTHER_RESOURCE_CONSTRUCTION_MATERIAL_PREPARATION_WORK | J7: ='Baumaterialien Matériaux'!G16 -> 240000 | K7: ='Baumaterialien Matériaux'!H16 -> 222000 | L7: ='Baumaterialien Matériaux'!I16 -> 17800 | M7: ='Baumaterialien Matériaux'!M16 -> 46.7 | N7: ='Baumaterialien Matériaux'!N16 -> 45.4 | O7: ='Baumaterialien Matériaux'!O16 -> 1.31 | P7: ='Baumaterialien Matériaux'!P16 -> 677 | Q7: ='Baumaterialien Matériaux'!Q16 -> 642 | R7: ='Baumaterialien Matériaux'!R16 -> 35.2 | S7: ='Baumaterialien Matériaux'!S16 -> 184 | T7: ='Baumaterialien Matériaux'!T16 -> 177 | U7: ='Baumaterialien Matériaux'!U16 -> 6.84 | V7: ='Baumaterialien Matériaux'!F16 -> m2 | W7: =SWITCH('Baumaterialien Matériaux'!F16, "m", "probeLength", "m2", "area", "m3", "volume", "kg", "mass", "Stk.", "device") -> area | X7: ='Baumaterialien Matériaux'!AC16 | Y7: =LEFT(A7,6) -> 00.006 | Z7: KBOB 2016 | AA7: ="Alle > " & SWITCH(F7, "COMPONENT","BAUTEILE", "OTHER_RESOURCE", "RESSOURCEN", "BUILDING_TECHNOLOGY", "GEBÄUDETECHNIK", "MATERIAL", "MATERIALIEN") & " > kbob.admin.ch > KBOB / ecobau / IPB 2009/1:2016" -> Alle > RESSOURCEN > kbob.admin.ch > KBOB / ecobau / IPB 2009/1:2016 | AB7: 60
A8: ='Baumaterialien Matériaux'!A17 & " " & 'Baumaterialien Matériaux'!B17 & " (KBOB.2016)" -> 00.007 Baugrubensicherung, Rühlwand, verankert (KBOB.2016) | B8: =A8 -> 00.007 Baugrubensicherung, Rühlwand, verankert (KBOB.2016) | F8: OTHER_RESOURCE | G8: =SWITCH(LEFT(A8,2), "00", "OTHER_RESOURCE_CONSTRUCTION_MATERIAL_PREPARATION_WORK", "") -> OTHER_RESOURCE_CONSTRUCTION_MATERIAL_PREPARATION_WORK | J8: ='Baumaterialien Matériaux'!G17 -> 259000 | K8: ='Baumaterialien Matériaux'!H17 -> 238000 | L8: ='Baumaterialien Matériaux'!I17 -> 20600 | M8: ='Baumaterialien Matériaux'!M17 -> 43.9 | N8: ='Baumaterialien Matériaux'!N17 -> 42.4 | O8: ='Baumaterialien Matériaux'!O17 -> 1.51 | P8: ='Baumaterialien Matériaux'!P17 -> 681 | Q8: ='Baumaterialien Matériaux'!Q17 -> 640 | R8: ='Baumaterialien Matériaux'!R17 -> 40.7 | S8: ='Baumaterialien Matériaux'!S17 -> 192 | T8: ='Baumaterialien Matériaux'!T17 -> 184 | U8: ='Baumaterialien Matériaux'!U17 -> 7.9 | V8: ='Baumaterialien Matériaux'!F17 -> m2 | W8: =SWITCH('Baumaterialien Matériaux'!F17, "m", "probeLength", "m2", "area", "m3", "volume", "kg", "mass", "Stk.", "device") -> area | X8: ='Baumaterialien Matériaux'!AC17 | Y8: =LEFT(A8,6) -> 00.007 | Z8: KBOB 2016 | AA8: ="Alle > " & SWITCH(F8, "COMPONENT","BAUTEILE", "OTHER_RESOURCE", "RESSOURCEN", "BUILDING_TECHNOLOGY", "GEBÄUDETECHNIK", "MATERIAL", "MATERIALIEN") & " > kbob.admin.ch > KBOB / ecobau / IPB 2009/1:2016" -> Alle > RESSOURCEN > kbob.admin.ch > KBOB / ecobau / IPB 2009/1:2016 | AB8: 60
A9: ='Baumaterialien Matériaux'!A18 & " " & 'Baumaterialien Matériaux'!B18 & " (KBOB.2016)" -> 00.008 Baugrubensicherung, Schlitzwand, 400 mm (KBOB.2016) | B9: =A9 -> 00.008 Baugrubensicherung, Schlitzwand, 400 mm (KBOB.2016) | F9: OTHER_RESOURCE | G9: =SWITCH(LEFT(A9,2), "00", "OTHER_RESOURCE_CONSTRUCTION_MATERIAL_PREPARATION_WORK", "") -> OTHER_RESOURCE_CONSTRUCTION_MATERIAL_PREPARATION_WORK | J9: ='Baumaterialien Matériaux'!G18 -> 648000 | K9: ='Baumaterialien Matériaux'!H18 -> 583000 | L9: ='Baumaterialien Matériaux'!I18 -> 65500 | M9: ='Baumaterialien Matériaux'!M18 -> 73.3 | N9: ='Baumaterialien Matériaux'!N18 -> 68.6 | O9: ='Baumaterialien Matériaux'!O18 -> 4.76 | P9: ='Baumaterialien Matériaux'!P18 -> 1250 | Q9: ='Baumaterialien Matériaux'!Q18 -> 1120 | R9: ='Baumaterialien Matériaux'!R18 -> 130 | S9: ='Baumaterialien Matériaux'!S18 -> 407 | T9: ='Baumaterialien Matériaux'!T18 -> 382 | U9: ='Baumaterialien Matériaux'!U18 -> 25.2 | V9: ='Baumaterialien Matériaux'!F18 -> m2 | W9: =SWITCH('Baumaterialien Matériaux'!F18, "m", "probeLength", "m2", "area", "m3", "volume", "kg", "mass", "Stk.", "device") -> area | X9: ='Baumaterialien Matériaux'!AC18 | Y9: =LEFT(A9,6) -> 00.008 | Z9: KBOB 2016 | AA9: ="Alle > " & SWITCH(F9, "COMPONENT","BAUTEILE", "OTHER_RESOURCE", "RESSOURCEN", "BUILDING_TECHNOLOGY", "GEBÄUDETECHNIK", "MATERIAL", "MATERIALIEN") & " > kbob.admin.ch > KBOB / ecobau / IPB 2009/1:2016" -> Alle > RESSOURCEN > kbob.admin.ch > KBOB / ecobau / IPB 2009/1:2016 | AB9: 60
A10: ='Baumaterialien Matériaux'!A19 & " " & 'Baumaterialien Matériaux'!B19 & " (KBOB.2016)" -> 00.009 Baugrubensicherung, Schlitzwand, 800 mm (KBOB.2016) | B10: =A10 -> 00.009 Baugrubensicherung, Schlitzwand, 800 mm (KBOB.2016) | F10: OTHER_RESOURCE | G10: =SWITCH(LEFT(A10,2), "00", "OTHER_RESOURCE_CONSTRUCTION_MATERIAL_PREPARATION_WORK", "") -> OTHER_RESOURCE_CONSTRUCTION_MATERIAL_PREPARATION_WORK | J10: ='Baumaterialien Matériaux'!G19 -> 1230000 | K10: ='Baumaterialien Matériaux'!H19 -> 1100000 | L10: ='Baumaterialien Matériaux'!I19 -> 129000 | M10: ='Baumaterialien Matériaux'!M19 -> 136 | N10: ='Baumaterialien Matériaux'!N19 -> 126 | O10: ='Baumaterialien Matériaux'!O19 -> 9.43 | P10: ='Baumaterialien Matériaux'!P19 -> 2270 | Q10: ='Baumaterialien Matériaux'!Q19 -> 2010 | R10: ='Baumaterialien Matériaux'!R19 -> 256 | S10: ='Baumaterialien Matériaux'!S19 -> 777 | T10: ='Baumaterialien Matériaux'!T19 -> 728 | U10: ='Baumaterialien Matériaux'!U19 -> 49.6 | V10: ='Baumaterialien Matériaux'!F19 -> m2 | W10: =SWITCH('Baumaterialien Matériaux'!F19, "m", "probeLength", "m2", "area", "m3", "volume", "kg", "mass", "Stk.", "device") -> area | X10: ='Baumaterialien Matériaux'!AC19 | Y10: =LEFT(A10,6) -> 00.009 | Z10: KBOB 2016 | AA10: ="Alle > " & SWITCH(F10, "COMPONENT","BAUTEILE", "OTHER_RESOURCE", "RESSOURCEN", "BUILDING_TECHNOLOGY", "GEBÄUDETECHNIK", "MATERIAL", "MATERIALIEN") & " > kbob.admin.ch > KBOB / ecobau / IPB 2009/1:2016" -> Alle > RESSOURCEN > kbob.admin.ch > KBOB / ecobau / IPB 2009/1:2016 | AB10: 60
A11: ='Baumaterialien Matériaux'!A20 & " " & 'Baumaterialien Matériaux'!B20 & " (KBOB.2016)" -> 00.010 Baugrubensicherung, Spundwand, auskragend (KBOB.2016) | B11: =A11 -> 00.010 Baugrubensicherung, Spundwand, auskragend (KBOB.2016) | F11: OTHER_RESOURCE | G11: =SWITCH(LEFT(A11,2), "00", "OTHER_RESOURCE_CONSTRUCTION_MATERIAL_PREPARATION_WORK", "") -> OTHER_RESOURCE_CONSTRUCTION_MATERIAL_PREPARATION_WORK | J11: ='Baumaterialien Matériaux'!G20 -> 228000 | K11: ='Baumaterialien Matériaux'!H20 -> 228000 | L11: ='Baumaterialien Matériaux'!I20 -> 0 | M11: ='Baumaterialien Matériaux'!M20 -> 46.2 | N11: ='Baumaterialien Matériaux'!N20 -> 46.2 | O11: ='Baumaterialien Matériaux'!O20 -> 0 | P11: ='Baumaterialien Matériaux'!P20 -> 747 | Q11: ='Baumaterialien Matériaux'!Q20 -> 747 | R11: ='Baumaterialien Matériaux'!R20 -> 0 | S11: ='Baumaterialien Matériaux'!S20 -> 163 | T11: ='Baumaterialien Matériaux'!T20 -> 163 | U11: ='Baumaterialien Matériaux'!U20 -> 0 | V11: ='Baumaterialien Matériaux'!F20 -> m2 | W11: =SWITCH('Baumaterialien Matériaux'!F20, "m", "probeLength", "m2", "area", "m3", "volume", "kg", "mass", "Stk.", "device") -> area | X11: ='Baumaterialien Matériaux'!AC20 | Y11: =LEFT(A11,6) -> 00.010 | Z11: KBOB 2016 | AA11: ="Alle > " & SWITCH(F11, "COMPONENT","BAUTEILE", "OTHER_RESOURCE", "RESSOURCEN", "BUILDING_TECHNOLOGY", "GEBÄUDETECHNIK", "MATERIAL", "MATERIALIEN") & " > kbob.admin.ch > KBOB / ecobau / IPB 2009/1:2016" -> Alle > RESSOURCEN > kbob.admin.ch > KBOB / ecobau / IPB 2009/1:2016 | AB11: 60
A12: ='Baumaterialien Matériaux'!A21 & " " & 'Baumaterialien Matériaux'!B21 & " (KBOB.2016)" -> 00.011 Baugrubensicherung, Spundwand, gespriesst (KBOB.2016) | B12: =A12 -> 00.011 Baugrubensicherung, Spundwand, gespriesst (KBOB.2016) | F12: OTHER_RESOURCE | G12: =SWITCH(LEFT(A12,2), "00", "OTHER_RESOURCE_CONSTRUCTION_MATERIAL_PREPARATION_WORK", "") -> OTHER_RESOURCE_CONSTRUCTION_MATERIAL_PREPARATION_WORK | J12: ='Baumaterialien Matériaux'!G21 -> 129000 | K12: ='Baumaterialien Matériaux'!H21 -> 129000 | L12: ='Baumaterialien Matériaux'!I21 -> 0 | M12: ='Baumaterialien Matériaux'!M21 -> 25.3 | N12: ='Baumaterialien Matériaux'!N21 -> 25.3 | O12: ='Baumaterialien Matériaux'!O21 -> 0 | P12: ='Baumaterialien Matériaux'!P21 -> 421 | Q12: ='Baumaterialien Matériaux'!Q21 -> 421 | R12: ='Baumaterialien Matériaux'!R21 -> 0 | S12: ='Baumaterialien Matériaux'!S21 -> 92.3 | T12: ='Baumaterialien Matériaux'!T21 -> 92.3 | U12: ='Baumaterialien Matériaux'!U21 -> 0 | V12: ='Baumaterialien Matériaux'!F21 -> m2 | W12: =SWITCH('Baumaterialien Matériaux'!F21, "m", "probeLength", "m2", "area", "m3", "volume", "kg", "mass", "Stk.", "device") -> area | X12: ='Baumaterialien Matériaux'!AC21 | Y12: =LEFT(A12,6) -> 00.011 | Z12: KBOB 2016 | AA12: ="Alle > " & SWITCH(F12, "COMPONENT","BAUTEILE", "OTHER_RESOURCE", "RESSOURCEN", "BUILDING_TECHNOLOGY", "GEBÄUDETECHNIK", "MATERIAL", "MATERIALIEN") & " > kbob.admin.ch > KBOB / ecobau / IPB 2009/1:2016" -> Alle > RESSOURCEN > kbob.admin.ch > KBOB / ecobau / IPB 2009/1:2016 | AB12: 60
A13: ='Baumaterialien Matériaux'!A22 & " " & 'Baumaterialien Matériaux'!B22 & " (KBOB.2016)" -> 00.012 Baugrubensicherung, Spundwand, verankert (KBOB.2016) | B13: =A13 -> 00.012 Baugrubensicherung, Spundwand, verankert (KBOB.2016) | F13: OTHER_RESOURCE | G13: =SWITCH(LEFT(A13,2), "00", "OTHER_RESOURCE_CONSTRUCTION_MATERIAL_PREPARATION_WORK", "") -> OTHER_RESOURCE_CONSTRUCTION_MATERIAL_PREPARATION_WORK | J13: ='Baumaterialien Matériaux'!G22 -> 255000 | K13: ='Baumaterialien Matériaux'!H22 -> 255000 | L13: ='Baumaterialien Matériaux'!I22 -> 0 | M13: ='Baumaterialien Matériaux'!M22 -> 55.3 | N13: ='Baumaterialien Matériaux'!N22 -> 55.3 | O13: ='Baumaterialien Matériaux'!O22 -> 0 | P13: ='Baumaterialien Matériaux'!P22 -> 813 | Q13: ='Baumaterialien Matériaux'!Q22 -> 813 | R13: ='Baumaterialien Matériaux'!R22 -> 0 | S13: ='Baumaterialien Matériaux'!S22 -> 181 | T13: ='Baumaterialien Matériaux'!T22 -> 181 | U13: ='Baumaterialien Matériaux'!U22 -> 0 | V13: ='Baumaterialien Matériaux'!F22 -> m2 | W13: =SWITCH('Baumaterialien Matériaux'!F22, "m", "probeLength", "m2", "area", "m3", "volume", "kg", "mass", "Stk.", "device") -> area | X13: ='Baumaterialien Matériaux'!AC22 | Y13: =LEFT(A13,6) -> 00.012 | Z13: KBOB 2016 | AA13: ="Alle > " & SWITCH(F13, "COMPONENT","BAUTEILE", "OTHER_RESOURCE", "RESSOURCEN", "BUILDING_TECHNOLOGY", "GEBÄUDETECHNIK", "MATERIAL", "MATERIALIEN") & " > kbob.admin.ch > KBOB / ecobau / IPB 2009/1:2016" -> Alle > RESSOURCEN > kbob.admin.ch > KBOB / ecobau / IPB 2009/1:2016 | AB13: 60
... A25: ='Baumaterialien Matériaux'!A34 & " " & 'Baumaterialien Matériaux'!B34 & " (KBOB.2016)" -> 00.024 Wasserhaltung, Pumphöhe 10 m (KBOB.2016) | B25: =A25 -> 00.024 Wasserhaltung, Pumphöhe 10 m (KBOB.2016) | F25: OTHER_RESOURCE | G25: =SWITCH(LEFT(A25,2), "00", "OTHER_RESOURCE_CONSTRUCTION_MATERIAL_PREPARATION_WORK", "") -> OTHER_RESOURCE_CONSTRUCTION_MATERIAL_PREPARATION_WORK | J25: ='Baumaterialien Matériaux'!G34 -> 22.5 | K25: ='Baumaterialien Matériaux'!H34 -> 22.5 | L25: ='Baumaterialien Matériaux'!I34 -> 0 | M25: ='Baumaterialien Matériaux'!M34 -> 0.0309 | N25: ='Baumaterialien Matériaux'!N34 -> 0.0309 | O25: ='Baumaterialien Matériaux'!O34 -> 0 | P25: ='Baumaterialien Matériaux'!P34 -> 0.159 | Q25: ='Baumaterialien Matériaux'!Q34 -> 0.159 | R25: ='Baumaterialien Matériaux'!R34 -> 0 | S25: ='Baumaterialien Matériaux'!S34 -> 0.00656 | T25: ='Baumaterialien Matériaux'!T34 -> 0.00656 | U25: ='Baumaterialien Matériaux'!U34 -> 0 | V25: ='Baumaterialien Matériaux'!F34 -> m3 | W25: =SWITCH('Baumaterialien Matériaux'!F34, "m", "probeLength", "m2", "area", "m3", "volume", "kg", "mass", "Stk.", "device") -> volume | X25: ='Baumaterialien Matériaux'!AC34 | Y25: =LEFT(A25,6) -> 00.024 | Z25: KBOB 2016 | AA25: ="Alle > " & SWITCH(F25, "COMPONENT","BAUTEILE", "OTHER_RESOURCE", "RESSOURCEN", "BUILDING_TECHNOLOGY", "GEBÄUDETECHNIK", "MATERIAL", "MATERIALIEN") & " > kbob.admin.ch > KBOB / ecobau / IPB 2009/1:2016" -> Alle > RESSOURCEN > kbob.admin.ch > KBOB / ecobau / IPB 2009/1:2016 | AB25: 60

Sheet Baumaterialien Matériaux
B1: Ökobilanzdaten im Baubereich | M1: KBOB / eco-bau / IPB 2009/1:2016 | V1: Données écobilans dans la construction
H3: Total | I3: Total | K3: Total | L3: Total | N3: Total, renewable | O3: Total, renewable | Q3: Total, non-renewable | R3: Total, non-renewable | T3: IPCC GWP 100a | U3: IPCC GWP 100a
A4: ID-Nummer | B4: BAUMATERIALIEN [Bibliographie treeze, version 2.2:2016] | C4: ID-Nummer Entsorgung | D4: Entsorgung | E4: Rohdichte/ Flächen-masse | F4: Bezug Référence | G4: UBP'13 | J4: Primärenergie Energie primaire | S4: Treibhaus- gasemissionen | V4: MATÉRIAUX [Bibliographie treeze, version 2.2:2016]
A5: No d'identi-fication | C5: No d'identification Déchets | G5: UBP | J5: gesamt | M5: erneuerbar | P5: nicht erneuerbar (Graue Energie) | S5: Emissions de gaz
E6: Masse volumique/ surface | J6: globale | M6: renouvelable | P6: non renouvelable (énergie grise) | S6: à effet de serre
B7: Hinweis: Anzeigen der herstellerspezifischen und herstellerregionenspezifischen Daten durch Anklicken der '+' am linken Rand. | G7: Total | H7: Herstellung | I7: Entsorgung | J7: Total | K7: Herstellung | L7: Entsorgung | M7: Total | N7: Herstellung | O7: Entsorgung | P7: Total | Q7: Herstellung | R7: Entsorgung | S7: Total | T7: Herstellung | U7: Entsorgung | V7: Remarque: Affichage des données spécifiques aux fabricants et aux régions de production en cliquant sur les '+' sur le bord gauche.
G8: Total | H8: Fabrication | I8: Elimination | J8: Total | K8: Fabrication | L8: Elimination | M8: Total | N8: Fabrication | O8: Elimination | P8: Total | Q8: Fabrication | R8: Elimination | S8: Total | T8: Fabrication | U8: Elimination
G9: UBP | H9: UBP | I9: UBP | J9: kWh oil-eq | K9: kWh oil-eq | L9: kWh oil-eq | M9: kWh oil-eq | N9: kWh oil-eq | O9: kWh oil-eq | P9: kWh oil-eq | Q9: kWh oil-eq | R9: kWh oil-eq | S9: kg CO2-eq | T9: kg CO2-eq | U9: kg CO2-eq
A10: 0 | B10: Vorbereitungsarbeiten | E10: - | V10: Travails de préparation
A11: 00.001 | B11: Baugrubensicherung, Bohrpfahlwand, gespriesst | C11: 91.074 | D11: Entsorgung, Baugrubensicherung, Bohrpfahlwand, gespriesst | E11: - | F11: m2 | G11: 1010000 | H11: 877000 | I11: 130000 | J11: 2390 | K11: 2120 | L11: 268 | M11: 110 | N11: 101 | O11: 9.57 | P11: 2280 | Q11: 2020 | R11: 258 | S11: 828 | T11: 778 | U11: 50.2 | V11: Blindage de fouille, paroi parisienne, étayé
A12: 00.002 | B12: Baugrubensicherung, Bohrpfahlwand, unverankert | C12: 91.075 | D12: Entsorgung, Baugrubensicherung, Bohrpfahlwand, unverankert | E12: - | F12: m2 | G12: 952000 | H12: 822000 | I12: 130000 | J12: 2180 | K12: 1910 | L12: 268 | M12: 94.3 | N12: 84.8 | O12: 9.57 | P12: 2090 | Q12: 1830 | R12: 258 | S12: 788 | T12: 738 | U12: 50.2 | V12: Blindage de fouille, paroi parisienne, flottant
A13: 00.003 | B13: Baugrubensicherung, Bohrpfahlwand, verankert | C13: 91.076 | D13: Entsorgung, Baugrubensicherung, Bohrpfahlwand, verankert | E13: - | F13: m2 | G13: 778000 | H13: 692000 | I13: 86200 | J13: 1590 | K13: 1410 | L13: 177 | M13: 82.8 | N13: 76.4 | O13: 6.32 | P13: 1510 | Q13: 1340 | R13: 170 | S13: 512 | T13: 478 | U13: 33.1 | V13: Blindage de fouille, paroi parisienne, fixe
A14: 00.004 | B14: Baugrubensicherung, Nagelwand | C14: 91.077 | D14: Entsorgung, Baugrubensicherung, Nagelwand | E14: - | F14: m2 | G14: 171000 | H14: 152000 | I14: 18900 | J14: 342 | K14: 303 | L14: 38.8 | M14: 17.9 | N14: 16.6 | O14: 1.39 | P14: 324 | Q14: 286 | R14: 37.5 | S14: 116 | T14: 109 | U14: 7.28 | V14: Blindage de fouille, paroi clouée
A15: 00.005 | B15: Baugrubensicherung, Rühlwand, auskragend | C15: 91.078 | D15: Entsorgung, Baugrubensicherung, Rühlwand, auskragend | E15: - | F15: m2 | G15: 332000 | H15: 302000 | I15: 30100 | J15: 1040 | K15: 980 | L15: 61.7 | M15: 108 | N15: 106 | O15: 2.2 | P15: 934 | Q15: 874 | R15: 59.5 | S15: 266 | T15: 254 | U15: 11.6 | V15: Blindage de fouille, paroi berlinoise, en porte-à-faux
A16: 00.006 | B16: Baugrubensicherung, Rühlwand, gespriesst | C16: 91.079 | D16: Entsorgung, Baugrubensicherung, Rühlwand, gespriesst | E16: - | F16: m2 | G16: 240000 | H16: 222000 | I16: 17800 | J16: 724 | K16: 687 | L16: 36.5 | M16: 46.7 | N16: 45.4 | O16: 1.31 | P16: 677 | Q16: 642 | R16: 35.2 | S16: 184 | T16: 177 | U16: 6.84 | V16: Blindage de fouille, paroi berlinoise, étayé
A17: 00.007 | B17: Baugrubensicherung, Rühlwand, verankert | C17: 91.080 | D17: Entsorgung, Baugrubensicherung, Rühlwand, verankert | E17: - | F17: m2 | G17: 259000 | H17: 238000 | I17: 20600 | J17: 725 | K17: 683 | L17: 42.2 | M17: 43.9 | N17: 42.4 | O17: 1.51 | P17: 681 | Q17: 640 | R17: 40.7 | S17: 192 | T17: 184 | U17: 7.9 | V17: Blindage de fouille, paroi berlinoise, fixe
A18: 00.008 | B18: Baugrubensicherung, Schlitzwand, 400 mm | C18: 91.081 | D18: Entsorgung, Baugrubensicherung, Schlitzwand, 400mm | E18: - | F18: m2 | G18: 648000 | H18: 583000 | I18: 65500 | J18: 1320 | K18: 1190 | L18: 135 | M18: 73.3 | N18: 68.6 | O18: 4.76 | P18: 1250 | Q18: 1120 | R18: 130 | S18: 407 | T18: 382 | U18: 25.2 | V18: Blindage de fouille, paroi moulée, 400 mm
A19: 00.009 | B19: Baugrubensicherung, Schlitzwand, 800 mm | C19: 91.082 | D19: Entsorgung, Baugrubensicherung, Schlitzwand, 800mm | E19: - | F19: m2 | G19: 1230000 | H19: 1100000 | I19: 129000 | J19: 2410 | K19: 2140 | L19: 265 | M19: 136 | N19: 126 | O19: 9.43 | P19: 2270 | Q19: 2010 | R19: 256 | S19: 777 | T19: 728 | U19: 49.6 | V19: Blindage de fouille, paroi moulée, 800 mm
A20: 00.010 | B20: Baugrubensicherung, Spundwand, auskragend | C20: 91.083 | D20: Entsorgung, Baugrubensicherung, Spundwand, auskragend | E20: - | F20: m2 | G20: 228000 | H20: 228000 | I20: 0 | J20: 793 | K20: 793 | L20: 0 | M20: 46.2 | N20: 46.2 | O20: 0 | P20: 747 | Q20: 747 | R20: 0 | S20: 163 | T20: 163 | U20: 0 | V20: Blindage de fouille, paroi de palplanche, en porte-à-faux
A21: 00.011 | B21: Baugrubensicherung, Spundwand, gespriesst | C21: 91.084 | D21: Entsorgung, Baugrubensicherung, Spundwand, gespriesst | E21: - | F21: m2 | G21: 129000 | H21: 129000 | I21: 0 | J21: 446 | K21: 446 | L21: 0 | M21: 25.3 | N21: 25.3 | O21: 0 | P21: 421 | Q21: 421 | R21: 0 | S21: 92.3 | T21: 92.3 | U21: 0 | V21: Blindage de fouille, paroi de palplanche, étayé
A22: 00.012 | B22: Baugrubensicherung, Spundwand, verankert | C22: 91.085 | D22: Entsorgung, Baugrubensicherung, Spundwand, verankert | E22: - | F22: m2 | G22: 255000 | H22: 255000 | I22: 0 | J22: 868 | K22: 868 | L22: 0 | M22: 55.3 | N22: 55.3 | O22: 0 | P22: 813 | Q22: 813 | R22: 0 | S22: 181 | T22: 181 | U22: 0 | V22: Blindage de fouille, paroi de palplanche, fixe
... A34: 00.024 | B34: Wasserhaltung, Pumphöhe 10 m | C34: 91.097 | D34: Entsorgung, Wasserhaltung, Pumphöhe 10m | E34: - | F34: m3 | G34: 22.5 | H34: 22.5 | I34: 0 | J34: 0.19 | K34: 0.19 | L34: 0 | M34: 0.0309 | N34: 0.0309 | O34: 0 | P34: 0.159 | Q34: 0.159 | R34: 0 | S34: 0.00656 | T34: 0.00656 | U34: 0 | V34: Épuisement des eaux, hauteur de refoulement, 10 m
A35: 01 | B35: Beton | E35: kg/m3 | V35: Béton
A36: 1.001 | B36: Magerbeton (ohne Bewehrung) | C36: 91.061 | D36: Entsorgungsmix, Beton unbewehrt | E36: 2150 | F36: kg | G36: 65.1 | H36: 40.2 | I36: 24.9 | J36: 0.149 | K36: 0.0995 | L36: 0.049 | M36: 0.00923 | N36: 0.00727 | O36: 0.00196 | P36: 0.139 | Q36: 0.0922 | R36: 0.0471 | S36: 0.0591 | T36: 0.0503 | U36: 0.00881 | V36: Béton maigre (sans armature)
A37: 1.002 | B37: Hochbaubeton (ohne Bewehrung) | C37: 91.060 | D37: Entsorgungsmix, Beton bewehrt | E37: 2300 | F37: kg | G37: 94.3 | H37: 67.3 | I37: 27 | J37: 0.215 | K37: 0.159 | L37: 0.0554 | M37: 0.0134 | N37: 0.0115 | O37: 0.00198 | P37: 0.201 | Q37: 0.148 | R37: 0.0535 | S37: 0.0992 | T37: 0.0889 | U37: 0.0104 | V37: Béton pour bâtiment (sans armature)
A38: 1.003 | B38: Tiefbaubeton (ohne Bewehrung) | C38: 91.060 | D38: Entsorgungsmix, Beton bewehrt | E38: 2350 | F38: kg | G38: 99.9 | H38: 72.9 | I38: 27 | J38: 0.232 | K38: 0.176 | L38: 0.0554 | M38: 0.0144 | N38: 0.0125 | O38: 0.00198 | P38: 0.217 | Q38: 0.164 | R38: 0.0534 | S38: 0.107 | T38: 0.0964 | U38: 0.0104 | V38: Béton pour travaux de génie civil (sans armature)
A39: 1.004 | B39: Bohrpfahlbeton (ohne Bewehrung) | C39: 91.060 | D39: Entsorgungsmix, Beton bewehrt | E39: 2325 | F39: kg | G39: 106 | H39: 79 | I39: 26.9 | J39: 0.243 | K39: 0.188 | L39: 0.0553 | M39: 0.0155 | N39: 0.0135 | O39: 0.00198 | P39: 0.228 | Q39: 0.175 | R39: 0.0533 | S39: 0.117 | T39: 0.107 | U39: 0.0104 | V39: Béton pour pieux (sans armature)
A40: 01.041 | B40: Betonfertigteil, hochfester Beton, ab Werk | C40: 91.060 | D40: Entsorgungsmix, Beton bewehrt | E40: 2770 | F40: kg | G40: 477 | H40: 454 | I40: 23.8 | J40: 0.826 | K40: 0.777 | L40: 0.0489 | M40: 0.0574 | N40: 0.0556 | O40: 0.00175 | P40: 0.768 | Q40: 0.721 | R40: 0.0472 | S40: 0.265 | T40: 0.255 | U40: 0.00917 | V40: Élément préfabriqué en béton, béton à hautes performances, sortie d'usine
A41: 01.042 | B41: Betonfertigteil, Normalbeton, ab Werk | C41: 91.060 | D41: Entsorgungsmix, Beton bewehrt | E41: 2500 | F41: kg | G41: 245 | H41: 218 | I41: 26.1 | J41: 0.58 | K41: 0.526 | L41: 0.0535 | M41: 0.0961 | N41: 0.0942 | O41: 0.00191 | P41: 0.484 | Q41: 0.432 | R41: 0.0516 | S41: 0.172 | T41: 0.162 | U41: 0.01 | V41: Élément préfabriqué en béton, béton normal, sortie d'usine
A42: 01.043 | B42: Hanfbeton | C42: 91.073 | D42: Entsorgungsmix, Hanfbeton | E42: 600 | F42: kg | G42: 371 | H42: 370 | I42: 0.743 | J42: 1.87 | K42: 1.86 | L42: 0.0028 | M42: 0.882 | N42: 0.882 | O42: 2.59e-05 | P42: 0.984 | Q42: 0.982 | R42: 0.00278 | S42: 0.288 | T42: 0.288 | U42: 0.000365 | V42: Béton chaux-chanvre
A43: 01.043.01 | B43: Hanfbeton, ARBIO | C43: 91.073 | D43: Entsorgungsmix, Hanfbeton | E43: 600 | F43: kg | G43: 357 | H43: 356 | I43: 0.743 | J43: 1.8 | K43: 1.79 | L43: 0.0028 | M43: 0.849 | N43: 0.848 | O43: 2.59e-05 | P43: 0.947 | Q43: 0.944 | R43: 0.00278 | S43: 0.277 | T43: 0.277 | U43: 0.000365 | V43: Béton chaux-chanvre, ARBIO
A44: Betonsortenrechner: Mit dem Betonsortenrechner (http://treeze.ch/de/rechner/betonsortenrechner/) können die Umweltkennwerte von spezifischen Betonen mit verschiedenen Zementtypen und Gesteinskörnungen berechnet werden.
A45: Calculatrice à béton: la calculatrice (http://treeze.ch/de/rechner/betonsortenrechner/) permet de calculer les données environnementales des différents types de béton fabriqués à partir de ciments et granulats divers.
A46: 02 | B46: Mauersteine | E46: kg/m3 | V46: Pierres de taille
A47: 02.001 | B47: Backstein | C47: 91.059 | D47: Entsorgungsmix, Backstein | E47: 900 | F47: kg | G47: 217 | H47: 191 | I47: 25.8 | J47: 0.868 | K47: 0.816 | L47: 0.0523 | M47: 0.0775 | N47: 0.0757 | O47: 0.00177 | P47: 0.791 | Q47: 0.74 | R47: 0.0505 | S47: 0.258 | T47: 0.249 | U47: 0.00903 | V47: Brique en terre cuite
A48: 02.002 | B48: Kalksandstein | C48: 91.065 | D48: Entsorgungsmix, Kalksandstein | E48: 1400 | F48: kg | G48: 157 | H48: 132 | I48: 25.1 | J48: 0.434 | K48: 0.385 | L48: 0.0499 | M48: 0.0368 | N48: 0.035 | O48: 0.00186 | P48: 0.398 | Q48: 0.35 | R48: 0.0481 | S48: 0.138 | T48: 0.129 | U48: 0.00868 | V48: Grès
A49: 02.002.01 | B49: Kalksandstein, FBB | C49: 91.065 | D49: Entsorgungsmix, Kalksandstein | E49: 1400 | F49: kg | G49: 122 | H49: 97.4 | I49: 25.1 | J49: 0.35 | K49: 0.3 | L49: 0.0499 | M49: 0.0344 | N49: 0.0325 | O49: 0.00186 | P49: 0.316 | Q49: 0.267 | R49: 0.0481 | S49: 0.108 | T49: 0.0996 | U49: 0.00868 | V49: Grès, FBB
A50: 02.003 | B50: Leichtlehmstein | C50: 91.059 | D50: Entsorgungsmix, Backstein | E50: 700 | F50: kg | G50: 237 | H50: 212 | I50: 25.8 | J50: 1.56 | K50: 1.5 | L50: 0.0523 | M50: 0.793 | N50: 0.791 | O50: 0.00177 | P50: 0.762 | Q50: 0.712 | R50: 0.0505 | S50: 0.17 | T50: 0.161 | U50: 0.00903 | V50: Brique en argile léger
A51: 02.004 | B51: Leichtzementstein, Blähton | C51: 91.070 | D51: Entsorgungsmix, Zement (in Beton) und Mauermörtel | E51: 1200 | F51: kg | G51: 471 | H51: 445 | I51: 26.6 | J51: 1.57 | K51: 1.51 | L51: 0.0547 | M51: 0.0521 | N51: 0.0503 | O51: 0.00178 | P51: 1.51 | Q51: 1.46 | R51: 0.0529 | S51: 0.417 | T51: 0.407 | U51: 0.00961 | V51: Pierre en béton léger: argile expansée
A52: 02.005 | B52: Leichtzementstein, Naturbims | C52: 91.070 | D52: Entsorgungsmix, Zement (in Beton) und Mauermörtel | E52: 1200 | F52: kg | G52: 222 | H52: 195 | I52: 26.6 | J52: 0.455 | K52: 0.4 | L52: 0.0547 | M52: 0.0309 | N52: 0.0291 | O52: 0.00178 | P52: 0.424 | Q52: 0.371 | R52: 0.0529 | S52: 0.223 | T52: 0.214 | U52: 0.00961 | V52: Pierre en béton léger: pierre ponce naturelle
A53: 02.006 | B53: Porenbetonstein | C53: 91.059 | D53: Entsorgungsmix, Backstein | E53: 500 | F53: kg | G53: 348 | H53: 323 | I53: 25.8 | J53: 0.99 | K53: 0.938 | L53: 0.0523 | M53: 0.0653 | N53: 0.0635 | O53: 0.00177 | P53: 0.925 | Q53: 0.875 | R53: 0.0505 | S53: 0.417 | T53: 0.408 | U53: 0.00903 | V53: Béton cellulaire
A54: 02.007 | B54: Zementstein | C54: 91.061 | D54: Entsorgungsmix, Beton unbewehrt | E54: 1700 | F54: kg | G54: 133 | H54: 108 | I54: 25.1 | J54: 0.278 | K54: 0.229 | L54: 0.0494 | M54: 0.0238 | N54: 0.0219 | O54: 0.00198 | P54: 0.254 | Q54: 0.207 | R54: 0.0474 | S54: 0.129 | T54: 0.121 | U54: 0.00887 | V54: Plot de ciment
A55: 03 | B55: Andere Massivbaustoffe | E55: kg/m3 | V55: Autres matériaux massifs
A56: 03.001 | B56: Betonziegel | C56: 91.059 | D56: Entsorgungsmix, Backstein | E56: 2300 | F56: kg | G56: 212 | H56: 187 | I56: 25.8 | J56: 0.551 | K56: 0.499 | L56: 0.0523 | M56: 0.0343 | N56: 0.0326 | O56: 0.00177 | P56: 0.517 | Q56: 0.466 | R56: 0.0505 | S56: 0.217 | T56: 0.208 | U56: 0.00903 | V56: Tuiles en béton
A57: 03.002 | B57: Faserzement-Dachschindel | C57: 91.070 | D57: Entsorgungsmix, Zement (in Beton) und Mauermörtel | E57: 1800 | F57: kg | G57: 751 | H57: 724 | I57: 26.6 | J57: 2.93 | K57: 2.87 | L57: 0.0547 | M57: 0.476 | N57: 0.474 | O57: 0.00178 | P57: 2.45 | Q57: 2.4 | R57: 0.0529 | S57: 0.727 | T57: 0.717 | U57: 0.00961 | V57: Bardeau de fibrociment
A58: 03.003 | B58: Faserzementplatte gross | C58: 91.070 | D58: Entsorgungsmix, Zement (in Beton) und Mauermörtel | E58: 1800 | F58: kg | G58: 1030 | H58: 1000 | I58: 26.6 | J58: 3.9 | K58: 3.84 | L58: 0.0547 | M58: 0.624 | N58: 0.622 | O58: 0.00178 | P58: 3.27 | Q58: 3.22 | R58: 0.0529 | S58: 1.09 | T58: 1.08 | U58: 0.00961 | V58: Dalle de fibrociment, grande
A59: 03.004 | B59: Faserzement-Wellplatte | C59: 91.070 | D59: Entsorgungsmix, Zement (in Beton) und Mauermörtel | E59: 1800 | F59: kg | G59: 726 | H59: 700 | I59: 26.6 | J59: 2.61 | K59: 2.55 | L59: 0.0547 | M59: 0.544 | N59: 0.543 | O59: 0.00178 | P59: 2.06 | Q59: 2.01 | R59: 0.0529 | S59: 0.678 | T59: 0.669 | U59: 0.00961 | V59: Plaque ondulée en fibrociment
A60: 03.005 | B60: Flachglas beschichtet | C60: 91.032 | D60: Entsorgung, Gebäude, Flachglas, in Beseitigung | E60: 2500 | F60: kg | G60: 1350 | H60: 1340 | I60: 18.6 | J60: 4.95 | K60: 4.88 | L60: 0.0684 | M60: 0.233 | N60: 0.232 | O60: 0.000668 | P60: 4.71 | Q60: 4.65 | R60: 0.0678 | S60: 1.16 | T60: 1.15 | U60: 0.00999 | V60: Verre plat, enduit
A61: 03.006 | B61: Flachglas unbeschichtet | C61: 91.032 | D61: Entsorgung, Gebäude, Flachglas, in Beseitigung | E61: 2500 | F61: kg | G61: 1140 | H61: 1120 | I61: 18.6 | J61: 4.19 | K61: 4.13 | L61: 0.0684 | M61: 0.13 | N61: 0.13 | O61: 0.000668 | P61: 4.06 | Q61: 4 | R61: 0.0678 | S61: 1.1 | T61: 1.09 | U61: 0.00999 | V61: Verre plat, non enduit
A62: 03.007 | B62: Gipsfaserplatte | C62: 91.063 | D62: Entsorgungsmix, Gipsfaserplatte | E62: 1200 | F62: kg | G62: 488 | H62: 470 | I62: 17.5 | J62: 2.55 | K62: 2.48 | L62: 0.0657 | M62: 0.0858 | N62: 0.0852 | O62: 0.000626 | P62: 2.46 | Q62: 2.4 | R62: 0.0651 | S62: 0.537 | T62: 0.527 | U62: 0.00926 | V62: Plaque de plâtre armé de fibres
A63: 03.008 | B63: Gipskartonplatte | C63: 91.064 | D63: Entsorgungsmix, Gipskartonplatte | E63: 850 | F63: kg | G63: 314 | H63: 296 | I63: 17.3 | J63: 1.43 | K63: 1.36 | L63: 0.0651 | M63: 0.0786 | N63: 0.078 | O63: 0.000621 | P63: 1.35 | Q63: 1.28 | R63: 0.0645 | S63: 0.293 | T63: 0.284 | U63: 0.00918 | V63: Plaque de plâtre cartonnées
A64: 03.016 | B64: Gips-Wandbauplatte / Vollgipsplatte | C64: 91.069 | D64: Entsorgungsmix, Gips-Wandbauplatte / Vollgipsplatte | E64: 1000 | F64: kg | G64: 343 | H64: 326 | I64: 17.2 | J64: 1.47 | K64: 1.4 | L64: 0.0647 | M64: 0.029 | N64: 0.0284 | O64: 0.000617 | P64: 1.44 | Q64: 1.37 | R64: 0.0641 | S64: 0.307 | T64: 0.298 | U64: 0.00913 | V64: Blocs de gypse / plâtre massif
A65: 03.009 | B65: Hartsandsteinplatte | C65: 91.065 | D65: Entsorgungsmix, Kalksandstein | E65: 2500 | F65: kg | G65: 75 | H65: 49.9 | I65: 25.1 | J65: 0.341 | K65: 0.291 | L65: 0.0499 | M65: 0.039 | N65: 0.0371 | O65: 0.00186 | P65: 0.302 | Q65: 0.254 | R65: 0.0481 | S65: 0.0336 | T65: 0.0249 | U65: 0.00868 | V65: Plaque de grès dur
A66: 03.017 | B66: Kalksteinplatte | C66: 91.065 | D66: Entsorgungsmix, Kalksandstein | E66: 2600 | F66: kg | G66: 79 | H66: 53.9 | I66: 25.1 | J66: 0.352 | K66: 0.303 | L66: 0.0499 | M66: 0.0246 | N66: 0.0227 | O66: 0.00186 | P66: 0.328 | Q66: 0.28 | R66: 0.0481 | S66: 0.0657 | T66: 0.057 | U66: 0.00868 | V66: Plaque de calcaire dur
A67: 03.010 | B67: Keramik-/Steinzeugplatte | C67: 91.059 | D67: Entsorgungsmix, Backstein | E67: 2600 | F67: kg | G67: 2460 | H67: 2430 | I67: 25.8 | J67: 4.05 | K67: 3.99 | L67: 0.0523 | M67: 0.234 | N67: 0.232 | O67: 0.00177 | P67: 3.81 | Q67: 3.76 | R67: 0.0505 | S67: 0.777 | T67: 0.768 | U67: 0.00903 | V67: Dalle de céramique/grès
... A73: 03.015 | B73: Tonziegel | C73: 91.059 | D73: Entsorgungsmix, Backstein | E73: 1700 | F73: kg | G73: 300 | H73: 274 | I73: 25.8 | J73: 1.15 | K73: 1.1 | L73: 0.0523 | M73: 0.0335 | N73: 0.0318 | O73: 0.00177 | P73: 1.12 | Q73: 1.07 | R73: 0.0505 | S73: 0.375 | T73: 0.366 | U73: 0.00903 | V73: Tuile en terre cuite
A74: 04 | B74: Mörtel und Putze | E74: kg/m3 | V74: Mortiers et enduits
A75: 04.008 | B75: Baukleber/Einbettmörtel mineralisch | C75: 91.100 | D75: Entsorgungsmix, Putz, ausgehärtet | E75: 1400 | F75: kg | G75: 427 | H75: 410 | I75: 17.2 | J75: 1.77 | K75: 1.7 | L75: 0.0647 | M75: 0.166 | N75: 0.166 | O75: 0.000617 | P75: 1.6 | Q75: 1.54 | R75: 0.0641 | S75: 0.406 | T75: 0.397 | U75: 0.00913 | V75: Colle de construction/mortier d'enrobage minéral(e)
A76: 04.010 | B76: Baukleber/Einbettmörtel mineralisch Leichtzuschlag | C76: 91.100 | D76: Entsorgungsmix, Putz, ausgehärtet | E76: 1100 | F76: kg | G76: 424 | H76: 407 | I76: 17.2 | J76: 1.84 | K76: 1.77 | L76: 0.0647 | M76: 0.146 | N76: 0.146 | O76: 0.000617 | P76: 1.69 | Q76: 1.62 | R76: 0.0641 | S76: 0.427 | T76: 0.418 | U76: 0.00913 | V76: Colle de construction/mortier d'enrobage minéral(e) avec agrégats légers
A77: 04.002 | B77: Baukleber/Einbettmörtel organisch | C77: 91.100 | D77: Entsorgungsmix, Putz, ausgehärtet | E77: 1670 | F77: kg | G77: 1000 | H77: 982 | I77: 17.2 | J77: 4.35 | K77: 4.28 | L77: 0.0647 | M77: 0.146 | N77: 0.145 | O77: 0.000617 | P77: 4.2 | Q77: 4.14 | R77: 0.0641 | S77: 0.758 | T77: 0.749 | U77: 0.00913 | V77: Colle de construction/mortier d'enrobage biologique
A78: 04.017 | B78: Gips-Kalk-Putz | C78: 91.098 | D78: Entsorgungsmix, Gips-Kalk-Putz | E78: 925 | F78: kg | G78: 151 | H78: 134 | I78: 17.2 | J78: 0.749 | K78: 0.685 | L78: 0.0647 | M78: 0.0635 | N78: 0.0629 | O78: 0.000617 | P78: 0.686 | Q78: 0.622 | R78: 0.0641 | S78: 0.155 | T78: 0.145 | U78: 0.00913 | V78: Enduit en plâtre et chaux
A79: 4.001 | B79: Gips-/Weissputz | C79: 91.099 | D79: Entsorgungsmix, Gips-/Weissputz | E79: 1100 | F79: kg | G79: 146 | H79: 129 | I79: 17.2 | J79: 0.754 | K79: 0.689 | L79: 0.0647 | M79: 0.0618 | N79: 0.0612 | O79: 0.000617 | P79: 0.692 | Q79: 0.628 | R79: 0.0641 | S79: 0.147 | T79: 0.138 | U79: 0.00913 | V79: Enduit minéral
A80: 4.003 | B80: Kunststoffputz (Dispersionsputz) | C80: 91.100 | D80: Entsorgungsmix, Putz, ausgehärtet | E80: 1540 | F80: kg | G80: 1230 | H80: 1210 | I80: 17.2 | J80: 5.48 | K80: 5.42 | L80: 0.0647 | M80: 0.227 | N80: 0.227 | O80: 0.000617 | P80: 5.25 | Q80: 5.19 | R80: 0.0641 | S80: 0.951 | T80: 0.942 | U80: 0.00913 | V80: Crépi synthétique (enduit de dispersion)
A81: 04.013 | B81: Kalk-Zement/Zement-Kalk-Putz | C81: 91.100 | D81: Entsorgungsmix, Putz, ausgehärtet | E81: 1550 | F81: kg | G81: 237 | H81: 220 | I81: 17.2 | J81: 0.895 | K81: 0.83 | L81: 0.0647 | M81: 0.13 | N81: 0.13 | O81: 0.000617 | P81: 0.765 | Q81: 0.701 | R81: 0.0641 | S81: 0.247 | T81: 0.238 | U81: 0.00913 | V81: Enduit en plâtre et en ciment
A82: 04.004 | B82: Lehmputz | C82: 91.067 | D82: Entsorgungsmix, Mineralischer Putz | E82: 1800 | F82: kg | G82: 62.3 | H82: 43 | I82: 19.3 | J82: 0.18 | K82: 0.148 | L82: 0.0324 | M82: 0.0159 | N82: 0.014 | O82: 0.0019 | P82: 0.164 | Q82: 0.134 | R82: 0.0305 | S82: 0.0229 | T82: 0.0182 | U82: 0.00473 | V82: Enduit de glaise
A83: 04.015 | B83: Leichtputz mineralisch | C83: 91.100 | D83: Entsorgungsmix, Putz, ausgehärtet | E83: 1000 | F83: kg | G83: 366 | H83: 348 | I83: 17.2 | J83: 1.45 | K83: 1.39 | L83: 0.0647 | M83: 0.154 | N83: 0.154 | O83: 0.000617 | P83: 1.3 | Q83: 1.23 | R83: 0.0641 | S83: 0.366 | T83: 0.357 | U83: 0.00913 | V83: Enduit de glaise minéral
A84: 04.011 | B84: Silikatputz (Dispersionssilikatputz) | C84: 91.100 | D84: Entsorgungsmix, Putz, ausgehärtet | E84: 1880 | F84: kg | G84: 1220 | H84: 1200 | I84: 17.2 | J84: 5.36 | K84: 5.29 | L84: 0.0647 | M84: 0.249 | N84: 0.248 | O84: 0.000617 | P84: 5.11 | Q84: 5.04 | R84: 0.0641 | S84: 0.975 | T84: 0.966 | U84: 0.00913 | V84: Crépi silicate (silicate de dispersion)
A85: 04.012 | B85: Silikonharzputz | C85: 91.100 | D85: Entsorgungsmix, Putz, ausgehärtet | E85: 1670 | F85: kg | G85: 1410 | H85: 1390 | I85: 17.2 | J85: 6.54 | K85: 6.47 | L85: 0.0647 | M85: 0.37 | N85: 0.37 | O85: 0.000617 | P85: 6.17 | Q85: 6.1 | R85: 0.0641 | S85: 1.12 | T85: 1.11 | U85: 0.00913 | V85: Crépi à la résine de silicone
A86: 04.016 | B86: Sumpfkalkputz | C86: 91.100 | D86: Entsorgungsmix, Putz, ausgehärtet | E86: 1350 | F86: kg | G86: 442 | H86: 425 | I86: 17.2 | J86: 1.92 | K86: 1.85 | L86: 0.0647 | M86: 0.113 | N86: 0.112 | O86: 0.000617 | P86: 1.8 | Q86: 1.74 | R86: 0.0641 | S86: 0.469 | T86: 0.46 | U86: 0.00913 | V86: Enduit à la chaux grasse
A87: 04.005 | B87: Unterlagsboden Anhydrit, 60 mm | C87: 91.101 | D87: Entsorgungsmix, Unterlagsboden Anhydrit, 60 mm | E87: 2000 | F87: kg | G87: 146 | H87: 128 | I87: 18.5 | J87: 0.483 | K87: 0.414 | L87: 0.0698 | M87: 0.0254 | N87: 0.0247 | O87: 0.000662 | P87: 0.458 | Q87: 0.389 | R87: 0.0691 | S87: 0.0867 | T87: 0.0769 | U87: 0.00978 | V87: Chape d'anhydrite, 60 mm
A88: 04.006 | B88: Unterlagsboden Zement, 85 mm | C88: 91.102 | D88: Entsorgungsmix, Unterlagsboden Zement, 85 mm | E88: 1850 | F88: kg | G88: 140 | H88: 122 | I88: 17.2 | J88: 0.312 | K88: 0.247 | L88: 0.0647 | M88: 0.0313 | N88: 0.0306 | O88: 0.000617 | P88: 0.281 | Q88: 0.217 | R88: 0.0641 | S88: 0.125 | T88: 0.116 | U88: 0.00913 | V88: Chape de ciment, 85 mm
A89: 04.007 | B89: Wärmedämmputz EPS | C89: 91.100 | D89: Entsorgungsmix, Putz, ausgehärtet | E89: 250 | F89: kg | G89: 613 | H89: 596 | I89: 17.2 | J89: 2.09 | K89: 2.03 | L89: 0.0647 | M89: 0.135 | N89: 0.135 | O89: 0.000617 | P89: 1.96 | Q89: 1.89 | R89: 0.0641 | S89: 0.767 | T89: 0.758 | U89: 0.00913 | V89: Enduit d'isolation thermique EPS
A90: 04.014 | B90: Weisszementputz | C90: 91.100 | D90: Entsorgungsmix, Putz, ausgehärtet | E90: 1550 | F90: kg | G90: 301 | H90: 284 | I90: 17.2 | J90: 1.14 | K90: 1.07 | L90: 0.0647 | M90: 0.136 | N90: 0.135 | O90: 0.000617 | P90: 1 | Q90: 0.938 | R90: 0.0641 | S90: 0.328 | T90: 0.319 | U90: 0.00913 | V90: Crépit en ciment
A91: 4.009 | B91: Zementputz | C91: 91.100 | D91: Entsorgungsmix, Putz, ausgehärtet | E91: 1550 | F91: kg | G91: 255 | H91: 238 | I91: 17.2 | J91: 0.85 | K91: 0.785 | L91: 0.0647 | M91: 0.122 | N91: 0.121 | O91: 0.000617 | P91: 0.728 | Q91: 0.664 | R91: 0.0641 | S91: 0.269 | T91: 0.26 | U91: 0.00913 | V91: Enduit de ciment
A92: 05 | B92: Fenster, Sonnenschutz, Fassadenverkleidungen | E92: kg/m2 | V92: Fenêtre et façades verre/métal
A93: 05.008 | B93: Fassade, Pfosten-Riegel, Alu/Glas | C93: 91.135 | D93: Entsorgung, Fassade, Pfosten-Riegel, Alu/Glas | E93: - | F93: m2 | G93: 250000 | H93: 242000 | I93: 7250 | J93: 827 | K93: 823 | L93: 3.18 | M93: 66.1 | N93: 66 | O93: 0.0986 | P93: 760 | Q93: 757 | R93: 3.08 | S93: 177 | T93: 163 | U93: 13.5 | V93: Façade, à montants et traverses, Alu/Glas
A94: 05.022 | B94: Fassadenplatte, Aluverbund, 4 mm | C94: 91.103 | D94: Entsorgungsmix, Fassadenplatte, Aluverbund, 4 mm | E94: 7.1 | F94: m2 | G94: 45400 | H94: 41100 | I94: 4240 | J94: 224 | K94: 224 | L94: 0.536 | M94: 24.5 | N94: 24.5 | O94: 0.0085 | P94: 200 | Q94: 199 | R94: 0.527 | S94: 44.3 | T94: 35.8 | U94: 8.58 | V94: Panneau de façade, en aluminium, 4 mm
A95: 05.023 | B95: Fassadenplatte, Hochdrucklaminatplatte (HPL), 8.1 mm | C95: 91.106 | D95: Entsorgung, HPL-Fassadenplatten, in Kehrichtverbrennung | E95: 11.6 | F95: m2 | G95: 49800 | H95: 43500 | I95: 6310 | J95: 288 | K95: 286 | L95: 1.87 | M95: 89.7 | N95: 89.7 | O95: 0.044 | P95: 198 | Q95: 196 | R95: 1.82 | S95: 44.5 | T95: 33.4 | U95: 11.1 | V95: Panneau de façade, stratifié (HPL), 8,1 mm
A96: 05.025 | B96: Fassadenplatte, Kalkstein, 30 mm | C96: 91.065 | D96: Entsorgungsmix, Kalksandstein | E96: 78 | F96: m2 | G96: 6160 | H96: 4210 | I96: 1960 | J96: 27.5 | K96: 23.6 | L96: 3.89 | M96: 1.92 | N96: 1.77 | O96: 0.145 | P96: 25.6 | Q96: 21.8 | R96: 3.75 | S96: 5.13 | T96: 4.45 | U96: 0.677 | V96: Panneau de façade, calcaire, 30 mm
A97: 05.024 | B97: Fassadenplatte, Kunststoff glasfaserverstärkt (GFK), 1.6 mm | C97: 91.071 | D97: Entsorgung, glasfaserverstärkter Kunststoff (GFK), in Kehrichtverbrennung | E97: 2.4 | F97: m2 | G97: 22100 | H97: 19600 | I97: 2460 | J97: 79.4 | K97: 78.9 | L97: 0.474 | M97: 3.66 | N97: 3.65 | O97: 0.012 | P97: 75.7 | Q97: 75.3 | R97: 0.462 | S97: 21.2 | T97: 16.5 | U97: 4.76 | V97: Panneau de façade, plastique à renfort de verre (PRV), 1,6 mm
A98: 05.004 | B98: Fensterrahmen Aluminium | C98: 91.105 | D98: Entsorgungsmix, Fensterrahmen Aluminium | E98: - | F98: m2 | G98: 406000 | H98: 387000 | I98: 18600 | J98: 1820 | K98: 1810 | L98: 3.54 | M98: 216 | N98: 216 | O98: 0.123 | P98: 1600 | Q98: 1600 | R98: 3.42 | S98: 362 | T98: 326 | U98: 36.1 | V98: Cadre de fenêtre en aluminium
A99: 05.004.01 | B99: Fensterrahmen Aluminium, WICLINE 75evo | C99: 91.105.01 | D99: Entsorgungsmix, Fensterrahmen Aluminium, WICLINE 75evo | E99: - | F99: m2 | G99: 259000 | H99: 248000 | I99: 10900 | J99: 1020 | K99: 1020 | L99: 1.64 | M99: 161 | N99: 161 | O99: 0.0467 | P99: 862 | Q99: 860 | R99: 1.59 | S99: 203 | T99: 182 | U99: 21.4 | V99: Cadre de fenêtre en aluminium, WICLINE 75evo
A100: 05.005 | B100: Fensterrahmen Holz | C100: 91.029 | D100: Entsorgung, Gebäude, Fensterrahmen, Holz, in Beseitigung | E100: - | F100: m2 | G100: 217000 | H100: 201000 | I100: 15900 | J100: 1280 | K100: 1280 | L100: 8.22 | M100: 711 | N100: 711 | O100: 0.136 | P100: 573 | Q100: 565 | R100: 8.09 | S100: 128 | T100: 109 | U100: 19.6 | V100: Cadre de fenêtre en bois
A101: 05.006 | B101: Fensterrahmen Holz-Aluminium | C101: 91.030 | D101: Entsorgung, Gebäude, Fensterrahmen, Holz-Metall, in Beseitigung | E101: - | F101: m2 | G101: 319000 | H101: 301000 | I101: 18400 | J101: 1670 | K101: 1660 | L101: 7.89 | M101: 720 | N101: 720 | O101: 0.138 | P101: 951 | Q101: 943 | R101: 7.75 | S101: 217 | T101: 191 | U101: 25.7 | V101: Cadre de fenêtre bois-aluminium
A102: 05.007 | B102: Fensterrahmen Kunststoff/PVC | C102: 91.031 | D102: Entsorgung, Gebäude, Fensterrahmen, Plastik, in Beseitigung | E102: - | F102: m2 | G102: 450000 | H102: 416000 | I102: 33200 | J102: 1590 | K102: 1560 | L102: 31.3 | M102: 69.4 | N102: 66.9 | O102: 2.42 | P102: 1520 | Q102: 1490 | R102: 28.9 | S102: 285 | T102: 228 | U102: 57.2 | V102: Cadre en matière synthétique (PVC)
A103: 05.001 | B103: Isolierverglasung 2-fach, Ug-Wert 1.1 W/m2K, Dicke 24 mm | C103: 91.042 | D103: Entsorgungsmix, Isolierverglasung 2-fach, Ug-Wert 1.1 W/m2K, Dicke 24 mm | E103: - | F103: m2 | G103: 46800 | H103: 44600 | I103: 2180 | J103: 181 | K103: 179 | L103: 1.36 | M103: 9.52 | N103: 9.51 | O103: 0.0176 | P103: 171 | Q103: 170 | R103: 1.35 | S103: 43.7 | T103: 39.8 | U103: 3.88 | V103: Double vitrage, U<1.1 W/m2K, épaisseur 24 mm
A104: 05.009 | B104: Isolierverglasung 2-fach, Ug-Wert 1.1 W/m2K, Dicke 18 mm | C104: 91.107 | D104: Entsorgungsmix, Isolierverglasung 2-fach, Ug-Wert 1.1 W/m2K, Dicke 18 mm | E104: - | F104: m2 | G104: 51300 | H104: 49600 | I104: 1730 | J104: 211 | K104: 210 | L104: 1.32 | M104: 12.3 | N104: 12.3 | O104: 0.0158 | P104: 199 | Q104: 198 | R104: 1.3 | S104: 47.9 | T104: 44.9 | U104: 2.98 | V104: Double vitrage, U<1.1 W/m2K, épaisseur 18 mm
A105: 05.010 | B105: Isolierverglasung 2-fach, ESG, Ug-Wert 1.1 W/m2K | C105: 91.108 | D105: Entsorgungsmix, Isolierverglasung 2-fach, ESG, Ug-Wert 1.1 W/m2K | E105: - | F105: m2 | G105: 57500 | H105: 55300 | I105: 2180 | J105: 243 | K105: 242 | L105: 1.36 | M105: 16.8 | N105: 16.8 | O105: 0.0176 | P105: 226 | Q105: 225 | R105: 1.35 | S105: 51.1 | T105: 47.2 | U105: 3.88 | V105: Double vitrage, verre ESG, U<1.1 W/m2K
A106: 05.002 | B106: Isolierverglasung 2-fach, VSG, Ug-Wert 1.1 W/m2K | C106: 91.043 | D106: Entsorgungsmix, Isolierverglasung 2-fach, VSG, Ug-Wert 1.1 W/m2K | E106: - | F106: m2 | G106: 84000 | H106: 80100 | I106: 3900 | J106: 354 | K106: 352 | L106: 2.08 | M106: 19.3 | N106: 19.2 | O106: 0.0249 | P106: 335 | Q106: 333 | R106: 2.05 | S106: 78.2 | T106: 71.1 | U106: 7.16 | V106: Double vitrage, verre VSG, U<1.1 W/m2K
A107: 05.011 | B107: Isolierverglasung 2-fach, ESG/VSG, Ug-Wert 1.1 W/m2K | C107: 91.109 | D107: Entsorgungsmix, Isolierverglasung 2-fach, ESG/VSG, Ug-Wert 1.1 W/m2K | E107: - | F107: m2 | G107: 94700 | H107: 90800 | I107: 3900 | J107: 416 | K107: 414 | L107: 2.08 | M107: 26.6 | N107: 26.5 | O107: 0.0249 | P107: 390 | Q107: 388 | R107: 2.05 | S107: 85.6 | T107: 78.4 | U107: 7.16 | V107: Double vitrage, verre ESG/VSG, U<1.1 W/m2K
A108: 05.003 | B108: Isolierverglasung 3-fach, Ug-Wert 0.5 W/m2K, Dicke 36 mm | C108: 91.044 | D108: Entsorgungsmix, Isolierverglasung 3-fach, Ug-Wert 0.5 W/m2K, Dicke 36 mm | E108: - | F108: m2 | G108: 83100 | H108: 80100 | I108: 2980 | J108: 349 | K108: 347 | L108: 2.01 | M108: 22 | N108: 22 | O108: 0.0253 | P108: 327 | Q108: 325 | R108: 1.99 | S108: 77.3 | T108: 72.1 | U108: 5.25 | V108: Triple vitrage, U<0.5 W/m2K, épaisseur 36 mm
A109: 05.012 | B109: Isolierverglasung 3-fach, Ug-Wert 0.6 W/m2K, Dicke 40 mm | C109: 91.110 | D109: Entsorgungsmix, Isolierverglasung 3-fach, Ug-Wert 0.6 W/m2K, Dicke 40 mm | E109: - | F109: m2 | G109: 74300 | H109: 70900 | I109: 3450 | J109: 276 | K109: 274 | L109: 2.06 | M109: 14.9 | N109: 14.9 | O109: 0.0271 | P109: 261 | Q109: 259 | R109: 2.04 | S109: 66.8 | T109: 60.7 | U109: 6.16 | V109: Triple vitrage, U<0.6 W/m2K, épaisseur 40 mm
... A113: 05.016 | B113: Isolierverglasung 3-fach, ESG/VSG, Ug-Wert 0.6 W/m2K | C113: 91.114 | D113: Entsorgungsmix, Isolierverglasung 3-fach, ESG/VSG, Ug-Wert 0.6 W/m2K | E113: - | F113: m2 | G113: 124000 | H113: 118000 | I113: 5170 | J113: 516 | K113: 513 | L113: 2.78 | M113: 32 | N113: 32 | O113: 0.0344 | P113: 484 | Q113: 481 | R113: 2.74 | S113: 110 | T113: 100 | U113: 9.45 | V113: Triple vitrage, verre ESG/VSG, U<0.6 W/m2K
A114: 05.020 | B114: Putzträgerplatte kunstharzgebunden 13 mm | C114: 91.116 | D114: Entsorgungsmix, Putzträgerplatte kunstharzgebunden 13 mm | E114: 6.3 | F114: m2 | G114: 11200 | H114: 11000 | I114: 108 | J114: 48.1 | K114: 47.7 | L114: 0.407 | M114: 3.64 | N114: 3.64 | O114: 0.00388 | P114: 44.5 | Q114: 44.1 | R114: 0.403 | S114: 8.01 | T114: 7.95 | U114: 0.0574 | V114: Panneau de support de crépis, liant en résine synthétique, 13 mm
A115: 05.021 | B115: Putzträgerplatte mineralisch gebunden 12.5 mm | C115: 91.117 | D115: Entsorgungsmix, Putzträgerplatte mineralisch gebunden 12.5 mm | E115: 14.4 | F115: m2 | G115: 7210 | H115: 6970 | I115: 248 | J115: 21.7 | K115: 20.7 | L115: 0.932 | M115: 2.37 | N115: 2.36 | O115: 0.00889 | P115: 19.3 | Q115: 18.4 | R115: 0.923 | S115: 6.18 | T115: 6.05 | U115: 0.131 | V115: Panneau de support de crépis, liant en matière minérale, 12,5 mm
A116: 05.018 | B116: Sonnenschutz, Ausstellstoren motorisiert | C116: 91.104 | D116: Entsorgungsmix, Sonnenschutz, Ausstellstoren motorisiert | E116: - | F116: m2 | G116: 141000 | H116: 140000 | I116: 831 | J116: 333 | K116: 333 | L116: 0.479 | M116: 36 | N116: 36 | O116: 0.0309 | P116: 297 | Q116: 297 | R116: 0.448 | S116: 65 | T116: 63.5 | U116: 1.48 | V116: Protection solaire, stores à projection avec moteur
A117: 05.017 | B117: Sonnenschutz, Lamellenstoren motorisiert | C117: 91.115 | D117: Entsorgungsmix, Sonnenschutz, Lamellenstoren motorisiert | E117: - | F117: m2 | G117: 111000 | H117: 110000 | I117: 633 | J117: 295 | K117: 295 | L117: 0.401 | M117: 32.4 | N117: 32.3 | O117: 0.0276 | P117: 263 | Q117: 262 | R117: 0.374 | S117: 57.4 | T117: 56.3 | U117: 1.11 | V117: Protection solaire, stores vénitiens avec moteur
A118: 05.019 | B118: Sonnenschutz, Rollladen motorisiert | C118: 91.118 | D118: Entsorgungsmix, Sonnenschutz, Rollladen motorisiert | E118: - | F118: m2 | G118: 138000 | H118: 137000 | I118: 284 | J118: 376 | K118: 376 | L118: 0.394 | M118: 44.5 | N118: 44.5 | O118: 0.0286 | P118: 331 | Q118: 331 | R118: 0.365 | S118: 71.9 | T118: 71.5 | U118: 0.408 | V118: Protection solaire, contrevent sur enrouleur avec moteur
A119: Bezugsgrössen: Fassade: Glas- und Rahmenfläche; Fensterrahmen: Rahmenfläche; Isolierverglasung: Glasfläche; Sonnenschutz: Fensterlichtmass; Valeurs de référence: façade: surface en verre et cadres; cadres de fenêtre; double vitrage: surface en verre; protection solaire: fenêtres
A120: 06 | B120: Metallbaustoffe | E120: kg/m3 | V120: Produits en métal
...

Sheet ImportGebäudetechnik
A1: Name | B1: ProductKey | C1: Description | D1: Picture | E1: Product sections | F1: Type | G1: SubType | H1: vyzn.catalogue.ch.minergie.eco.MepClassification | I1: vyzn.catalogue.Density | J1: vyzn.catalogue.ch.KBOB2022.UBPTotal | K1: vyzn.catalogue.ch.KBOB2022.UBPProduction | L1: vyzn.catalogue.ch.KBOB2022.UBPDisposal | M1: vyzn.catalogue.ch.KBOB2022.RenewableEnergyTotal | N1: vyzn.catalogue.ch.KBOB2022.RenewableEnergyProduction | O1: vyzn.catalogue.ch.KBOB2022.RenewableEnergyDisposal | P1: vyzn.catalogue.ch.KBOB2022.GreyEnergyTotal | Q1: vyzn.catalogue.ch.KBOB2022.GreyEnergyProduction | R1: vyzn.catalogue.ch.KBOB2022.GreyEnergyDisposal | S1: vyzn.catalogue.ch.KBOB2022.GHGEmissionsTotal | T1: vyzn.catalogue.ch.KBOB2022.GHGEmissionsProduction | U1: vyzn.catalogue.ch.KBOB2022.GHGEmissionsDisposal | V1: vyzn.catalogue.ch.KBOB2022.LCARefUnit | W1: vyzn.catalogue.ch.KBOB2022.LCARefDimension | X1: vyzn.catalogue.ch.KBOB2022.BiogenicCarbon | Y1: KBOB REF | Z1: vyzn.catalogue.SourceENV | AA1: categoryPath | AB1: vyzn.catalogue.lifeCycle
A2: 31.001 Wärmeerzeuger, spez. Leistungsbedarf 10 W/m2 (KBOB.2016) | B2: 31.001 Wärmeerzeuger, spez. Leistungsbedarf 10 W/m2 (KBOB.2016) | F2: BUILDING_TECHNOLOGY | G2: BUILDING_TECHNOLOGY_HEATING | H2: heatGeneration | J2: 1200.000000 | K2: 1190.000000 | L2: 10.600000 | M2: 0.236000 | N2: 0.236000 | O2: 0.000317 | P2: 2.280000 | Q2: 2.260000 | R2: 0.018100 | S2: 0.512000 | T2: 0.501000 | U2: 0.010900 | V2: m2 | W2: energyReferenceArea | X2: 0 | Y2: 31.001 | Z2: KBOB 2016 | AA2: Alle > GEBÄUDETECHNIK > kbob.admin.ch > KBOB / ecobau / IPB 2009/1:2016 | AB2: 20
A3: 31.002 Wärmeerzeuger, spez. Leistungsbedarf 30 W/m2 (KBOB.2016) | B3: 31.002 Wärmeerzeuger, spez. Leistungsbedarf 30 W/m2 (KBOB.2016) | F3: BUILDING_TECHNOLOGY | G3: BUILDING_TECHNOLOGY_HEATING | H3: heatGeneration | J3: 3590.000000 | K3: 3560.000000 | L3: 31.800000 | M3: 0.708000 | N3: 0.707000 | O3: 0.000952 | P3: 6.830000 | Q3: 6.780000 | R3: 0.054400 | S3: 1.530000 | T3: 1.500000 | U3: 0.032700 | V3: m2 | W3: energyReferenceArea | X3: 0 | Y3: 31.002 | Z3: KBOB 2016 | AA3: Alle > GEBÄUDETECHNIK > kbob.admin.ch > KBOB / ecobau / IPB 2009/1:2016 | AB3: 20
A4: 31.003 Wärmeerzeuger, spez. Leistungsbedarf 50 W/m2 (KBOB.2016) | B4: 31.003 Wärmeerzeuger, spez. Leistungsbedarf 50 W/m2 (KBOB.2016) | F4: BUILDING_TECHNOLOGY | G4: BUILDING_TECHNOLOGY_HEATING | H4: heatGeneration | J4: 5990.000000 | K4: 5930.000000 | L4: 53.000000 | M4: 1.180000 | N4: 1.180000 | O4: 0.001590 | P4: 11.400000 | Q4: 11.300000 | R4: 0.090600 | S4: 2.560000 | T4: 2.500000 | U4: 0.054500 | V4: m2 | W4: energyReferenceArea | X4: 0 | Y4: 31.003 | Z4: KBOB 2016 | AA4: Alle > GEBÄUDETECHNIK > kbob.admin.ch > KBOB / ecobau / IPB 2009/1:2016 | AB4: 20
A5: 31.021 Wärmeverteilung Wohngebäude (KBOB.2016) | B5: 31.021 Wärmeverteilung Wohngebäude (KBOB.2016) | F5: BUILDING_TECHNOLOGY | G5: BUILDING_TECHNOLOGY_HEATING | H5: heatDistribution | J5: 5480.000000 | K5: 4670.000000 | L5: 807.000000 | M5: 1.510000 | N5: 1.140000 | O5: 0.370000 | P5: 14.300000 | Q5: 12.000000 | R5: 2.330000 | S5: 3.070000 | T5: 2.390000 | U5: 0.674000 | V5: m2 | W5: energyReferenceArea | X5: 0 | Y5: 31.021 | Z5: KBOB 2016 | AA5: Alle > GEBÄUDETECHNIK > kbob.admin.ch > KBOB / ecobau / IPB 2009/1:2016 | AB5: 30
A6: 31.022 Wärmeverteilung Bürogebäude (KBOB.2016) | B6: 31.022 Wärmeverteilung Bürogebäude (KBOB.2016) | F6: BUILDING_TECHNOLOGY | G6: BUILDING_TECHNOLOGY_HEATING | H6: heatDistribution | J6: 15000.000000 | K6: 13900.000000 | L6: 1090.000000 | M6: 2.680000 | N6: 2.250000 | O6: 0.433000 | P6: 32.700000 | Q6: 29.900000 | R6: 2.790000 | S6: 7.620000 | T6: 6.560000 | U6: 1.060000 | V6: m2 | W6: energyReferenceArea | X6: 0 | Y6: 31.022 | Z6: KBOB 2016 | AA6: Alle > GEBÄUDETECHNIK > kbob.admin.ch > KBOB / ecobau / IPB 2009/1:2016 | AB6: 30
A7: 31.023 Wärmeabgabe über Heizkörper (KBOB.2016) | B7: 31.023 Wärmeabgabe über Heizkörper (KBOB.2016) | F7: BUILDING_TECHNOLOGY | G7: BUILDING_TECHNOLOGY_HEATING | H7: heatEmission | J7: 10200.000000 | K7: 10200.000000 | L7: 17.900000 | M7: 1.630000 | N7: 1.620000 | O7: 0.001850 | P7: 22.800000 | Q7: 22.700000 | R7: 0.035200 | S7: 5.460000 | T7: 5.440000 | U7: 0.022700 | V7: m2 | W7: energyReferenceArea | X7: 0 | Y7: 31.023 | Z7: KBOB 2016 | AA7: Alle > GEBÄUDETECHNIK > kbob.admin.ch > KBOB / ecobau / IPB 2009/1:2016 | AB7: 30
A8: 31.024 Wärmeabgabe über Fussbodenheizung (KBOB.2016) | B8: 31.024 Wärmeabgabe über Fussbodenheizung (KBOB.2016) | F8: BUILDING_TECHNOLOGY | G8: BUILDING_TECHNOLOGY_HEATING | H8: heatEmission | J8: 4040.000000 | K8: 3040.000000 | L8: 997.000000 | M8: 1.480000 | N8: 1.480000 | O8: 0.001650 | P8: 22.300000 | Q8: 22.200000 | R8: 0.091700 | S8: 5.060000 | T8: 3.020000 | U8: 2.040000 | V8: m2 | W8: energyReferenceArea | X8: 0 | Y8: 31.024 | Z8: KBOB 2016 | AA8: Alle > GEBÄUDETECHNIK > kbob.admin.ch > KBOB / ecobau / IPB 2009/1:2016 | AB8: 30
A9: 31.025 Wärmeabgabe über Heizkühldecke (ohne Gips- oder Metalldecke) (KBOB.2016) | B9: 31.025 Wärmeabgabe über Heizkühldecke (ohne Gips- oder Metalldecke) (KBOB.2016) | F9: BUILDING_TECHNOLOGY | G9: BUILDING_TECHNOLOGY_HEATING | H9: heatEmission | J9: 39400.000000 | K9: 39400.000000 | L9: 70.400000 | M9: 4.470000 | N9: 4.470000 | O9: 0.001590 | P9: 26.400000 | Q9: 26.300000 | R9: 0.030600 | S9: 5.770000 | T9: 5.640000 | U9: 0.134000 | V9: m2 | W9: energyReferenceArea | X9: 0 | Y9: 31.025 | Z9: KBOB 2016 | AA9: Alle > GEBÄUDETECHNIK > kbob.admin.ch > KBOB / ecobau / IPB 2009/1:2016 | AB9: 30
A10: 31.015 Wärmeverteilung und Abgabe, Luftheizung (KBOB.2016) | B10: 31.015 Wärmeverteilung und Abgabe, Luftheizung (KBOB.2016) | F10: BUILDING_TECHNOLOGY | G10: BUILDING_TECHNOLOGY_HEATING | H10: heatDistribution | J10: 2940.000000 | K10: 2910.000000 | L10: 33.600000 | M10: 0.325000 | N10: 0.325000 | O10: 0.000083 | P10: 7.960000 | Q10: 7.950000 | R10: 0.006480 | S10: 1.700000 | T10: 1.630000 | U10: 0.067200 | V10: m2 | W10: energyReferenceArea | X10: 0 | Y10: 31.015 | Z10: KBOB 2016 | AA10: Alle > GEBÄUDETECHNIK > kbob.admin.ch > KBOB / ecobau / IPB 2009/1:2016 | AB10: 30
A11: 31.016 Erdsonden, für Sole-Wasser-Wärmepumpe (KBOB.2016) | B11: 31.016 Erdsonden, für Sole-Wasser-Wärmepumpe (KBOB.2016) | F11: BUILDING_TECHNOLOGY | G11: BUILDING_TECHNOLOGY_HEATING | H11: geothermalProbe | J11: 34600.000000 | K11: 30500.000000 | L11: 4100.000000 | M11: 2.870000 | N11: 2.610000 | O11: 0.255000 | P11: 130.000000 | Q11: 129.000000 | R11: 1.480000 | S11: 28.100000 | T11: 25.300000 | U11: 2.730000 | V11: m | W11: probeLength | X11: 0 | Y11: 31.016 | Z11: KBOB 2016 | AA11: Alle > GEBÄUDETECHNIK > kbob.admin.ch > KBOB / ecobau / IPB 2009/1:2016 | AB11: 40
A12: 31.017 Sole-Wasser Wärmepumpe 8 kW (KBOB.2016) | B12: 31.017 Sole-Wasser Wärmepumpe 8 kW (KBOB.2016) | F12: BUILDING_TECHNOLOGY | G12: BUILDING_TECHNOLOGY_HEATING | H12: heatGeneration | J12: 4220000.000000 | K12: 3860000.000000 | L12: 367000.000000 | M12: 506.000000 | N12: 503.000000 | O12: 3.820000 | P12: 5520.000000 | Q12: 5480.000000 | R12: 45.200000 | S12: 2180.000000 | T12: 1470.000000 | U12: 706.000000 | V12: Stk. | W12: device | X12: 0 | Y12: 31.017 | Z12: KBOB 2016 | AA12: Alle > GEBÄUDETECHNIK > kbob.admin.ch > KBOB / ecobau / IPB 2009/1:2016 | AB12: 20
A13: 31.018 Sole-Wasser Wärmepumpe 8 kW (KBOB.2016) | B13: 31.018 Sole-Wasser Wärmepumpe 8 kW (KBOB.2016) | F13: BUILDING_TECHNOLOGY | G13: BUILDING_TECHNOLOGY_HEATING | H13: heatGeneration | J13: 22500.000000 | K13: 20600.000000 | L13: 1960.000000 | M13: 2.700000 | N13: 2.680000 | O13: 0.020400 | P13: 29.500000 | Q13: 29.200000 | R13: 0.241000 | S13: 11.600000 | T13: 7.860000 | U13: 3.770000 | V13: kg | W13: mass | X13: 0 | Y13: 31.018 | Z13: KBOB 2016 | AA13: Alle > GEBÄUDETECHNIK > kbob.admin.ch > KBOB / ecobau / IPB 2009/1:2016 | AB13: 20
... A15: 31.020 Luft-Wasser Wärmepumpe 8 kW (KBOB.2016) | B15: 31.020 Luft-Wasser Wärmepumpe 8 kW (KBOB.2016) | F15: BUILDING_TECHNOLOGY | G15: BUILDING_TECHNOLOGY_HEATING | H15: heatGeneration | J15: 22400.000000 | K15: 20200.000000 | L15: 2240.000000 | M15: 2.630000 | N15: 2.610000 | O15: 0.020600 | P15: 26.500000 | Q15: 26.200000 | R15: 0.248000 | S15: 12.000000 | T15: 7.620000 | U15: 4.330000 | V15: kg | W15: mass | X15: 0 | Y15: 31.020 | Z15: KBOB 2016 | AA15: Alle > GEBÄUDETECHNIK > kbob.admin.ch > KBOB / ecobau / IPB 2009/1:2016 | AB15: 20
A16: 31.007 Flachkollektor für Warmwasser EFH (KBOB.2016) | B16: 31.007 Flachkollektor für Warmwasser EFH (KBOB.2016) | F16: BUILDING_TECHNOLOGY | G16: BUILDING_TECHNOLOGY_HEATING | H16: heatGeneration | J16: 676000.000000 | K16: 676000.000000 | M16: 142.000000 | N16: 142.000000 | P16: 1140.000000 | Q16: 1140.000000 | S16: 256.000000 | T16: 256.000000 | V16: m2 | W16: collectorArea | X16: 0 | Y16: 31.007 | Z16: KBOB 2016 | AA16: Alle > GEBÄUDETECHNIK > kbob.admin.ch > KBOB / ecobau / IPB 2009/1:2016 | AB16: 30
A17: 31.008 Flachkollektor für Raumheizung und Warmwasser EFH (KBOB.2016) | B17: 31.008 Flachkollektor für Raumheizung und Warmwasser EFH (KBOB.2016) | F17: BUILDING_TECHNOLOGY | G17: BUILDING_TECHNOLOGY_HEATING | H17: heatGeneration | J17: 452000.000000 | K17: 452000.000000 | M17: 102.000000 | N17: 102.000000 | P17: 824.000000 | Q17: 824.000000 | S17: 184.000000 | T17: 184.000000 | V17: m2 | W17: collectorArea | X17: 0 | Y17: 31.008 | Z17: KBOB 2016 | AA17: Alle > GEBÄUDETECHNIK > kbob.admin.ch > KBOB / ecobau / IPB 2009/1:2016 | AB17: 30
A18: 31.009 Flachkollektor für Warmwasser MFH (KBOB.2016) | B18: 31.009 Flachkollektor für Warmwasser MFH (KBOB.2016) | F18: BUILDING_TECHNOLOGY | G18: BUILDING_TECHNOLOGY_HEATING | H18: heatGeneration | J18: 394000.000000 | K18: 394000.000000 | M18: 79.000000 | N18: 79.000000 | P18: 695.000000 | Q18: 695.000000 | S18: 155.000000 | T18: 155.000000 | V18: m2 | W18: collectorArea | X18: 0 | Y18: 31.009 | Z18: KBOB 2016 | AA18: Alle > GEBÄUDETECHNIK > kbob.admin.ch > KBOB / ecobau / IPB 2009/1:2016 | AB18: 30
A19: 31.010 Röhrenkollektor für Raumheizung und Warmwasser EFH (KBOB.2016) | B19: 31.010 Röhrenkollektor für Raumheizung und Warmwasser EFH (KBOB.2016) | F19: BUILDING_TECHNOLOGY | G19: BUILDING_TECHNOLOGY_HEATING | H19: heatGeneration | J19: 465000.000000 | K19: 465000.000000 | M19: 101.000000 | N19: 101.000000 | P19: 924.000000 | Q19: 924.000000 | S19: 208.000000 | T19: 208.000000 | V19: m2 | W19: collectorArea | X19: 0 | Y19: 31.010 | Z19: KBOB 2016 | AA19: Alle > GEBÄUDETECHNIK > kbob.admin.ch > KBOB / ecobau / IPB 2009/1:2016 | AB19: 30
A20: 32.011 Lüftungsanlage, spez. Luftmenge 1 m3/hm2 EBF (KBOB.2016) | B20: 32.011 Lüftungsanlage, spez. Luftmenge 1 m3/hm2 EBF (KBOB.2016) | F20: BUILDING_TECHNOLOGY | G20: BUILDING_TECHNOLOGY_VENTILATION | H20: ventilation | J20: 31700.000000 | K20: 31400.000000 | L20: 222.000000 | M20: 4.350000 | N20: 4.350000 | O20: 0.006950 | P20: 54.500000 | Q20: 54.300000 | R20: 0.208000 | S20: 12.700000 | T20: 12.300000 | U20: 0.345000 | V20: m2 | W20: energyReferenceArea | X20: 0 | Y20: 32.011 | Z20: KBOB 2016 | AA20: Alle > GEBÄUDETECHNIK > kbob.admin.ch > KBOB / ecobau / IPB 2009/1:2016 | AB20: 30
A21: 32.005 Lüftungsanlage, spez. Luftmenge 2 m3/hm2 EBF (KBOB.2016) | B21: 32.005 Lüftungsanlage, spez. Luftmenge 2 m3/hm2 EBF (KBOB.2016) | F21: BUILDING_TECHNOLOGY | G21: BUILDING_TECHNOLOGY_VENTILATION | H21: ventilation | J21: 42700.000000 | K21: 42400.000000 | L21: 311.000000 | M21: 5.850000 | N21: 5.840000 | O21: 0.009470 | P21: 73.600000 | Q21: 73.300000 | R21: 0.287000 | S21: 17.100000 | T21: 16.600000 | U21: 0.485000 | V21: m2 | W21: energyReferenceArea | X21: 0 | Y21: 32.005 | Z21: KBOB 2016 | AA21: Alle > GEBÄUDETECHNIK > kbob.admin.ch > KBOB / ecobau / IPB 2009/1:2016 | AB21: 30
A22: 32.006 Lüftungsanlage, spez. Luftmenge 4 m3/hm2 EBF (KBOB.2016) | B22: 32.006 Lüftungsanlage, spez. Luftmenge 4 m3/hm2 EBF (KBOB.2016) | F22: BUILDING_TECHNOLOGY | G22: BUILDING_TECHNOLOGY_VENTILATION | H22: ventilation | J22: 64800.000000 | K22: 64300.000000 | L22: 488.000000 | M22: 8.840000 | N22: 8.830000 | O22: 0.014500 | P22: 112.000000 | Q22: 111.000000 | R22: 0.444000 | S22: 25.900000 | T22: 25.200000 | U22: 0.763000 | V22: m2 | W22: energyReferenceArea | X22: 0 | Y22: 32.006 | Z22: KBOB 2016 | AA22: Alle > GEBÄUDETECHNIK > kbob.admin.ch > KBOB / ecobau / IPB 2009/1:2016 | AB22: 30
A23: 32.007 Lüftungsanlage, spez. Luftmenge 6 m3/hm2 EBF (KBOB.2016) | B23: 32.007 Lüftungsanlage, spez. Luftmenge 6 m3/hm2 EBF (KBOB.2016) | F23: BUILDING_TECHNOLOGY | G23: BUILDING_TECHNOLOGY_VENTILATION | H23: ventilation | J23: 86900.000000 | K23: 86200.000000 | L23: 666.000000 | M23: 11.800000 | N23: 11.800000 | O23: 0.019600 | P23: 150.000000 | Q23: 149.000000 | R23: 0.601000 | S23: 34.800000 | T23: 33.700000 | U23: 1.040000 | V23: m2 | W23: energyReferenceArea | X23: 0 | Y23: 32.007 | Z23: KBOB 2016 | AA23: Alle > GEBÄUDETECHNIK > kbob.admin.ch > KBOB / ecobau / IPB 2009/1:2016 | AB23: 30
A24: 32.012 Lüftungsanlage, spez. Luftmenge 8 m3/hm2 EBF (KBOB.2016) | B24: 32.012 Lüftungsanlage, spez. Luftmenge 8 m3/hm2 EBF (KBOB.2016) | F24: BUILDING_TECHNOLOGY | G24: BUILDING_TECHNOLOGY_VENTILATION | H24: ventilation | J24: 109000.000000 | K24: 108000.000000 | L24: 843.000000 | M24: 14.800000 | N24: 14.800000 | O24: 0.024600 | P24: 188.000000 | Q24: 187.000000 | R24: 0.758000 | S24: 43.600000 | T24: 42.300000 | U24: 1.320000 | V24: m2 | W24: energyReferenceArea | X24: 0 | Y24: 32.012 | Z24: KBOB 2016 | AA24: Alle > GEBÄUDETECHNIK > kbob.admin.ch > KBOB / ecobau / IPB 2009/1:2016 | AB24: 30
A25: 32.001 Lüftungsanlage Wohnen, Blechkanäle, inkl. Küchenabluft (KBOB.2016) | B25: 32.001 Lüftungsanlage Wohnen, Blechkanäle, inkl. Küchenabluft (KBOB.2016) | F25: BUILDING_TECHNOLOGY | G25: BUILDING_TECHNOLOGY_VENTILATION | H25: ventilation | J25: 45200.000000 | K25: 45000.000000 | L25: 182.000000 | M25: 3.990000 | N25: 3.990000 | O25: 0.003880 | P25: 53.300000 | Q25: 53.200000 | R25: 0.083100 | S25: 12.000000 | T25: 11.700000 | U25: 0.299000 | V25: m2 | W25: energyReferenceArea | X25: 0 | Y25: 32.001 | Z25: KBOB 2016 | AA25: Alle > GEBÄUDETECHNIK > kbob.admin.ch > KBOB / ecobau / IPB 2009/1:2016 | AB25: 30
A26: 32.002 Lüftungsanlage Wohnen, PE-Kanäle, inkl. Küchenabluft (KBOB.2016) | B26: 32.002 Lüftungsanlage Wohnen, PE-Kanäle, inkl. Küchenabluft (KBOB.2016) | F26: BUILDING_TECHNOLOGY | G26: BUILDING_TECHNOLOGY_VENTILATION | H26: ventilation | J26: 22000.000000 | K26: 21600.000000 | L26: 371.000000 | M26: 2.360000 | N26: 2.360000 | O26: 0.002530 | P26: 32.700000 | Q26: 32.600000 | R26: 0.074300 | S26: 7.320000 | T26: 6.600000 | U26: 0.724000 | V26: m2 | W26: energyReferenceArea | X26: 0 | Y26: 32.002 | Z26: KBOB 2016 | AA26: Alle > GEBÄUDETECHNIK > kbob.admin.ch > KBOB / ecobau / IPB 2009/1:2016 | AB26: 30
A27: 32.003 Abluftanlage Küche und Bad (KBOB.2016) | B27: 32.003 Abluftanlage Küche und Bad (KBOB.2016) | F27: BUILDING_TECHNOLOGY | G27: BUILDING_TECHNOLOGY_VENTILATION | H27: ventilation | J27: 13300.000000 | K27: 13300.000000 | L27: 65.700000 | M27: 0.981000 | N27: 0.980000 | O27: 0.000208 | P27: 15.100000 | Q27: 15.100000 | R27: 0.016500 | S27: 3.400000 | T27: 3.280000 | U27: 0.126000 | V27: m2 | W27: energyReferenceArea | X27: 0 | Y27: 32.003 | Z27: KBOB 2016 | AA27: Alle > GEBÄUDETECHNIK > kbob.admin.ch > KBOB / ecobau / IPB 2009/1:2016 | AB27: 30
A28: 32.004 Erdregister zu Lüftungsanlage Wohnen (KBOB.2016) | B28: 32.004 Erdregister zu Lüftungsanlage Wohnen (KBOB.2016) | F28: BUILDING_TECHNOLOGY | G28: BUILDING_TECHNOLOGY_VENTILATION | H28: ventilation | J28: 4550.000000 | K28: 3220.000000 | L28: 1330.000000 | M28: 0.554000 | N28: 0.502000 | O28: 0.051800 | P28: 16.100000 | Q28: 14.800000 | R28: 1.280000 | S28: 4.550000 | T28: 2.920000 | U28: 1.630000 | V28: m2 | W28: energyReferenceArea | X28: 0 | Y28: 32.004 | Z28: KBOB 2016 | AA28: Alle > GEBÄUDETECHNIK > kbob.admin.ch > KBOB / ecobau / IPB 2009/1:2016 | AB28: 30
A29: 32.008 Erdregister kurz zu Lüftungsanlage Büro (0.27 m/m2 EBF) (KBOB.2016) | B29: 32.008 Erdregister kurz zu Lüftungsanlage Büro (0.27 m/m2 EBF) (KBOB.2016) | F29: BUILDING_TECHNOLOGY | G29: BUILDING_TECHNOLOGY_VENTILATION | H29: ventilation | J29: 7890.000000 | K29: 5590.000000 | L29: 2300.000000 | M29: 0.960000 | N29: 0.870000 | O29: 0.089800 | P29: 27.900000 | Q29: 25.700000 | R29: 2.220000 | S29: 7.890000 | T29: 5.060000 | U29: 2.820000 | V29: m2 | W29: energyReferenceArea | X29: 0 | Y29: 32.008 | Z29: KBOB 2016 | AA29: Alle > GEBÄUDETECHNIK > kbob.admin.ch > KBOB / ecobau / IPB 2009/1:2016 | AB29: 30
A30: 32.009 Erdregister lang zu Lüftungsanlage Büro (0.67 m/m2 EBF) (KBOB.2016) | B30: 32.009 Erdregister lang zu Lüftungsanlage Büro (0.67 m/m2 EBF) (KBOB.2016) | F30: BUILDING_TECHNOLOGY | G30: BUILDING_TECHNOLOGY_VENTILATION | H30: ventilation | J30: 19700.000000 | K30: 14000.000000 | L30: 5760.000000 | M30: 2.400000 | N30: 2.180000 | O30: 0.224000 | P30: 69.700000 | Q30: 64.200000 | R30: 5.540000 | S30: 19.700000 | T30: 12.700000 | U30: 7.050000 | V30: m2 | W30: energyReferenceArea | X30: 0 | Y30: 32.009 | Z30: KBOB 2016 | AA30: Alle > GEBÄUDETECHNIK > kbob.admin.ch > KBOB / ecobau / IPB 2009/1:2016 | AB30: 30
A31: 32.010 Einzelraumlüfer Fenstermodell 10-30 m3/h, ohne Montage (KBOB.2016) | B31: 32.010 Einzelraumlüfer Fenstermodell 10-30 m3/h, ohne Montage (KBOB.2016) | F31: BUILDING_TECHNOLOGY | G31: BUILDING_TECHNOLOGY_VENTILATION | H31: ventilation | J31: 63200.000000 | K31: 59900.000000 | L31: 3260.000000 | M31: 109.000000 | N31: 109.000000 | O31: 0.075800 | P31: 220.000000 | Q31: 218.000000 | R31: 1.410000 | S31: 43.500000 | T31: 38.000000 | U31: 5.480000 | V31: Stk. | W31: device | X31: 0 | Y31: 32.010 | Z31: KBOB 2016 | AA31: Alle > GEBÄUDETECHNIK > kbob.admin.ch > KBOB / ecobau / IPB 2009/1:2016 | AB31: 30
... A36: 34.002 Elektroanlagen Büro (KBOB.2016) | B36: 34.002 Elektroanlagen Büro (KBOB.2016) | F36: BUILDING_TECHNOLOGY | G36: BUILDING_TECHNOLOGY_ELECTRICAL | H36: electrical | J36: 117000.000000 | K36: 116000.000000 | L36: 900.000000 | M36: 76.200000 | N36: 76.100000 | O36: 0.048300 | P36: 114.000000 | Q36: 113.000000 | R36: 0.832000 | S36: 23.800000 | T36: 22.400000 | U36: 1.450000 | V36: m2 | W36: energyReferenceArea | X36: 0 | Y36: 34.002 | Z36: KBOB 2016 | AA36: Alle > GEBÄUDETECHNIK > kbob.admin.ch > KBOB / ecobau / IPB 2009/1:2016 | AB36: 30
A37: 34.024 Solarstromanlage (KBOB.2016) | B37: 34.024 Solarstromanlage (KBOB.2016) | F37: BUILDING_TECHNOLOGY | G37: BUILDING_TECHNOLOGY_ELECTRICAL | H37: photovoltaicSystem | J37: 3170000.000000 | K37: 3170000.000000 | M37: 905.000000 | N37: 905.000000 | P37: 7390.000000 | Q37: 7390.000000 | S37: 2080.000000 | T37: 2080.000000 | V37: kWp | W37: maxPower | X37: 0 | Y37: 34.024 | Z37: KBOB 2016 | AA37: Alle > GEBÄUDETECHNIK > kbob.admin.ch > KBOB / ecobau / IPB 2009/1:2016 | AB37: 30
A38: 34.025 Solarstromanlage Schrägdach (KBOB.2016) | B38: 34.025 Solarstromanlage Schrägdach (KBOB.2016) | F38: BUILDING_TECHNOLOGY | G38: BUILDING_TECHNOLOGY_ELECTRICAL | H38: photovoltaicSystem | J38: 3190000.000000 | K38: 3190000.000000 | M38: 897.000000 | N38: 897.000000 | P38: 7290.000000 | Q38: 7290.000000 | S38: 2030.000000 | T38: 2030.000000 | V38: kWp | W38: maxPower | X38: 0 | Y38: 34.025 | Z38: KBOB 2016 | AA38: Alle > GEBÄUDETECHNIK > kbob.admin.ch > KBOB / ecobau / IPB 2009/1:2016 | AB38: 30
A39: 34.026 Solarstromanlage Flachdach (KBOB.2016) | B39: 34.026 Solarstromanlage Flachdach (KBOB.2016) | F39: BUILDING_TECHNOLOGY | G39: BUILDING_TECHNOLOGY_ELECTRICAL | H39: photovoltaicSystem | J39: 3070000.000000 | K39: 3070000.000000 | M39: 959.000000 | N39: 959.000000 | P39: 8020.000000 | Q39: 8020.000000 | S39: 2320.000000 | T39: 2320.000000 | V39: kWp | W39: maxPower | X39: 0 | Y39: 34.026 | Z39: KBOB 2016 | AA39: Alle > GEBÄUDETECHNIK > kbob.admin.ch > KBOB / ecobau / IPB 2009/1:2016 | AB39: 30
A40: 34.027 Solarstromanlage Fassade (KBOB.2016) | B40: 34.027 Solarstromanlage Fassade (KBOB.2016) | F40: BUILDING_TECHNOLOGY | G40: BUILDING_TECHNOLOGY_ELECTRICAL | H40: photovoltaicSystem | J40: 3170000.000000 | K40: 3170000.000000 | M40: 905.000000 | N40: 905.000000 | P40: 7460.000000 | Q40: 7460.000000 | S40: 2140.000000 | T40: 2140.000000 | V40: kWp | W40: maxPower | X40: 0 | Y40: 34.027 | Z40: KBOB 2016 | AA40: Alle > GEBÄUDETECHNIK > kbob.admin.ch > KBOB / ecobau / IPB 2009/1:2016 | AB40: 30

Sheet ConsolidatedGebäudetechnik
A1: Name | B1: ProductKey | C1: Description | D1: Picture | E1: Product sections | F1: Type | G1: SubType | H1: vyzn.catalogue.ch.minergie.eco.MepClassification | I1: vyzn.catalogue.Density | J1: vyzn.catalogue.ch.KBOB2022.UBPTotal | K1: vyzn.catalogue.ch.KBOB2022.UBPProduction | L1: vyzn.catalogue.ch.KBOB2022.UBPDisposal | M1: vyzn.catalogue.ch.KBOB2022.RenewableEnergyTotal | N1: vyzn.catalogue.ch.KBOB2022.RenewableEnergyProduction | O1: vyzn.catalogue.ch.KBOB2022.RenewableEnergyDisposal | P1: vyzn.catalogue.ch.KBOB2022.GreyEnergyTotal | Q1: vyzn.catalogue.ch.KBOB2022.GreyEnergyProduction | R1: vyzn.catalogue.ch.KBOB2022.GreyEnergyDisposal | S1: vyzn.catalogue.ch.KBOB2022.GHGEmissionsTotal | T1: vyzn.catalogue.ch.KBOB2022.GHGEmissionsProduction | U1: vyzn.catalogue.ch.KBOB2022.GHGEmissionsDisposal | V1: vyzn.catalogue.ch.KBOB2022.LCARefUnit | W1: vyzn.catalogue.ch.KBOB2022.LCARefDimension | X1: vyzn.catalogue.ch.KBOB2022.BiogenicCarbon | Y1: KBOB REF | Z1: vyzn.catalogue.SourceENV | AA1: categoryPath | AB1: vyzn.catalogue.lifeCycle
A2: ='Gebäudetechnik Technique'!A11 & " " & 'Gebäudetechnik Technique'!B11 & " (KBOB.2016)" -> 31.001 Wärmeerzeuger, spez. Leistungsbedarf 10 W/m2 (KBOB.2016) | B2: =A2 -> 31.001 Wärmeerzeuger, spez. Leistungsbedarf 10 W/m2 (KBOB.2016) | F2: BUILDING_TECHNOLOGY | G2: =IF(LEFT(A2, 2)="31", "BUILDING_TECHNOLOGY_HEATING", IF(LEFT(A2, 2)="32", "BUILDING_TECHNOLOGY_VENTILATION", IF(LEFT(A2, 2)="33", "BUILDING_TECHNOLOGY_SANITARY", IF(LEFT(A2, 2)="34", "BUILDING_TECHNOLOGY_ELECTRICAL")))) -> BUILDING_TECHNOLOGY_HEATING | H2: =VLOOKUP(LEFT(A2,6),MepClassificationAndLifecycle!A2:C68,2,false) -> heatGeneration | J2: ='Gebäudetechnik Technique'!G11 -> 1200 | K2: ='Gebäudetechnik Technique'!H11 -> 1190 | L2: ='Gebäudetechnik Technique'!I11 -> 10.6 | M2: ='Gebäudetechnik Technique'!M11 -> 0.236 | N2: ='Gebäudetechnik Technique'!N11 -> 0.236 | O2: ='Gebäudetechnik Technique'!O11 -> 0.000317 | P2: ='Gebäudetechnik Technique'!P11 -> 2.28 | Q2: ='Gebäudetechnik Technique'!Q11 -> 2.26 | R2: ='Gebäudetechnik Technique'!R11 -> 0.0181 | S2: ='Gebäudetechnik Technique'!S11 -> 0.512 | T2: ='Gebäudetechnik Technique'!T11 -> 0.501 | U2: ='Gebäudetechnik Technique'!U11 -> 0.0109 | V2: ='Gebäudetechnik Technique'!F11 -> m2 | W2: =VLOOKUP('Gebäudetechnik Technique'!E11,RefDimensions!A$2:B$15,2,false) -> energyReferenceArea | X2: 0 | Y2: ='Gebäudetechnik Technique'!A11 -> 31.001 | Z2: KBOB 2016 | AA2: ="Alle > " & SWITCH(F2, "COMPONENT","BAUTEILE", "OTHER_RESOURCE", "RESSOURCEN", "BUILDING_TECHNOLOGY", "GEBÄUDETECHNIK", "MATERIAL", "MATERIALIEN") & " > kbob.admin.ch > KBOB / ecobau / IPB 2009/1:2016" -> Alle > GEBÄUDETECHNIK > kbob.admin.ch > KBOB / ecobau / IPB 2009/1:2016 | AB2: =VLOOKUP(LEFT(A2,6),MepClassificationAndLifecycle!A2:C68,3,false) -> 20
A3: ='Gebäudetechnik Technique'!A12 & " " & 'Gebäudetechnik Technique'!B12 & " (KBOB.2016)" -> 31.002 Wärmeerzeuger, spez. Leistungsbedarf 30 W/m2 (KBOB.2016) | B3: =A3 -> 31.002 Wärmeerzeuger, spez. Leistungsbedarf 30 W/m2 (KBOB.2016) | F3: BUILDING_TECHNOLOGY | G3: =IF(LEFT(A3, 2)="31", "BUILDING_TECHNOLOGY_HEATING", IF(LEFT(A3, 2)="32", "BUILDING_TECHNOLOGY_VENTILATION", IF(LEFT(A3, 2)="33", "BUILDING_TECHNOLOGY_SANITARY", IF(LEFT(A3, 2)="34", "BUILDING_TECHNOLOGY_ELECTRICAL")))) -> BUILDING_TECHNOLOGY_HEATING | H3: =VLOOKUP(LEFT(A3,6),MepClassificationAndLifecycle!A3:C69,2,false) -> heatGeneration | J3: ='Gebäudetechnik Technique'!G12 -> 3590 | K3: ='Gebäudetechnik Technique'!H12 -> 3560 | L3: ='Gebäudetechnik Technique'!I12 -> 31.8 | M3: ='Gebäudetechnik Technique'!M12 -> 0.708 | N3: ='Gebäudetechnik Technique'!N12 -> 0.707 | O3: ='Gebäudetechnik Technique'!O12 -> 0.000952 | P3: ='Gebäudetechnik Technique'!P12 -> 6.83 | Q3: ='Gebäudetechnik Technique'!Q12 -> 6.78 | R3: ='Gebäudetechnik Technique'!R12 -> 0.0544 | S3: ='Gebäudetechnik Technique'!S12 -> 1.53 | T3: ='Gebäudetechnik Technique'!T12 -> 1.5 | U3: ='Gebäudetechnik Technique'!U12 -> 0.0327 | V3: ='Gebäudetechnik Technique'!F12 -> m2 | W3: =VLOOKUP('Gebäudetechnik Technique'!E12,RefDimensions!A$2:B$15,2,false) -> energyReferenceArea | X3: 0 | Y3: ='Gebäudetechnik Technique'!A12 -> 31.002 | Z3: KBOB 2016 | AA3: ="Alle > " & SWITCH(F3, "COMPONENT","BAUTEILE", "OTHER_RESOURCE", "RESSOURCEN", "BUILDING_TECHNOLOGY", "GEBÄUDETECHNIK", "MATERIAL", "MATERIALIEN") & " > kbob.admin.ch > KBOB / ecobau / IPB 2009/1:2016" -> Alle > GEBÄUDETECHNIK > kbob.admin.ch > KBOB / ecobau / IPB 2009/1:2016 | AB3: =VLOOKUP(LEFT(A3,6),MepClassificationAndLifecycle!A3:C69,3,false) -> 20
A4: ='Gebäudetechnik Technique'!A13 & " " & 'Gebäudetechnik Technique'!B13 & " (KBOB.2016)" -> 31.003 Wärmeerzeuger, spez. Leistungsbedarf 50 W/m2 (KBOB.2016) | B4: =A4 -> 31.003 Wärmeerzeuger, spez. Leistungsbedarf 50 W/m2 (KBOB.2016) | F4: BUILDING_TECHNOLOGY | G4: =IF(LEFT(A4, 2)="31", "BUILDING_TECHNOLOGY_HEATING", IF(LEFT(A4, 2)="32", "BUILDING_TECHNOLOGY_VENTILATION", IF(LEFT(A4, 2)="33", "BUILDING_TECHNOLOGY_SANITARY", IF(LEFT(A4, 2)="34", "BUILDING_TECHNOLOGY_ELECTRICAL")))) -> BUILDING_TECHNOLOGY_HEATING | H4: =VLOOKUP(LEFT(A4,6),MepClassificationAndLifecycle!A4:C70,2,false) -> heatGeneration | J4: ='Gebäudetechnik Technique'!G13 -> 5990 | K4: ='Gebäudetechnik Technique'!H13 -> 5930 | L4: ='Gebäudetechnik Technique'!I13 -> 53 | M4: ='Gebäudetechnik Technique'!M13 -> 1.18 | N4: ='Gebäudetechnik Technique'!N13 -> 1.18 | O4: ='Gebäudetechnik Technique'!O13 -> 0.00159 | P4: ='Gebäudetechnik Technique'!P13 -> 11.4 | Q4: ='Gebäudetechnik Technique'!Q13 -> 11.3 | R4: ='Gebäudetechnik Technique'!R13 -> 0.0906 | S4: ='Gebäudetechnik Technique'!S13 -> 2.56 | T4: ='Gebäudetechnik Technique'!T13 -> 2.5 | U4: ='Gebäudetechnik Technique'!U13 -> 0.0545 | V4: ='Gebäudetechnik Technique'!F13 -> m2 | W4: =VLOOKUP('Gebäudetechnik Technique'!E13,RefDimensions!A$2:B$15,2,false) -> energyReferenceArea | X4: 0 | Y4: ='Gebäudetechnik Technique'!A13 -> 31.003 | Z4: KBOB 2016 | AA4: ="Alle > " & SWITCH(F4, "COMPONENT","BAUTEILE", "OTHER_RESOURCE", "RESSOURCEN", "BUILDING_TECHNOLOGY", "GEBÄUDETECHNIK", "MATERIAL", "MATERIALIEN") & " > kbob.admin.ch > KBOB / ecobau / IPB 2009/1:2016" -> Alle > GEBÄUDETECHNIK > kbob.admin.ch > KBOB / ecobau / IPB 2009/1:2016 | AB4: =VLOOKUP(LEFT(A4,6),MepClassificationAndLifecycle!A4:C70,3,false) -> 20
A5: ='Gebäudetechnik Technique'!A14 & " " & 'Gebäudetechnik Technique'!B14 & " (KBOB.2016)" -> 31.021 Wärmeverteilung Wohngebäude (KBOB.2016) | B5: =A5 -> 31.021 Wärmeverteilung Wohngebäude (KBOB.2016) | F5: BUILDING_TECHNOLOGY | G5: =IF(LEFT(A5, 2)="31", "BUILDING_TECHNOLOGY_HEATING", IF(LEFT(A5, 2)="32", "BUILDING_TECHNOLOGY_VENTILATION", IF(LEFT(A5, 2)="33", "BUILDING_TECHNOLOGY_SANITARY", IF(LEFT(A5, 2)="34", "BUILDING_TECHNOLOGY_ELECTRICAL")))) -> BUILDING_TECHNOLOGY_HEATING | H5: =VLOOKUP(LEFT(A5,6),MepClassificationAndLifecycle!A5:C71,2,false) -> heatDistribution | J5: ='Gebäudetechnik Technique'!G14 -> 5480 | K5: ='Gebäudetechnik Technique'!H14 -> 4670 | L5: ='Gebäudetechnik Technique'!I14 -> 807 | M5: ='Gebäudetechnik Technique'!M14 -> 1.51 | N5: ='Gebäudetechnik Technique'!N14 -> 1.14 | O5: ='Gebäudetechnik Technique'!O14 -> 0.37 | P5: ='Gebäudetechnik Technique'!P14 -> 14.3 | Q5: ='Gebäudetechnik Technique'!Q14 -> 12 | R5: ='Gebäudetechnik Technique'!R14 -> 2.33 | S5: ='Gebäudetechnik Technique'!S14 -> 3.07 | T5: ='Gebäudetechnik Technique'!T14 -> 2.39 | U5: ='Gebäudetechnik Technique'!U14 -> 0.674 | V5: ='Gebäudetechnik Technique'!F14 -> m2 | W5: =VLOOKUP('Gebäudetechnik Technique'!E14,RefDimensions!A$2:B$15,2,false) -> energyReferenceArea | X5: 0 | Y5: ='Gebäudetechnik Technique'!A14 -> 31.021 | Z5: KBOB 2016 | AA5: ="Alle > " & SWITCH(F5, "COMPONENT","BAUTEILE", "OTHER_RESOURCE", "RESSOURCEN", "BUILDING_TECHNOLOGY", "GEBÄUDETECHNIK", "MATERIAL", "MATERIALIEN") & " > kbob.admin.ch > KBOB / ecobau / IPB 2009/1:2016" -> Alle > GEBÄUDETECHNIK > kbob.admin.ch > KBOB / ecobau / IPB 2009/1:2016 | AB5: =VLOOKUP(LEFT(A5,6),MepClassificationAndLifecycle!A5:C71,3,false) -> 30
A6: ='Gebäudetechnik Technique'!A15 & " " & 'Gebäudetechnik Technique'!B15 & " (KBOB.2016)" -> 31.022 Wärmeverteilung Bürogebäude (KBOB.2016) | B6: =A6 -> 31.022 Wärmeverteilung Bürogebäude (KBOB.2016) | F6: BUILDING_TECHNOLOGY | G6: =IF(LEFT(A6, 2)="31", "BUILDING_TECHNOLOGY_HEATING", IF(LEFT(A6, 2)="32", "BUILDING_TECHNOLOGY_VENTILATION", IF(LEFT(A6, 2)="33", "BUILDING_TECHNOLOGY_SANITARY", IF(LEFT(A6, 2)="34", "BUILDING_TECHNOLOGY_ELECTRICAL")))) -> BUILDING_TECHNOLOGY_HEATING | H6: =VLOOKUP(LEFT(A6,6),MepClassificationAndLifecycle!A6:C72,2,false) -> heatDistribution | J6: ='Gebäudetechnik Technique'!G15 -> 15000 | K6: ='Gebäudetechnik Technique'!H15 -> 13900 | L6: ='Gebäudetechnik Technique'!I15 -> 1090 | M6: ='Gebäudetechnik Technique'!M15 -> 2.68 | N6: ='Gebäudetechnik Technique'!N15 -> 2.25 | O6: ='Gebäudetechnik Technique'!O15 -> 0.433 | P6: ='Gebäudetechnik Technique'!P15 -> 32.7 | Q6: ='Gebäudetechnik Technique'!Q15 -> 29.9 | R6: ='Gebäudetechnik Technique'!R15 -> 2.79 | S6: ='Gebäudetechnik Technique'!S15 -> 7.62 | T6: ='Gebäudetechnik Technique'!T15 -> 6.56 | U6: ='Gebäudetechnik Technique'!U15 -> 1.06 | V6: ='Gebäudetechnik Technique'!F15 -> m2 | W6: =VLOOKUP('Gebäudetechnik Technique'!E15,RefDimensions!A$2:B$15,2,false) -> energyReferenceArea | X6: 0 | Y6: ='Gebäudetechnik Technique'!A15 -> 31.022 | Z6: KBOB 2016 | AA6: ="Alle > " & SWITCH(F6, "COMPONENT","BAUTEILE", "OTHER_RESOURCE", "RESSOURCEN", "BUILDING_TECHNOLOGY", "GEBÄUDETECHNIK", "MATERIAL", "MATERIALIEN") & " > kbob.admin.ch > KBOB / ecobau / IPB 2009/1:2016" -> Alle > GEBÄUDETECHNIK > kbob.admin.ch > KBOB / ecobau / IPB 2009/1:2016 | AB6: =VLOOKUP(LEFT(A6,6),MepClassificationAndLifecycle!A6:C72,3,false) -> 30
A7: ='Gebäudetechnik Technique'!A16 & " " & 'Gebäudetechnik Technique'!B16 & " (KBOB.2016)" -> 31.023 Wärmeabgabe über Heizkörper (KBOB.2016) | B7: =A7 -> 31.023 Wärmeabgabe über Heizkörper (KBOB.2016) | F7: BUILDING_TECHNOLOGY | G7: =IF(LEFT(A7, 2)="31", "BUILDING_TECHNOLOGY_HEATING", IF(LEFT(A7, 2)="32", "BUILDING_TECHNOLOGY_VENTILATION", IF(LEFT(A7, 2)="33", "BUILDING_TECHNOLOGY_SANITARY", IF(LEFT(A7, 2)="34", "BUILDING_TECHNOLOGY_ELECTRICAL")))) -> BUILDING_TECHNOLOGY_HEATING | H7: =VLOOKUP(LEFT(A7,6),MepClassificationAndLifecycle!A7:C73,2,false) -> heatEmission | J7: ='Gebäudetechnik Technique'!G16 -> 10200 | K7: ='Gebäudetechnik Technique'!H16 -> 10200 | L7: ='Gebäudetechnik Technique'!I16 -> 17.9 | M7: ='Gebäudetechnik Technique'!M16 -> 1.63 | N7: ='Gebäudetechnik Technique'!N16 -> 1.62 | O7: ='Gebäudetechnik Technique'!O16 -> 0.00185 | P7: ='Gebäudetechnik Technique'!P16 -> 22.8 | Q7: ='Gebäudetechnik Technique'!Q16 -> 22.7 | R7: ='Gebäudetechnik Technique'!R16 -> 0.0352 | S7: ='Gebäudetechnik Technique'!S16 -> 5.46 | T7: ='Gebäudetechnik Technique'!T16 -> 5.44 | U7: ='Gebäudetechnik Technique'!U16 -> 0.0227 | V7: ='Gebäudetechnik Technique'!F16 -> m2 | W7: =VLOOKUP('Gebäudetechnik Technique'!E16,RefDimensions!A$2:B$15,2,false) -> energyReferenceArea | X7: 0 | Y7: ='Gebäudetechnik Technique'!A16 -> 31.023 | Z7: KBOB 2016 | AA7: ="Alle > " & SWITCH(F7, "COMPONENT","BAUTEILE", "OTHER_RESOURCE", "RESSOURCEN", "BUILDING_TECHNOLOGY", "GEBÄUDETECHNIK", "MATERIAL", "MATERIALIEN") & " > kbob.admin.ch > KBOB / ecobau / IPB 2009/1:2016" -> Alle > GEBÄUDETECHNIK > kbob.admin.ch > KBOB / ecobau / IPB 2009/1:2016 | AB7: =VLOOKUP(LEFT(A7,6),MepClassificationAndLifecycle!A7:C73,3,false) -> 30
A8: ='Gebäudetechnik Technique'!A17 & " " & 'Gebäudetechnik Technique'!B17 & " (KBOB.2016)" -> 31.024 Wärmeabgabe über Fussbodenheizung (KBOB.2016) | B8: =A8 -> 31.024 Wärmeabgabe über Fussbodenheizung (KBOB.2016) | F8: BUILDING_TECHNOLOGY | G8: =IF(LEFT(A8, 2)="31", "BUILDING_TECHNOLOGY_HEATING", IF(LEFT(A8, 2)="32", "BUILDING_TECHNOLOGY_VENTILATION", IF(LEFT(A8, 2)="33", "BUILDING_TECHNOLOGY_SANITARY", IF(LEFT(A8, 2)="34", "BUILDING_TECHNOLOGY_ELECTRICAL")))) -> BUILDING_TECHNOLOGY_HEATING | H8: =VLOOKUP(LEFT(A8,6),MepClassificationAndLifecycle!A8:C74,2,false) -> heatEmission | J8: ='Gebäudetechnik Technique'!G17 -> 4040 | K8: ='Gebäudetechnik Technique'!H17 -> 3040 | L8: ='Gebäudetechnik Technique'!I17 -> 997 | M8: ='Gebäudetechnik Technique'!M17 -> 1.48 | N8: ='Gebäudetechnik Technique'!N17 -> 1.48 | O8: ='Gebäudetechnik Technique'!O17 -> 0.00165 | P8: ='Gebäudetechnik Technique'!P17 -> 22.3 | Q8: ='Gebäudetechnik Technique'!Q17 -> 22.2 | R8: ='Gebäudetechnik Technique'!R17 -> 0.0917 | S8: ='Gebäudetechnik Technique'!S17 -> 5.06 | T8: ='Gebäudetechnik Technique'!T17 -> 3.02 | U8: ='Gebäudetechnik Technique'!U17 -> 2.04 | V8: ='Gebäudetechnik Technique'!F17 -> m2 | W8: =VLOOKUP('Gebäudetechnik Technique'!E17,RefDimensions!A$2:B$15,2,false) -> energyReferenceArea | X8: 0 | Y8: ='Gebäudetechnik Technique'!A17 -> 31.024 | Z8: KBOB 2016 | AA8: ="Alle > " & SWITCH(F8, "COMPONENT","BAUTEILE", "OTHER_RESOURCE", "RESSOURCEN", "BUILDING_TECHNOLOGY", "GEBÄUDETECHNIK", "MATERIAL", "MATERIALIEN") & " > kbob.admin.ch > KBOB / ecobau / IPB 2009/1:2016" -> Alle > GEBÄUDETECHNIK > kbob.admin.ch > KBOB / ecobau / IPB 2009/1:2016 | AB8: =VLOOKUP(LEFT(A8,6),MepClassificationAndLifecycle!A8:C74,3,false) -> 30
A9: ='Gebäudetechnik Technique'!A18 & " " & 'Gebäudetechnik Technique'!B18 & " (KBOB.2016)" -> 31.025 Wärmeabgabe über Heizkühldecke (ohne Gips- oder Metalldecke) (KBOB.2016) | B9: =A9 -> 31.025 Wärmeabgabe über Heizkühldecke (ohne Gips- oder Metalldecke) (KBOB.2016) | F9: BUILDING_TECHNOLOGY | G9: =IF(LEFT(A9, 2)="31", "BUILDING_TECHNOLOGY_HEATING", IF(LEFT(A9, 2)="32", "BUILDING_TECHNOLOGY_VENTILATION", IF(LEFT(A9, 2)="33", "BUILDING_TECHNOLOGY_SANITARY", IF(LEFT(A9, 2)="34", "BUILDING_TECHNOLOGY_ELECTRICAL")))) -> BUILDING_TECHNOLOGY_HEATING | H9: =VLOOKUP(LEFT(A9,6),MepClassificationAndLifecycle!A9:C75,2,false) -> heatEmission | J9: ='Gebäudetechnik Technique'!G18 -> 39400 | K9: ='Gebäudetechnik Technique'!H18 -> 39400 | L9: ='Gebäudetechnik Technique'!I18 -> 70.4 | M9: ='Gebäudetechnik Technique'!M18 -> 4.47 | N9: ='Gebäudetechnik Technique'!N18 -> 4.47 | O9: ='Gebäudetechnik Technique'!O18 -> 0.00159 | P9: ='Gebäudetechnik Technique'!P18 -> 26.4 | Q9: ='Gebäudetechnik Technique'!Q18 -> 26.3 | R9: ='Gebäudetechnik Technique'!R18 -> 0.0306 | S9: ='Gebäudetechnik Technique'!S18 -> 5.77 | T9: ='Gebäudetechnik Technique'!T18 -> 5.64 | U9: ='Gebäudetechnik Technique'!U18 -> 0.134 | V9: ='Gebäudetechnik Technique'!F18 -> m2 | W9: =VLOOKUP('Gebäudetechnik Technique'!E18,RefDimensions!A$2:B$15,2,false) -> energyReferenceArea | X9: 0 | Y9: ='Gebäudetechnik Technique'!A18 -> 31.025 | Z9: KBOB 2016 | AA9: ="Alle > " & SWITCH(F9, "COMPONENT","BAUTEILE", "OTHER_RESOURCE", "RESSOURCEN", "BUILDING_TECHNOLOGY", "GEBÄUDETECHNIK", "MATERIAL", "MATERIALIEN") & " > kbob.admin.ch > KBOB / ecobau / IPB 2009/1:2016" -> Alle > GEBÄUDETECHNIK > kbob.admin.ch > KBOB / ecobau / IPB 2009/1:2016 | AB9: =VLOOKUP(LEFT(A9,6),MepClassificationAndLifecycle!A9:C75,3,false) -> 30
A10: ='Gebäudetechnik Technique'!A19 & " " & 'Gebäudetechnik Technique'!B19 & " (KBOB.2016)" -> 31.015 Wärmeverteilung und Abgabe, Luftheizung (KBOB.2016) | B10: =A10 -> 31.015 Wärmeverteilung und Abgabe, Luftheizung (KBOB.2016) | F10: BUILDING_TECHNOLOGY | G10: =IF(LEFT(A10, 2)="31", "BUILDING_TECHNOLOGY_HEATING", IF(LEFT(A10, 2)="32", "BUILDING_TECHNOLOGY_VENTILATION", IF(LEFT(A10, 2)="33", "BUILDING_TECHNOLOGY_SANITARY", IF(LEFT(A10, 2)="34", "BUILDING_TECHNOLOGY_ELECTRICAL")))) -> BUILDING_TECHNOLOGY_HEATING | H10: =VLOOKUP(LEFT(A10,6),MepClassificationAndLifecycle!A10:C76,2,false) -> heatDistribution | J10: ='Gebäudetechnik Technique'!G19 -> 2940 | K10: ='Gebäudetechnik Technique'!H19 -> 2910 | L10: ='Gebäudetechnik Technique'!I19 -> 33.6 | M10: ='Gebäudetechnik Technique'!M19 -> 0.325 | N10: ='Gebäudetechnik Technique'!N19 -> 0.325 | O10: ='Gebäudetechnik Technique'!O19 -> 8.3e-05 | P10: ='Gebäudetechnik Technique'!P19 -> 7.96 | Q10: ='Gebäudetechnik Technique'!Q19 -> 7.95 | R10: ='Gebäudetechnik Technique'!R19 -> 0.00648 | S10: ='Gebäudetechnik Technique'!S19 -> 1.7 | T10: ='Gebäudetechnik Technique'!T19 -> 1.63 | U10: ='Gebäudetechnik Technique'!U19 -> 0.0672 | V10: ='Gebäudetechnik Technique'!F19 -> m2 | W10: =VLOOKUP('Gebäudetechnik Technique'!E19,RefDimensions!A$2:B$15,2,false) -> energyReferenceArea | X10: 0 | Y10: ='Gebäudetechnik Technique'!A19 -> 31.015 | Z10: KBOB 2016 | AA10: ="Alle > " & SWITCH(F10, "COMPONENT","BAUTEILE", "OTHER_RESOURCE", "RESSOURCEN", "BUILDING_TECHNOLOGY", "GEBÄUDETECHNIK", "MATERIAL", "MATERIALIEN") & " > kbob.admin.ch > KBOB / ecobau / IPB 2009/1:2016" -> Alle > GEBÄUDETECHNIK > kbob.admin.ch > KBOB / ecobau / IPB 2009/1:2016 | AB10: =VLOOKUP(LEFT(A10,6),MepClassificationAndLifecycle!A10:C76,3,false) -> 30
A11: ='Gebäudetechnik Technique'!A20 & " " & 'Gebäudetechnik Technique'!B20 & " (KBOB.2016)" -> 31.016 Erdsonden, für Sole-Wasser-Wärmepumpe (KBOB.2016) | B11: =A11 -> 31.016 Erdsonden, für Sole-Wasser-Wärmepumpe (KBOB.2016) | F11: BUILDING_TECHNOLOGY | G11: =IF(LEFT(A11, 2)="31", "BUILDING_TECHNOLOGY_HEATING", IF(LEFT(A11, 2)="32", "BUILDING_TECHNOLOGY_VENTILATION", IF(LEFT(A11, 2)="33", "BUILDING_TECHNOLOGY_SANITARY", IF(LEFT(A11, 2)="34", "BUILDING_TECHNOLOGY_ELECTRICAL")))) -> BUILDING_TECHNOLOGY_HEATING | H11: =VLOOKUP(LEFT(A11,6),MepClassificationAndLifecycle!A11:C77,2,false) -> geothermalProbe | J11: ='Gebäudetechnik Technique'!G20 -> 34600 | K11: ='Gebäudetechnik Technique'!H20 -> 30500 | L11: ='Gebäudetechnik Technique'!I20 -> 4100 | M11: ='Gebäudetechnik Technique'!M20 -> 2.87 | N11: ='Gebäudetechnik Technique'!N20 -> 2.61 | O11: ='Gebäudetechnik Technique'!O20 -> 0.255 | P11: ='Gebäudetechnik Technique'!P20 -> 130 | Q11: ='Gebäudetechnik Technique'!Q20 -> 129 | R11: ='Gebäudetechnik Technique'!R20 -> 1.48 | S11: ='Gebäudetechnik Technique'!S20 -> 28.1 | T11: ='Gebäudetechnik Technique'!T20 -> 25.3 | U11: ='Gebäudetechnik Technique'!U20 -> 2.73 | V11: ='Gebäudetechnik Technique'!F20 -> m | W11: =VLOOKUP('Gebäudetechnik Technique'!E20,RefDimensions!A$2:B$15,2,false) -> probeLength | X11: 0 | Y11: ='Gebäudetechnik Technique'!A20 -> 31.016 | Z11: KBOB 2016 | AA11: ="Alle > " & SWITCH(F11, "COMPONENT","BAUTEILE", "OTHER_RESOURCE", "RESSOURCEN", "BUILDING_TECHNOLOGY", "GEBÄUDETECHNIK", "MATERIAL", "MATERIALIEN") & " > kbob.admin.ch > KBOB / ecobau / IPB 2009/1:2016" -> Alle > GEBÄUDETECHNIK > kbob.admin.ch > KBOB / ecobau / IPB 2009/1:2016 | AB11: =VLOOKUP(LEFT(A11,6),MepClassificationAndLifecycle!A11:C77,3,false) -> 40
A12: ='Gebäudetechnik Technique'!A21 & " " & 'Gebäudetechnik Technique'!B21 & " (KBOB.2016)" -> 31.017 Sole-Wasser Wärmepumpe 8 kW (KBOB.2016) | B12: =A12 -> 31.017 Sole-Wasser Wärmepumpe 8 kW (KBOB.2016) | F12: BUILDING_TECHNOLOGY | G12: =IF(LEFT(A12, 2)="31", "BUILDING_TECHNOLOGY_HEATING", IF(LEFT(A12, 2)="32", "BUILDING_TECHNOLOGY_VENTILATION", IF(LEFT(A12, 2)="33", "BUILDING_TECHNOLOGY_SANITARY", IF(LEFT(A12, 2)="34", "BUILDING_TECHNOLOGY_ELECTRICAL")))) -> BUILDING_TECHNOLOGY_HEATING | H12: =VLOOKUP(LEFT(A12,6),MepClassificationAndLifecycle!A12:C78,2,false) -> heatGeneration | J12: ='Gebäudetechnik Technique'!G21 -> 4220000 | K12: ='Gebäudetechnik Technique'!H21 -> 3860000 | L12: ='Gebäudetechnik Technique'!I21 -> 367000 | M12: ='Gebäudetechnik Technique'!M21 -> 506 | N12: ='Gebäudetechnik Technique'!N21 -> 503 | O12: ='Gebäudetechnik Technique'!O21 -> 3.82 | P12: ='Gebäudetechnik Technique'!P21 -> 5520 | Q12: ='Gebäudetechnik Technique'!Q21 -> 5480 | R12: ='Gebäudetechnik Technique'!R21 -> 45.2 | S12: ='Gebäudetechnik Technique'!S21 -> 2180 | T12: ='Gebäudetechnik Technique'!T21 -> 1470 | U12: ='Gebäudetechnik Technique'!U21 -> 706 | V12: ='Gebäudetechnik Technique'!F21 -> Stk. | W12: =VLOOKUP('Gebäudetechnik Technique'!E21,RefDimensions!A$2:B$15,2,false) -> device | X12: 0 | Y12: ='Gebäudetechnik Technique'!A21 -> 31.017 | Z12: KBOB 2016 | AA12: ="Alle > " & SWITCH(F12, "COMPONENT","BAUTEILE", "OTHER_RESOURCE", "RESSOURCEN", "BUILDING_TECHNOLOGY", "GEBÄUDETECHNIK", "MATERIAL", "MATERIALIEN") & " > kbob.admin.ch > KBOB / ecobau / IPB 2009/1:2016" -> Alle > GEBÄUDETECHNIK > kbob.admin.ch > KBOB / ecobau / IPB 2009/1:2016 | AB12: =VLOOKUP(LEFT(A12,6),MepClassificationAndLifecycle!A12:C78,3,false) -> 20
A13: ='Gebäudetechnik Technique'!A22 & " " & 'Gebäudetechnik Technique'!B22 & " (KBOB.2016)" -> 31.018 Sole-Wasser Wärmepumpe 8 kW (KBOB.2016) | B13: =A13 -> 31.018 Sole-Wasser Wärmepumpe 8 kW (KBOB.2016) | F13: BUILDING_TECHNOLOGY | G13: =IF(LEFT(A13, 2)="31", "BUILDING_TECHNOLOGY_HEATING", IF(LEFT(A13, 2)="32", "BUILDING_TECHNOLOGY_VENTILATION", IF(LEFT(A13, 2)="33", "BUILDING_TECHNOLOGY_SANITARY", IF(LEFT(A13, 2)="34", "BUILDING_TECHNOLOGY_ELECTRICAL")))) -> BUILDING_TECHNOLOGY_HEATING | H13: =VLOOKUP(LEFT(A13,6),MepClassificationAndLifecycle!A13:C79,2,false) -> heatGeneration | J13: ='Gebäudetechnik Technique'!G22 -> 22500 | K13: ='Gebäudetechnik Technique'!H22 -> 20600 | L13: ='Gebäudetechnik Technique'!I22 -> 1960 | M13: ='Gebäudetechnik Technique'!M22 -> 2.7 | N13: ='Gebäudetechnik Technique'!N22 -> 2.68 | O13: ='Gebäudetechnik Technique'!O22 -> 0.0204 | P13: ='Gebäudetechnik Technique'!P22 -> 29.5 | Q13: ='Gebäudetechnik Technique'!Q22 -> 29.2 | R13: ='Gebäudetechnik Technique'!R22 -> 0.241 | S13: ='Gebäudetechnik Technique'!S22 -> 11.6 | T13: ='Gebäudetechnik Technique'!T22 -> 7.86 | U13: ='Gebäudetechnik Technique'!U22 -> 3.77 | V13: ='Gebäudetechnik Technique'!F22 -> kg | W13: =VLOOKUP('Gebäudetechnik Technique'!E22,RefDimensions!A$2:B$15,2,false) -> mass | X13: 0 | Y13: ='Gebäudetechnik Technique'!A22 -> 31.018 | Z13: KBOB 2016 | AA13: ="Alle > " & SWITCH(F13, "COMPONENT","BAUTEILE", "OTHER_RESOURCE", "RESSOURCEN", "BUILDING_TECHNOLOGY", "GEBÄUDETECHNIK", "MATERIAL", "MATERIALIEN") & " > kbob.admin.ch > KBOB / ecobau / IPB 2009/1:2016" -> Alle > GEBÄUDETECHNIK > kbob.admin.ch > KBOB / ecobau / IPB 2009/1:2016 | AB13: =VLOOKUP(LEFT(A13,6),MepClassificationAndLifecycle!A13:C79,3,false) -> 20
... A15: ='Gebäudetechnik Technique'!A24 & " " & 'Gebäudetechnik Technique'!B24 & " (KBOB.2016)" -> 31.020 Luft-Wasser Wärmepumpe 8 kW (KBOB.2016) | B15: =A15 -> 31.020 Luft-Wasser Wärmepumpe 8 kW (KBOB.2016) | F15: BUILDING_TECHNOLOGY | G15: =IF(LEFT(A15, 2)="31", "BUILDING_TECHNOLOGY_HEATING", IF(LEFT(A15, 2)="32", "BUILDING_TECHNOLOGY_VENTILATION", IF(LEFT(A15, 2)="33", "BUILDING_TECHNOLOGY_SANITARY", IF(LEFT(A15, 2)="34", "BUILDING_TECHNOLOGY_ELECTRICAL")))) -> BUILDING_TECHNOLOGY_HEATING | H15: =VLOOKUP(LEFT(A15,6),MepClassificationAndLifecycle!A15:C81,2,false) -> heatGeneration | J15: ='Gebäudetechnik Technique'!G24 -> 22400 | K15: ='Gebäudetechnik Technique'!H24 -> 20200 | L15: ='Gebäudetechnik Technique'!I24 -> 2240 | M15: ='Gebäudetechnik Technique'!M24 -> 2.63 | N15: ='Gebäudetechnik Technique'!N24 -> 2.61 | O15: ='Gebäudetechnik Technique'!O24 -> 0.0206 | P15: ='Gebäudetechnik Technique'!P24 -> 26.5 | Q15: ='Gebäudetechnik Technique'!Q24 -> 26.2 | R15: ='Gebäudetechnik Technique'!R24 -> 0.248 | S15: ='Gebäudetechnik Technique'!S24 -> 12 | T15: ='Gebäudetechnik Technique'!T24 -> 7.62 | U15: ='Gebäudetechnik Technique'!U24 -> 4.33 | V15: ='Gebäudetechnik Technique'!F24 -> kg | W15: =VLOOKUP('Gebäudetechnik Technique'!E24,RefDimensions!A$2:B$15,2,false) -> mass | X15: 0 | Y15: ='Gebäudetechnik Technique'!A24 -> 31.020 | Z15: KBOB 2016 | AA15: ="Alle > " & SWITCH(F15, "COMPONENT","BAUTEILE", "OTHER_RESOURCE", "RESSOURCEN", "BUILDING_TECHNOLOGY", "GEBÄUDETECHNIK", "MATERIAL", "MATERIALIEN") & " > kbob.admin.ch > KBOB / ecobau / IPB 2009/1:2016" -> Alle > GEBÄUDETECHNIK > kbob.admin.ch > KBOB / ecobau / IPB 2009/1:2016 | AB15: =VLOOKUP(LEFT(A15,6),MepClassificationAndLifecycle!A15:C81,3,false) -> 20
A16: ='Gebäudetechnik Technique'!A25 & " " & 'Gebäudetechnik Technique'!B25 & " (KBOB.2016)" -> 31.007 Flachkollektor für Warmwasser EFH (KBOB.2016) | B16: =A16 -> 31.007 Flachkollektor für Warmwasser EFH (KBOB.2016) | F16: BUILDING_TECHNOLOGY | G16: =IF(LEFT(A16, 2)="31", "BUILDING_TECHNOLOGY_HEATING", IF(LEFT(A16, 2)="32", "BUILDING_TECHNOLOGY_VENTILATION", IF(LEFT(A16, 2)="33", "BUILDING_TECHNOLOGY_SANITARY", IF(LEFT(A16, 2)="34", "BUILDING_TECHNOLOGY_ELECTRICAL")))) -> BUILDING_TECHNOLOGY_HEATING | H16: =VLOOKUP(LEFT(A16,6),MepClassificationAndLifecycle!A16:C82,2,false) -> heatGeneration | J16: ='Gebäudetechnik Technique'!G25 -> 676000 | K16: ='Gebäudetechnik Technique'!H25 -> 676000 | M16: ='Gebäudetechnik Technique'!M25 -> 142 | N16: ='Gebäudetechnik Technique'!N25 -> 142 | P16: ='Gebäudetechnik Technique'!P25 -> 1140 | Q16: ='Gebäudetechnik Technique'!Q25 -> 1140 | S16: ='Gebäudetechnik Technique'!S25 -> 256 | T16: ='Gebäudetechnik Technique'!T25 -> 256 | V16: ='Gebäudetechnik Technique'!F25 -> m2 | W16: =VLOOKUP('Gebäudetechnik Technique'!E25,RefDimensions!A$2:B$15,2,false) -> collectorArea | X16: 0 | Y16: ='Gebäudetechnik Technique'!A25 -> 31.007 | Z16: KBOB 2016 | AA16: ="Alle > " & SWITCH(F16, "COMPONENT","BAUTEILE", "OTHER_RESOURCE", "RESSOURCEN", "BUILDING_TECHNOLOGY", "GEBÄUDETECHNIK", "MATERIAL", "MATERIALIEN") & " > kbob.admin.ch > KBOB / ecobau / IPB 2009/1:2016" -> Alle > GEBÄUDETECHNIK > kbob.admin.ch > KBOB / ecobau / IPB 2009/1:2016 | AB16: =VLOOKUP(LEFT(A16,6),MepClassificationAndLifecycle!A16:C82,3,false) -> 30
A17: ='Gebäudetechnik Technique'!A26 & " " & 'Gebäudetechnik Technique'!B26 & " (KBOB.2016)" -> 31.008 Flachkollektor für Raumheizung und Warmwasser EFH (KBOB.2016) | B17: =A17 -> 31.008 Flachkollektor für Raumheizung und Warmwasser EFH (KBOB.2016) | F17: BUILDING_TECHNOLOGY | G17: =IF(LEFT(A17, 2)="31", "BUILDING_TECHNOLOGY_HEATING", IF(LEFT(A17, 2)="32", "BUILDING_TECHNOLOGY_VENTILATION", IF(LEFT(A17, 2)="33", "BUILDING_TECHNOLOGY_SANITARY", IF(LEFT(A17, 2)="34", "BUILDING_TECHNOLOGY_ELECTRICAL")))) -> BUILDING_TECHNOLOGY_HEATING | H17: =VLOOKUP(LEFT(A17,6),MepClassificationAndLifecycle!A17:C83,2,false) -> heatGeneration | J17: ='Gebäudetechnik Technique'!G26 -> 452000 | K17: ='Gebäudetechnik Technique'!H26 -> 452000 | M17: ='Gebäudetechnik Technique'!M26 -> 102 | N17: ='Gebäudetechnik Technique'!N26 -> 102 | P17: ='Gebäudetechnik Technique'!P26 -> 824 | Q17: ='Gebäudetechnik Technique'!Q26 -> 824 | S17: ='Gebäudetechnik Technique'!S26 -> 184 | T17: ='Gebäudetechnik Technique'!T26 -> 184 | V17: ='Gebäudetechnik Technique'!F26 -> m2 | W17: =VLOOKUP('Gebäudetechnik Technique'!E26,RefDimensions!A$2:B$15,2,false) -> collectorArea | X17: 0 | Y17: ='Gebäudetechnik Technique'!A26 -> 31.008 | Z17: KBOB 2016 | AA17: ="Alle > " & SWITCH(F17, "COMPONENT","BAUTEILE", "OTHER_RESOURCE", "RESSOURCEN", "BUILDING_TECHNOLOGY", "GEBÄUDETECHNIK", "MATERIAL", "MATERIALIEN") & " > kbob.admin.ch > KBOB / ecobau / IPB 2009/1:2016" -> Alle > GEBÄUDETECHNIK > kbob.admin.ch > KBOB / ecobau / IPB 2009/1:2016 | AB17: =VLOOKUP(LEFT(A17,6),MepClassificationAndLifecycle!A17:C83,3,false) -> 30
A18: ='Gebäudetechnik Technique'!A27 & " " & 'Gebäudetechnik Technique'!B27 & " (KBOB.2016)" -> 31.009 Flachkollektor für Warmwasser MFH (KBOB.2016) | B18: =A18 -> 31.009 Flachkollektor für Warmwasser MFH (KBOB.2016) | F18: BUILDING_TECHNOLOGY | G18: =IF(LEFT(A18, 2)="31", "BUILDING_TECHNOLOGY_HEATING", IF(LEFT(A18, 2)="32", "BUILDING_TECHNOLOGY_VENTILATION", IF(LEFT(A18, 2)="33", "BUILDING_TECHNOLOGY_SANITARY", IF(LEFT(A18, 2)="34", "BUILDING_TECHNOLOGY_ELECTRICAL")))) -> BUILDING_TECHNOLOGY_HEATING | H18: =VLOOKUP(LEFT(A18,6),MepClassificationAndLifecycle!A18:C84,2,false) -> heatGeneration | J18: ='Gebäudetechnik Technique'!G27 -> 394000 | K18: ='Gebäudetechnik Technique'!H27 -> 394000 | M18: ='Gebäudetechnik Technique'!M27 -> 79 | N18: ='Gebäudetechnik Technique'!N27 -> 79 | P18: ='Gebäudetechnik Technique'!P27 -> 695 | Q18: ='Gebäudetechnik Technique'!Q27 -> 695 | S18: ='Gebäudetechnik Technique'!S27 -> 155 | T18: ='Gebäudetechnik Technique'!T27 -> 155 | V18: ='Gebäudetechnik Technique'!F27 -> m2 | W18: =VLOOKUP('Gebäudetechnik Technique'!E27,RefDimensions!A$2:B$15,2,false) -> collectorArea | X18: 0 | Y18: ='Gebäudetechnik Technique'!A27 -> 31.009 | Z18: KBOB 2016 | AA18: ="Alle > " & SWITCH(F18, "COMPONENT","BAUTEILE", "OTHER_RESOURCE", "RESSOURCEN", "BUILDING_TECHNOLOGY", "GEBÄUDETECHNIK", "MATERIAL", "MATERIALIEN") & " > kbob.admin.ch > KBOB / ecobau / IPB 2009/1:2016" -> Alle > GEBÄUDETECHNIK > kbob.admin.ch > KBOB / ecobau / IPB 2009/1:2016 | AB18: =VLOOKUP(LEFT(A18,6),MepClassificationAndLifecycle!A18:C84,3,false) -> 30
A19: ='Gebäudetechnik Technique'!A28 & " " & 'Gebäudetechnik Technique'!B28 & " (KBOB.2016)" -> 31.010 Röhrenkollektor für Raumheizung und Warmwasser EFH (KBOB.2016) | B19: =A19 -> 31.010 Röhrenkollektor für Raumheizung und Warmwasser EFH (KBOB.2016) | F19: BUILDING_TECHNOLOGY | G19: =IF(LEFT(A19, 2)="31", "BUILDING_TECHNOLOGY_HEATING", IF(LEFT(A19, 2)="32", "BUILDING_TECHNOLOGY_VENTILATION", IF(LEFT(A19, 2)="33", "BUILDING_TECHNOLOGY_SANITARY", IF(LEFT(A19, 2)="34", "BUILDING_TECHNOLOGY_ELECTRICAL")))) -> BUILDING_TECHNOLOGY_HEATING | H19: =VLOOKUP(LEFT(A19,6),MepClassificationAndLifecycle!A19:C85,2,false) -> heatGeneration | J19: ='Gebäudetechnik Technique'!G28 -> 465000 | K19: ='Gebäudetechnik Technique'!H28 -> 465000 | M19: ='Gebäudetechnik Technique'!M28 -> 101 | N19: ='Gebäudetechnik Technique'!N28 -> 101 | P19: ='Gebäudetechnik Technique'!P28 -> 924 | Q19: ='Gebäudetechnik Technique'!Q28 -> 924 | S19: ='Gebäudetechnik Technique'!S28 -> 208 | T19: ='Gebäudetechnik Technique'!T28 -> 208 | V19: ='Gebäudetechnik Technique'!F28 -> m2 | W19: =VLOOKUP('Gebäudetechnik Technique'!E28,RefDimensions!A$2:B$15,2,false) -> collectorArea | X19: 0 | Y19: ='Gebäudetechnik Technique'!A28 -> 31.010 | Z19: KBOB 2016 | AA19: ="Alle > " & SWITCH(F19, "COMPONENT","BAUTEILE", "OTHER_RESOURCE", "RESSOURCEN", "BUILDING_TECHNOLOGY", "GEBÄUDETECHNIK", "MATERIAL", "MATERIALIEN") & " > kbob.admin.ch > KBOB / ecobau / IPB 2009/1:2016" -> Alle > GEBÄUDETECHNIK > kbob.admin.ch > KBOB / ecobau / IPB 2009/1:2016 | AB19: =VLOOKUP(LEFT(A19,6),MepClassificationAndLifecycle!A19:C85,3,false) -> 30
A20: ='Gebäudetechnik Technique'!A30 & " " & 'Gebäudetechnik Technique'!B30 & " (KBOB.2016)" -> 32.011 Lüftungsanlage, spez. Luftmenge 1 m3/hm2 EBF (KBOB.2016) | B20: =A20 -> 32.011 Lüftungsanlage, spez. Luftmenge 1 m3/hm2 EBF (KBOB.2016) | F20: BUILDING_TECHNOLOGY | G20: =IF(LEFT(A20, 2)="31", "BUILDING_TECHNOLOGY_HEATING", IF(LEFT(A20, 2)="32", "BUILDING_TECHNOLOGY_VENTILATION", IF(LEFT(A20, 2)="33", "BUILDING_TECHNOLOGY_SANITARY", IF(LEFT(A20, 2)="34", "BUILDING_TECHNOLOGY_ELECTRICAL")))) -> BUILDING_TECHNOLOGY_VENTILATION | H20: =VLOOKUP(LEFT(A20,6),MepClassificationAndLifecycle!A20:C86,2,false) -> ventilation | J20: ='Gebäudetechnik Technique'!G30 -> 31700 | K20: ='Gebäudetechnik Technique'!H30 -> 31400 | L20: ='Gebäudetechnik Technique'!I30 -> 222 | M20: ='Gebäudetechnik Technique'!M30 -> 4.35 | N20: ='Gebäudetechnik Technique'!N30 -> 4.35 | O20: ='Gebäudetechnik Technique'!O30 -> 0.00695 | P20: ='Gebäudetechnik Technique'!P30 -> 54.5 | Q20: ='Gebäudetechnik Technique'!Q30 -> 54.3 | R20: ='Gebäudetechnik Technique'!R30 -> 0.208 | S20: ='Gebäudetechnik Technique'!S30 -> 12.7 | T20: ='Gebäudetechnik Technique'!T30 -> 12.3 | U20: ='Gebäudetechnik Technique'!U30 -> 0.345 | V20: ='Gebäudetechnik Technique'!F30 -> m2 | W20: =VLOOKUP('Gebäudetechnik Technique'!E30,RefDimensions!A$2:B$15,2,false) -> energyReferenceArea | X20: 0 | Y20: ='Gebäudetechnik Technique'!A30 -> 32.011 | Z20: KBOB 2016 | AA20: ="Alle > " & SWITCH(F20, "COMPONENT","BAUTEILE", "OTHER_RESOURCE", "RESSOURCEN", "BUILDING_TECHNOLOGY", "GEBÄUDETECHNIK", "MATERIAL", "MATERIALIEN") & " > kbob.admin.ch > KBOB / ecobau / IPB 2009/1:2016" -> Alle > GEBÄUDETECHNIK > kbob.admin.ch > KBOB / ecobau / IPB 2009/1:2016 | AB20: =VLOOKUP(LEFT(A20,6),MepClassificationAndLifecycle!A20:C86,3,false) -> 30
A21: ='Gebäudetechnik Technique'!A31 & " " & 'Gebäudetechnik Technique'!B31 & " (KBOB.2016)" -> 32.005 Lüftungsanlage, spez. Luftmenge 2 m3/hm2 EBF (KBOB.2016) | B21: =A21 -> 32.005 Lüftungsanlage, spez. Luftmenge 2 m3/hm2 EBF (KBOB.2016) | F21: BUILDING_TECHNOLOGY | G21: =IF(LEFT(A21, 2)="31", "BUILDING_TECHNOLOGY_HEATING", IF(LEFT(A21, 2)="32", "BUILDING_TECHNOLOGY_VENTILATION", IF(LEFT(A21, 2)="33", "BUILDING_TECHNOLOGY_SANITARY", IF(LEFT(A21, 2)="34", "BUILDING_TECHNOLOGY_ELECTRICAL")))) -> BUILDING_TECHNOLOGY_VENTILATION | H21: =VLOOKUP(LEFT(A21,6),MepClassificationAndLifecycle!A21:C87,2,false) -> ventilation | J21: ='Gebäudetechnik Technique'!G31 -> 42700 | K21: ='Gebäudetechnik Technique'!H31 -> 42400 | L21: ='Gebäudetechnik Technique'!I31 -> 311 | M21: ='Gebäudetechnik Technique'!M31 -> 5.85 | N21: ='Gebäudetechnik Technique'!N31 -> 5.84 | O21: ='Gebäudetechnik Technique'!O31 -> 0.00947 | P21: ='Gebäudetechnik Technique'!P31 -> 73.6 | Q21: ='Gebäudetechnik Technique'!Q31 -> 73.3 | R21: ='Gebäudetechnik Technique'!R31 -> 0.287 | S21: ='Gebäudetechnik Technique'!S31 -> 17.1 | T21: ='Gebäudetechnik Technique'!T31 -> 16.6 | U21: ='Gebäudetechnik Technique'!U31 -> 0.485 | V21: ='Gebäudetechnik Technique'!F31 -> m2 | W21: =VLOOKUP('Gebäudetechnik Technique'!E31,RefDimensions!A$2:B$15,2,false) -> energyReferenceArea | X21: 0 | Y21: ='Gebäudetechnik Technique'!A31 -> 32.005 | Z21: KBOB 2016 | AA21: ="Alle > " & SWITCH(F21, "COMPONENT","BAUTEILE", "OTHER_RESOURCE", "RESSOURCEN", "BUILDING_TECHNOLOGY", "GEBÄUDETECHNIK", "MATERIAL", "MATERIALIEN") & " > kbob.admin.ch > KBOB / ecobau / IPB 2009/1:2016" -> Alle > GEBÄUDETECHNIK > kbob.admin.ch > KBOB / ecobau / IPB 2009/1:2016 | AB21: =VLOOKUP(LEFT(A21,6),MepClassificationAndLifecycle!A21:C87,3,false) -> 30
A22: ='Gebäudetechnik Technique'!A32 & " " & 'Gebäudetechnik Technique'!B32 & " (KBOB.2016)" -> 32.006 Lüftungsanlage, spez. Luftmenge 4 m3/hm2 EBF (KBOB.2016) | B22: =A22 -> 32.006 Lüftungsanlage, spez. Luftmenge 4 m3/hm2 EBF (KBOB.2016) | F22: BUILDING_TECHNOLOGY | G22: =IF(LEFT(A22, 2)="31", "BUILDING_TECHNOLOGY_HEATING", IF(LEFT(A22, 2)="32", "BUILDING_TECHNOLOGY_VENTILATION", IF(LEFT(A22, 2)="33", "BUILDING_TECHNOLOGY_SANITARY", IF(LEFT(A22, 2)="34", "BUILDING_TECHNOLOGY_ELECTRICAL")))) -> BUILDING_TECHNOLOGY_VENTILATION | H22: =VLOOKUP(LEFT(A22,6),MepClassificationAndLifecycle!A22:C88,2,false) -> ventilation | J22: ='Gebäudetechnik Technique'!G32 -> 64800 | K22: ='Gebäudetechnik Technique'!H32 -> 64300 | L22: ='Gebäudetechnik Technique'!I32 -> 488 | M22: ='Gebäudetechnik Technique'!M32 -> 8.84 | N22: ='Gebäudetechnik Technique'!N32 -> 8.83 | O22: ='Gebäudetechnik Technique'!O32 -> 0.0145 | P22: ='Gebäudetechnik Technique'!P32 -> 112 | Q22: ='Gebäudetechnik Technique'!Q32 -> 111 | R22: ='Gebäudetechnik Technique'!R32 -> 0.444 | S22: ='Gebäudetechnik Technique'!S32 -> 25.9 | T22: ='Gebäudetechnik Technique'!T32 -> 25.2 | U22: ='Gebäudetechnik Technique'!U32 -> 0.763 | V22: ='Gebäudetechnik Technique'!F32 -> m2 | W22: =VLOOKUP('Gebäudetechnik Technique'!E32,RefDimensions!A$2:B$15,2,false) -> energyReferenceArea | X22: 0 | Y22: ='Gebäudetechnik Technique'!A32 -> 32.006 | Z22: KBOB 2016 | AA22: ="Alle > " & SWITCH(F22, "COMPONENT","BAUTEILE", "OTHER_RESOURCE", "RESSOURCEN", "BUILDING_TECHNOLOGY", "GEBÄUDETECHNIK", "MATERIAL", "MATERIALIEN") & " > kbob.admin.ch > KBOB / ecobau / IPB 2009/1:2016" -> Alle > GEBÄUDETECHNIK > kbob.admin.ch > KBOB / ecobau / IPB 2009/1:2016 | AB22: =VLOOKUP(LEFT(A22,6),MepClassificationAndLifecycle!A22:C88,3,false) -> 30
A23: ='Gebäudetechnik Technique'!A33 & " " & 'Gebäudetechnik Technique'!B33 & " (KBOB.2016)" -> 32.007 Lüftungsanlage, spez. Luftmenge 6 m3/hm2 EBF (KBOB.2016) | B23: =A23 -> 32.007 Lüftungsanlage, spez. Luftmenge 6 m3/hm2 EBF (KBOB.2016) | F23: BUILDING_TECHNOLOGY | G23: =IF(LEFT(A23, 2)="31", "BUILDING_TECHNOLOGY_HEATING", IF(LEFT(A23, 2)="32", "BUILDING_TECHNOLOGY_VENTILATION", IF(LEFT(A23, 2)="33", "BUILDING_TECHNOLOGY_SANITARY", IF(LEFT(A23, 2)="34", "BUILDING_TECHNOLOGY_ELECTRICAL")))) -> BUILDING_TECHNOLOGY_VENTILATION | H23: =VLOOKUP(LEFT(A23,6),MepClassificationAndLifecycle!A23:C89,2,false) -> ventilation | J23: ='Gebäudetechnik Technique'!G33 -> 86900 | K23: ='Gebäudetechnik Technique'!H33 -> 86200 | L23: ='Gebäudetechnik Technique'!I33 -> 666 | M23: ='Gebäudetechnik Technique'!M33 -> 11.8 | N23: ='Gebäudetechnik Technique'!N33 -> 11.8 | O23: ='Gebäudetechnik Technique'!O33 -> 0.0196 | P23: ='Gebäudetechnik Technique'!P33 -> 150 | Q23: ='Gebäudetechnik Technique'!Q33 -> 149 | R23: ='Gebäudetechnik Technique'!R33 -> 0.601 | S23: ='Gebäudetechnik Technique'!S33 -> 34.8 | T23: ='Gebäudetechnik Technique'!T33 -> 33.7 | U23: ='Gebäudetechnik Technique'!U33 -> 1.04 | V23: ='Gebäudetechnik Technique'!F33 -> m2 | W23: =VLOOKUP('Gebäudetechnik Technique'!E33,RefDimensions!A$2:B$15,2,false) -> energyReferenceArea | X23: 0 | Y23: ='Gebäudetechnik Technique'!A33 -> 32.007 | Z23: KBOB 2016 | AA23: ="Alle > " & SWITCH(F23, "COMPONENT","BAUTEILE", "OTHER_RESOURCE", "RESSOURCEN", "BUILDING_TECHNOLOGY", "GEBÄUDETECHNIK", "MATERIAL", "MATERIALIEN") & " > kbob.admin.ch > KBOB / ecobau / IPB 2009/1:2016" -> Alle > GEBÄUDETECHNIK > kbob.admin.ch > KBOB / ecobau / IPB 2009/1:2016 | AB23: =VLOOKUP(LEFT(A23,6),MepClassificationAndLifecycle!A23:C89,3,false) -> 30
A24: ='Gebäudetechnik Technique'!A34 & " " & 'Gebäudetechnik Technique'!B34 & " (KBOB.2016)" -> 32.012 Lüftungsanlage, spez. Luftmenge 8 m3/hm2 EBF (KBOB.2016) | B24: =A24 -> 32.012 Lüftungsanlage, spez. Luftmenge 8 m3/hm2 EBF (KBOB.2016) | F24: BUILDING_TECHNOLOGY | G24: =IF(LEFT(A24, 2)="31", "BUILDING_TECHNOLOGY_HEATING", IF(LEFT(A24, 2)="32", "BUILDING_TECHNOLOGY_VENTILATION", IF(LEFT(A24, 2)="33", "BUILDING_TECHNOLOGY_SANITARY", IF(LEFT(A24, 2)="34", "BUILDING_TECHNOLOGY_ELECTRICAL")))) -> BUILDING_TECHNOLOGY_VENTILATION | H24: =VLOOKUP(LEFT(A24,6),MepClassificationAndLifecycle!A24:C90,2,false) -> ventilation | J24: ='Gebäudetechnik Technique'!G34 -> 109000 | K24: ='Gebäudetechnik Technique'!H34 -> 108000 | L24: ='Gebäudetechnik Technique'!I34 -> 843 | M24: ='Gebäudetechnik Technique'!M34 -> 14.8 | N24: ='Gebäudetechnik Technique'!N34 -> 14.8 | O24: ='Gebäudetechnik Technique'!O34 -> 0.0246 | P24: ='Gebäudetechnik Technique'!P34 -> 188 | Q24: ='Gebäudetechnik Technique'!Q34 -> 187 | R24: ='Gebäudetechnik Technique'!R34 -> 0.758 | S24: ='Gebäudetechnik Technique'!S34 -> 43.6 | T24: ='Gebäudetechnik Technique'!T34 -> 42.3 | U24: ='Gebäudetechnik Technique'!U34 -> 1.32 | V24: ='Gebäudetechnik Technique'!F34 -> m2 | W24: =VLOOKUP('Gebäudetechnik Technique'!E34,RefDimensions!A$2:B$15,2,false) -> energyReferenceArea | X24: 0 | Y24: ='Gebäudetechnik Technique'!A34 -> 32.012 | Z24: KBOB 2016 | AA24: ="Alle > " & SWITCH(F24, "COMPONENT","BAUTEILE", "OTHER_RESOURCE", "RESSOURCEN", "BUILDING_TECHNOLOGY", "GEBÄUDETECHNIK", "MATERIAL", "MATERIALIEN") & " > kbob.admin.ch > KBOB / ecobau / IPB 2009/1:2016" -> Alle > GEBÄUDETECHNIK > kbob.admin.ch > KBOB / ecobau / IPB 2009/1:2016 | AB24: =VLOOKUP(LEFT(A24,6),MepClassificationAndLifecycle!A24:C90,3,false) -> 30
A25: ='Gebäudetechnik Technique'!A35 & " " & 'Gebäudetechnik Technique'!B35 & " (KBOB.2016)" -> 32.001 Lüftungsanlage Wohnen, Blechkanäle, inkl. Küchenabluft (KBOB.2016) | B25: =A25 -> 32.001 Lüftungsanlage Wohnen, Blechkanäle, inkl. Küchenabluft (KBOB.2016) | F25: BUILDING_TECHNOLOGY | G25: =IF(LEFT(A25, 2)="31", "BUILDING_TECHNOLOGY_HEATING", IF(LEFT(A25, 2)="32", "BUILDING_TECHNOLOGY_VENTILATION", IF(LEFT(A25, 2)="33", "BUILDING_TECHNOLOGY_SANITARY", IF(LEFT(A25, 2)="34", "BUILDING_TECHNOLOGY_ELECTRICAL")))) -> BUILDING_TECHNOLOGY_VENTILATION | H25: =VLOOKUP(LEFT(A25,6),MepClassificationAndLifecycle!A25:C91,2,false) -> ventilation | J25: ='Gebäudetechnik Technique'!G35 -> 45200 | K25: ='Gebäudetechnik Technique'!H35 -> 45000 | L25: ='Gebäudetechnik Technique'!I35 -> 182 | M25: ='Gebäudetechnik Technique'!M35 -> 3.99 | N25: ='Gebäudetechnik Technique'!N35 -> 3.99 | O25: ='Gebäudetechnik Technique'!O35 -> 0.00388 | P25: ='Gebäudetechnik Technique'!P35 -> 53.3 | Q25: ='Gebäudetechnik Technique'!Q35 -> 53.2 | R25: ='Gebäudetechnik Technique'!R35 -> 0.0831 | S25: ='Gebäudetechnik Technique'!S35 -> 12 | T25: ='Gebäudetechnik Technique'!T35 -> 11.7 | U25: ='Gebäudetechnik Technique'!U35 -> 0.299 | V25: ='Gebäudetechnik Technique'!F35 -> m2 | W25: =VLOOKUP('Gebäudetechnik Technique'!E35,RefDimensions!A$2:B$15,2,false) -> energyReferenceArea | X25: 0 | Y25: ='Gebäudetechnik Technique'!A35 -> 32.001 | Z25: KBOB 2016 | AA25: ="Alle > " & SWITCH(F25, "COMPONENT","BAUTEILE", "OTHER_RESOURCE", "RESSOURCEN", "BUILDING_TECHNOLOGY", "GEBÄUDETECHNIK", "MATERIAL", "MATERIALIEN") & " > kbob.admin.ch > KBOB / ecobau / IPB 2009/1:2016" -> Alle > GEBÄUDETECHNIK > kbob.admin.ch > KBOB / ecobau / IPB 2009/1:2016 | AB25: =VLOOKUP(LEFT(A25,6),MepClassificationAndLifecycle!A25:C91,3,false) -> 30
A26: ='Gebäudetechnik Technique'!A36 & " " & 'Gebäudetechnik Technique'!B36 & " (KBOB.2016)" -> 32.002 Lüftungsanlage Wohnen, PE-Kanäle, inkl. Küchenabluft (KBOB.2016) | B26: =A26 -> 32.002 Lüftungsanlage Wohnen, PE-Kanäle, inkl. Küchenabluft (KBOB.2016) | F26: BUILDING_TECHNOLOGY | G26: =IF(LEFT(A26, 2)="31", "BUILDING_TECHNOLOGY_HEATING", IF(LEFT(A26, 2)="32", "BUILDING_TECHNOLOGY_VENTILATION", IF(LEFT(A26, 2)="33", "BUILDING_TECHNOLOGY_SANITARY", IF(LEFT(A26, 2)="34", "BUILDING_TECHNOLOGY_ELECTRICAL")))) -> BUILDING_TECHNOLOGY_VENTILATION | H26: =VLOOKUP(LEFT(A26,6),MepClassificationAndLifecycle!A26:C92,2,false) -> ventilation | J26: ='Gebäudetechnik Technique'!G36 -> 22000 | K26: ='Gebäudetechnik Technique'!H36 -> 21600 | L26: ='Gebäudetechnik Technique'!I36 -> 371 | M26: ='Gebäudetechnik Technique'!M36 -> 2.36 | N26: ='Gebäudetechnik Technique'!N36 -> 2.36 | O26: ='Gebäudetechnik Technique'!O36 -> 0.00253 | P26: ='Gebäudetechnik Technique'!P36 -> 32.7 | Q26: ='Gebäudetechnik Technique'!Q36 -> 32.6 | R26: ='Gebäudetechnik Technique'!R36 -> 0.0743 | S26: ='Gebäudetechnik Technique'!S36 -> 7.32 | T26: ='Gebäudetechnik Technique'!T36 -> 6.6 | U26: ='Gebäudetechnik Technique'!U36 -> 0.724 | V26: ='Gebäudetechnik Technique'!F36 -> m2 | W26: =VLOOKUP('Gebäudetechnik Technique'!E36,RefDimensions!A$2:B$15,2,false) -> energyReferenceArea | X26: 0 | Y26: ='Gebäudetechnik Technique'!A36 -> 32.002 | Z26: KBOB 2016 | AA26: ="Alle > " & SWITCH(F26, "COMPONENT","BAUTEILE", "OTHER_RESOURCE", "RESSOURCEN", "BUILDING_TECHNOLOGY", "GEBÄUDETECHNIK", "MATERIAL", "MATERIALIEN") & " > kbob.admin.ch > KBOB / ecobau / IPB 2009/1:2016" -> Alle > GEBÄUDETECHNIK > kbob.admin.ch > KBOB / ecobau / IPB 2009/1:2016 | AB26: =VLOOKUP(LEFT(A26,6),MepClassificationAndLifecycle!A26:C92,3,false) -> 30
A27: ='Gebäudetechnik Technique'!A37 & " " & 'Gebäudetechnik Technique'!B37 & " (KBOB.2016)" -> 32.003 Abluftanlage Küche und Bad (KBOB.2016) | B27: =A27 -> 32.003 Abluftanlage Küche und Bad (KBOB.2016) | F27: BUILDING_TECHNOLOGY | G27: =IF(LEFT(A27, 2)="31", "BUILDING_TECHNOLOGY_HEATING", IF(LEFT(A27, 2)="32", "BUILDING_TECHNOLOGY_VENTILATION", IF(LEFT(A27, 2)="33", "BUILDING_TECHNOLOGY_SANITARY", IF(LEFT(A27, 2)="34", "BUILDING_TECHNOLOGY_ELECTRICAL")))) -> BUILDING_TECHNOLOGY_VENTILATION | H27: =VLOOKUP(LEFT(A27,6),MepClassificationAndLifecycle!A27:C93,2,false) -> ventilation | J27: ='Gebäudetechnik Technique'!G37 -> 13300 | K27: ='Gebäudetechnik Technique'!H37 -> 13300 | L27: ='Gebäudetechnik Technique'!I37 -> 65.7 | M27: ='Gebäudetechnik Technique'!M37 -> 0.981 | N27: ='Gebäudetechnik Technique'!N37 -> 0.98 | O27: ='Gebäudetechnik Technique'!O37 -> 0.000208 | P27: ='Gebäudetechnik Technique'!P37 -> 15.1 | Q27: ='Gebäudetechnik Technique'!Q37 -> 15.1 | R27: ='Gebäudetechnik Technique'!R37 -> 0.0165 | S27: ='Gebäudetechnik Technique'!S37 -> 3.4 | T27: ='Gebäudetechnik Technique'!T37 -> 3.28 | U27: ='Gebäudetechnik Technique'!U37 -> 0.126 | V27: ='Gebäudetechnik Technique'!F37 -> m2 | W27: =VLOOKUP('Gebäudetechnik Technique'!E37,RefDimensions!A$2:B$15,2,false) -> energyReferenceArea | X27: 0 | Y27: ='Gebäudetechnik Technique'!A37 -> 32.003 | Z27: KBOB 2016 | AA27: ="Alle > " & SWITCH(F27, "COMPONENT","BAUTEILE", "OTHER_RESOURCE", "RESSOURCEN", "BUILDING_TECHNOLOGY", "GEBÄUDETECHNIK", "MATERIAL", "MATERIALIEN") & " > kbob.admin.ch > KBOB / ecobau / IPB 2009/1:2016" -> Alle > GEBÄUDETECHNIK > kbob.admin.ch > KBOB / ecobau / IPB 2009/1:2016 | AB27: =VLOOKUP(LEFT(A27,6),MepClassificationAndLifecycle!A27:C93,3,false) -> 30
A28: ='Gebäudetechnik Technique'!A38 & " " & 'Gebäudetechnik Technique'!B38 & " (KBOB.2016)" -> 32.004 Erdregister zu Lüftungsanlage Wohnen (KBOB.2016) | B28: =A28 -> 32.004 Erdregister zu Lüftungsanlage Wohnen (KBOB.2016) | F28: BUILDING_TECHNOLOGY | G28: =IF(LEFT(A28, 2)="31", "BUILDING_TECHNOLOGY_HEATING", IF(LEFT(A28, 2)="32", "BUILDING_TECHNOLOGY_VENTILATION", IF(LEFT(A28, 2)="33", "BUILDING_TECHNOLOGY_SANITARY", IF(LEFT(A28, 2)="34", "BUILDING_TECHNOLOGY_ELECTRICAL")))) -> BUILDING_TECHNOLOGY_VENTILATION | H28: =VLOOKUP(LEFT(A28,6),MepClassificationAndLifecycle!A28:C94,2,false) -> ventilation | J28: ='Gebäudetechnik Technique'!G38 -> 4550 | K28: ='Gebäudetechnik Technique'!H38 -> 3220 | L28: ='Gebäudetechnik Technique'!I38 -> 1330 | M28: ='Gebäudetechnik Technique'!M38 -> 0.554 | N28: ='Gebäudetechnik Technique'!N38 -> 0.502 | O28: ='Gebäudetechnik Technique'!O38 -> 0.0518 | P28: ='Gebäudetechnik Technique'!P38 -> 16.1 | Q28: ='Gebäudetechnik Technique'!Q38 -> 14.8 | R28: ='Gebäudetechnik Technique'!R38 -> 1.28 | S28: ='Gebäudetechnik Technique'!S38 -> 4.55 | T28: ='Gebäudetechnik Technique'!T38 -> 2.92 | U28: ='Gebäudetechnik Technique'!U38 -> 1.63 | V28: ='Gebäudetechnik Technique'!F38 -> m2 | W28: =VLOOKUP('Gebäudetechnik Technique'!E38,RefDimensions!A$2:B$15,2,false) -> energyReferenceArea | X28: 0 | Y28: ='Gebäudetechnik Technique'!A38 -> 32.004 | Z28: KBOB 2016 | AA28: ="Alle > " & SWITCH(F28, "COMPONENT","BAUTEILE", "OTHER_RESOURCE", "RESSOURCEN", "BUILDING_TECHNOLOGY", "GEBÄUDETECHNIK", "MATERIAL", "MATERIALIEN") & " > kbob.admin.ch > KBOB / ecobau / IPB 2009/1:2016" -> Alle > GEBÄUDETECHNIK > kbob.admin.ch > KBOB / ecobau / IPB 2009/1:2016 | AB28: =VLOOKUP(LEFT(A28,6),MepClassificationAndLifecycle!A28:C94,3,false) -> 30
A29: ='Gebäudetechnik Technique'!A39 & " " & 'Gebäudetechnik Technique'!B39 & " (KBOB.2016)" -> 32.008 Erdregister kurz zu Lüftungsanlage Büro (0.27 m/m2 EBF) (KBOB.2016) | B29: =A29 -> 32.008 Erdregister kurz zu Lüftungsanlage Büro (0.27 m/m2 EBF) (KBOB.2016) | F29: BUILDING_TECHNOLOGY | G29: =IF(LEFT(A29, 2)="31", "BUILDING_TECHNOLOGY_HEATING", IF(LEFT(A29, 2)="32", "BUILDING_TECHNOLOGY_VENTILATION", IF(LEFT(A29, 2)="33", "BUILDING_TECHNOLOGY_SANITARY", IF(LEFT(A29, 2)="34", "BUILDING_TECHNOLOGY_ELECTRICAL")))) -> BUILDING_TECHNOLOGY_VENTILATION | H29: =VLOOKUP(LEFT(A29,6),MepClassificationAndLifecycle!A29:C95,2,false) -> ventilation | J29: ='Gebäudetechnik Technique'!G39 -> 7890 | K29: ='Gebäudetechnik Technique'!H39 -> 5590 | L29: ='Gebäudetechnik Technique'!I39 -> 2300 | M29: ='Gebäudetechnik Technique'!M39 -> 0.96 | N29: ='Gebäudetechnik Technique'!N39 -> 0.87 | O29: ='Gebäudetechnik Technique'!O39 -> 0.0898 | P29: ='Gebäudetechnik Technique'!P39 -> 27.9 | Q29: ='Gebäudetechnik Technique'!Q39 -> 25.7 | R29: ='Gebäudetechnik Technique'!R39 -> 2.22 | S29: ='Gebäudetechnik Technique'!S39 -> 7.89 | T29: ='Gebäudetechnik Technique'!T39 -> 5.06 | U29: ='Gebäudetechnik Technique'!U39 -> 2.82 | V29: ='Gebäudetechnik Technique'!F39 -> m2 | W29: =VLOOKUP('Gebäudetechnik Technique'!E39,RefDimensions!A$2:B$15,2,false) -> energyReferenceArea | X29: 0 | Y29: ='Gebäudetechnik Technique'!A39 -> 32.008 | Z29: KBOB 2016 | AA29: ="Alle > " & SWITCH(F29, "COMPONENT","BAUTEILE", "OTHER_RESOURCE", "RESSOURCEN", "BUILDING_TECHNOLOGY", "GEBÄUDETECHNIK", "MATERIAL", "MATERIALIEN") & " > kbob.admin.ch > KBOB / ecobau / IPB 2009/1:2016" -> Alle > GEBÄUDETECHNIK > kbob.admin.ch > KBOB / ecobau / IPB 2009/1:2016 | AB29: =VLOOKUP(LEFT(A29,6),MepClassificationAndLifecycle!A29:C95,3,false) -> 30
A30: ='Gebäudetechnik Technique'!A40 & " " & 'Gebäudetechnik Technique'!B40 & " (KBOB.2016)" -> 32.009 Erdregister lang zu Lüftungsanlage Büro (0.67 m/m2 EBF) (KBOB.2016) | B30: =A30 -> 32.009 Erdregister lang zu Lüftungsanlage Büro (0.67 m/m2 EBF) (KBOB.2016) | F30: BUILDING_TECHNOLOGY | G30: =IF(LEFT(A30, 2)="31", "BUILDING_TECHNOLOGY_HEATING", IF(LEFT(A30, 2)="32", "BUILDING_TECHNOLOGY_VENTILATION", IF(LEFT(A30, 2)="33", "BUILDING_TECHNOLOGY_SANITARY", IF(LEFT(A30, 2)="34", "BUILDING_TECHNOLOGY_ELECTRICAL")))) -> BUILDING_TECHNOLOGY_VENTILATION | H30: =VLOOKUP(LEFT(A30,6),MepClassificationAndLifecycle!A30:C96,2,false) -> ventilation | J30: ='Gebäudetechnik Technique'!G40 -> 19700 | K30: ='Gebäudetechnik Technique'!H40 -> 14000 | L30: ='Gebäudetechnik Technique'!I40 -> 5760 | M30: ='Gebäudetechnik Technique'!M40 -> 2.4 | N30: ='Gebäudetechnik Technique'!N40 -> 2.18 | O30: ='Gebäudetechnik Technique'!O40 -> 0.224 | P30: ='Gebäudetechnik Technique'!P40 -> 69.7 | Q30: ='Gebäudetechnik Technique'!Q40 -> 64.2 | R30: ='Gebäudetechnik Technique'!R40 -> 5.54 | S30: ='Gebäudetechnik Technique'!S40 -> 19.7 | T30: ='Gebäudetechnik Technique'!T40 -> 12.7 | U30: ='Gebäudetechnik Technique'!U40 -> 7.05 | V30: ='Gebäudetechnik Technique'!F40 -> m2 | W30: =VLOOKUP('Gebäudetechnik Technique'!E40,RefDimensions!A$2:B$15,2,false) -> energyReferenceArea | X30: 0 | Y30: ='Gebäudetechnik Technique'!A40 -> 32.009 | Z30: KBOB 2016 | AA30: ="Alle > " & SWITCH(F30, "COMPONENT","BAUTEILE", "OTHER_RESOURCE", "RESSOURCEN", "BUILDING_TECHNOLOGY", "GEBÄUDETECHNIK", "MATERIAL", "MATERIALIEN") & " > kbob.admin.ch > KBOB / ecobau / IPB 2009/1:2016" -> Alle > GEBÄUDETECHNIK > kbob.admin.ch > KBOB / ecobau / IPB 2009/1:2016 | AB30: =VLOOKUP(LEFT(A30,6),MepClassificationAndLifecycle!A30:C96,3,false) -> 30
A31: ='Gebäudetechnik Technique'!A41 & " " & 'Gebäudetechnik Technique'!B41 & " (KBOB.2016)" -> 32.010 Einzelraumlüfer Fenstermodell 10-30 m3/h, ohne Montage (KBOB.2016) | B31: =A31 -> 32.010 Einzelraumlüfer Fenstermodell 10-30 m3/h, ohne Montage (KBOB.2016) | F31: BUILDING_TECHNOLOGY | G31: =IF(LEFT(A31, 2)="31", "BUILDING_TECHNOLOGY_HEATING", IF(LEFT(A31, 2)="32", "BUILDING_TECHNOLOGY_VENTILATION", IF(LEFT(A31, 2)="33", "BUILDING_TECHNOLOGY_SANITARY", IF(LEFT(A31, 2)="34", "BUILDING_TECHNOLOGY_ELECTRICAL")))) -> BUILDING_TECHNOLOGY_VENTILATION | H31: =VLOOKUP(LEFT(A31,6),MepClassificationAndLifecycle!A31:C97,2,false) -> ventilation | J31: ='Gebäudetechnik Technique'!G41 -> 63200 | K31: ='Gebäudetechnik Technique'!H41 -> 59900 | L31: ='Gebäudetechnik Technique'!I41 -> 3260 | M31: ='Gebäudetechnik Technique'!M41 -> 109 | N31: ='Gebäudetechnik Technique'!N41 -> 109 | O31: ='Gebäudetechnik Technique'!O41 -> 0.0758 | P31: ='Gebäudetechnik Technique'!P41 -> 220 | Q31: ='Gebäudetechnik Technique'!Q41 -> 218 | R31: ='Gebäudetechnik Technique'!R41 -> 1.41 | S31: ='Gebäudetechnik Technique'!S41 -> 43.5 | T31: ='Gebäudetechnik Technique'!T41 -> 38 | U31: ='Gebäudetechnik Technique'!U41 -> 5.48 | V31: ='Gebäudetechnik Technique'!F41 -> Stk. | W31: =VLOOKUP('Gebäudetechnik Technique'!E41,RefDimensions!A$2:B$15,2,false) -> device | X31: 0 | Y31: ='Gebäudetechnik Technique'!A41 -> 32.010 | Z31: KBOB 2016 | AA31: ="Alle > " & SWITCH(F31, "COMPONENT","BAUTEILE", "OTHER_RESOURCE", "RESSOURCEN", "BUILDING_TECHNOLOGY", "GEBÄUDETECHNIK", "MATERIAL", "MATERIALIEN") & " > kbob.admin.ch > KBOB / ecobau / IPB 2009/1:2016" -> Alle > GEBÄUDETECHNIK > kbob.admin.ch > KBOB / ecobau / IPB 2009/1:2016 | AB31: =VLOOKUP(LEFT(A31,6),MepClassificationAndLifecycle!A31:C97,3,false) -> 30
A32: ='Gebäudetechnik Technique'!A43 & " " & 'Gebäudetechnik Technique'!B43 & " (KBOB.2016)" -> 33.001 Sanitäranlagen, Büro, einfach, inkl. Apparate und Leitungen (KBOB.2016) | B32: =A32 -> 33.001 Sanitäranlagen, Büro, einfach, inkl. Apparate und Leitungen (KBOB.2016) | F32: BUILDING_TECHNOLOGY | G32: =IF(LEFT(A32, 2)="31", "BUILDING_TECHNOLOGY_HEATING", IF(LEFT(A32, 2)="32", "BUILDING_TECHNOLOGY_VENTILATION", IF(LEFT(A32, 2)="33", "BUILDING_TECHNOLOGY_SANITARY", IF(LEFT(A32, 2)="34", "BUILDING_TECHNOLOGY_ELECTRICAL")))) -> BUILDING_TECHNOLOGY_SANITARY | H32: =VLOOKUP(LEFT(A32,6),MepClassificationAndLifecycle!A32:C98,2,false) -> sanitary | J32: ='Gebäudetechnik Technique'!G43 -> 6980 | K32: ='Gebäudetechnik Technique'!H43 -> 6390 | L32: ='Gebäudetechnik Technique'!I43 -> 587 | M32: ='Gebäudetechnik Technique'!M43 -> 1.2 | N32: ='Gebäudetechnik Technique'!N43 -> 1.19 | O32: ='Gebäudetechnik Technique'!O43 -> 0.00458 | P32: ='Gebäudetechnik Technique'!P43 -> 19.6 | Q32: ='Gebäudetechnik Technique'!Q43 -> 19.4 | R32: ='Gebäudetechnik Technique'!R43 -> 0.137 | S32: ='Gebäudetechnik Technique'!S43 -> 4.48 | T32: ='Gebäudetechnik Technique'!T43 -> 3.33 | U32: ='Gebäudetechnik Technique'!U43 -> 1.15 | V32: ='Gebäudetechnik Technique'!F43 -> m2 | W32: =VLOOKUP('Gebäudetechnik Technique'!E43,RefDimensions!A$2:B$15,2,false) -> energyReferenceArea | X32: 0 | Y32: ='Gebäudetechnik Technique'!A43 -> 33.001 | Z32: KBOB 2016 | AA32: ="Alle > " & SWITCH(F32, "COMPONENT","BAUTEILE", "OTHER_RESOURCE", "RESSOURCEN", "BUILDING_TECHNOLOGY", "GEBÄUDETECHNIK", "MATERIAL", "MATERIALIEN") & " > kbob.admin.ch > KBOB / ecobau / IPB 2009/1:2016" -> Alle > GEBÄUDETECHNIK > kbob.admin.ch > KBOB / ecobau / IPB 2009/1:2016 | AB32: =VLOOKUP(LEFT(A32,6),MepClassificationAndLifecycle!A32:C98,3,false) -> 30
A33: ='Gebäudetechnik Technique'!A44 & " " & 'Gebäudetechnik Technique'!B44 & " (KBOB.2016)" -> 33.002 Sanitäranlagen, Büro, aufwändig, inkl. Apparate und Leitungen (KBOB.2016) | B33: =A33 -> 33.002 Sanitäranlagen, Büro, aufwändig, inkl. Apparate und Leitungen (KBOB.2016) | F33: BUILDING_TECHNOLOGY | G33: =IF(LEFT(A33, 2)="31", "BUILDING_TECHNOLOGY_HEATING", IF(LEFT(A33, 2)="32", "BUILDING_TECHNOLOGY_VENTILATION", IF(LEFT(A33, 2)="33", "BUILDING_TECHNOLOGY_SANITARY", IF(LEFT(A33, 2)="34", "BUILDING_TECHNOLOGY_ELECTRICAL")))) -> BUILDING_TECHNOLOGY_SANITARY | H33: =VLOOKUP(LEFT(A33,6),MepClassificationAndLifecycle!A33:C99,2,false) -> sanitary | J33: ='Gebäudetechnik Technique'!G44 -> 18600 | K33: ='Gebäudetechnik Technique'!H44 -> 16700 | L33: ='Gebäudetechnik Technique'!I44 -> 1950 | M33: ='Gebäudetechnik Technique'!M44 -> 3.37 | N33: ='Gebäudetechnik Technique'!N44 -> 3.35 | O33: ='Gebäudetechnik Technique'!O44 -> 0.0147 | P33: ='Gebäudetechnik Technique'!P44 -> 46.6 | Q33: ='Gebäudetechnik Technique'!Q44 -> 46.2 | R33: ='Gebäudetechnik Technique'!R44 -> 0.478 | S33: ='Gebäudetechnik Technique'!S44 -> 11.8 | T33: ='Gebäudetechnik Technique'!T44 -> 8.05 | U33: ='Gebäudetechnik Technique'!U44 -> 3.76 | V33: ='Gebäudetechnik Technique'!F44 -> m2 | W33: =VLOOKUP('Gebäudetechnik Technique'!E44,RefDimensions!A$2:B$15,2,false) -> energyReferenceArea | X33: 0 | Y33: ='Gebäudetechnik Technique'!A44 -> 33.002 | Z33: KBOB 2016 | AA33: ="Alle > " & SWITCH(F33, "COMPONENT","BAUTEILE", "OTHER_RESOURCE", "RESSOURCEN", "BUILDING_TECHNOLOGY", "GEBÄUDETECHNIK", "MATERIAL", "MATERIALIEN") & " > kbob.admin.ch > KBOB / ecobau / IPB 2009/1:2016" -> Alle > GEBÄUDETECHNIK > kbob.admin.ch > KBOB / ecobau / IPB 2009/1:2016 | AB33: =VLOOKUP(LEFT(A33,6),MepClassificationAndLifecycle!A33:C99,3,false) -> 30
A34: ='Gebäudetechnik Technique'!A45 & " " & 'Gebäudetechnik Technique'!B45 & " (KBOB.2016)" -> 33.003 Sanitäranlagen, Wohnen, inkl. Apparate und Leitungen (KBOB.2016) | B34: =A34 -> 33.003 Sanitäranlagen, Wohnen, inkl. Apparate und Leitungen (KBOB.2016) | F34: BUILDING_TECHNOLOGY | G34: =IF(LEFT(A34, 2)="31", "BUILDING_TECHNOLOGY_HEATING", IF(LEFT(A34, 2)="32", "BUILDING_TECHNOLOGY_VENTILATION", IF(LEFT(A34, 2)="33", "BUILDING_TECHNOLOGY_SANITARY", IF(LEFT(A34, 2)="34", "BUILDING_TECHNOLOGY_ELECTRICAL")))) -> BUILDING_TECHNOLOGY_SANITARY | H34: =VLOOKUP(LEFT(A34,6),MepClassificationAndLifecycle!A34:C100,2,false) -> sanitary | J34: ='Gebäudetechnik Technique'!G45 -> 24100 | K34: ='Gebäudetechnik Technique'!H45 -> 23200 | L34: ='Gebäudetechnik Technique'!I45 -> 833 | M34: ='Gebäudetechnik Technique'!M45 -> 3.85 | N34: ='Gebäudetechnik Technique'!N45 -> 3.83 | O34: ='Gebäudetechnik Technique'!O45 -> 0.0192 | P34: ='Gebäudetechnik Technique'!P45 -> 48.6 | Q34: ='Gebäudetechnik Technique'!Q45 -> 48.2 | R34: ='Gebäudetechnik Technique'!R45 -> 0.337 | S34: ='Gebäudetechnik Technique'!S45 -> 11.4 | T34: ='Gebäudetechnik Technique'!T45 -> 9.81 | U34: ='Gebäudetechnik Technique'!U45 -> 1.55 | V34: ='Gebäudetechnik Technique'!F45 -> m2 | W34: =VLOOKUP('Gebäudetechnik Technique'!E45,RefDimensions!A$2:B$15,2,false) -> energyReferenceArea | X34: 0 | Y34: ='Gebäudetechnik Technique'!A45 -> 33.003 | Z34: KBOB 2016 | AA34: ="Alle > " & SWITCH(F34, "COMPONENT","BAUTEILE", "OTHER_RESOURCE", "RESSOURCEN", "BUILDING_TECHNOLOGY", "GEBÄUDETECHNIK", "MATERIAL", "MATERIALIEN") & " > kbob.admin.ch > KBOB / ecobau / IPB 2009/1:2016" -> Alle > GEBÄUDETECHNIK > kbob.admin.ch > KBOB / ecobau / IPB 2009/1:2016 | AB34: =VLOOKUP(LEFT(A34,6),MepClassificationAndLifecycle!A34:C100,3,false) -> 30
A35: ='Gebäudetechnik Technique'!A47 & " " & 'Gebäudetechnik Technique'!B47 & " (KBOB.2016)" -> 34.001 Elektroanlagen Wohnen (KBOB.2016) | B35: =A35 -> 34.001 Elektroanlagen Wohnen (KBOB.2016) | F35: BUILDING_TECHNOLOGY | G35: =IF(LEFT(A35, 2)="31", "BUILDING_TECHNOLOGY_HEATING", IF(LEFT(A35, 2)="32", "BUILDING_TECHNOLOGY_VENTILATION", IF(LEFT(A35, 2)="33", "BUILDING_TECHNOLOGY_SANITARY", IF(LEFT(A35, 2)="34", "BUILDING_TECHNOLOGY_ELECTRICAL")))) -> BUILDING_TECHNOLOGY_ELECTRICAL | H35: =VLOOKUP(LEFT(A35,6),MepClassificationAndLifecycle!A35:C101,2,false) -> electrical | J35: ='Gebäudetechnik Technique'!G47 -> 47200 | K35: ='Gebäudetechnik Technique'!H47 -> 45400 | L35: ='Gebäudetechnik Technique'!I47 -> 1820 | M35: ='Gebäudetechnik Technique'!M47 -> 4.85 | N35: ='Gebäudetechnik Technique'!N47 -> 4.79 | O35: ='Gebäudetechnik Technique'!O47 -> 0.0581 | P35: ='Gebäudetechnik Technique'!P47 -> 55.4 | Q35: ='Gebäudetechnik Technique'!Q47 -> 54.6 | R35: ='Gebäudetechnik Technique'!R47 -> 0.757 | S35: ='Gebäudetechnik Technique'!S47 -> 12.7 | T35: ='Gebäudetechnik Technique'!T47 -> 9.3 | U35: ='Gebäudetechnik Technique'!U47 -> 3.4 | V35: ='Gebäudetechnik Technique'!F47 -> m2 | W35: =VLOOKUP('Gebäudetechnik Technique'!E47,RefDimensions!A$2:B$15,2,false) -> energyReferenceArea | X35: 0 | Y35: ='Gebäudetechnik Technique'!A47 -> 34.001 | Z35: KBOB 2016 | AA35: ="Alle > " & SWITCH(F35, "COMPONENT","BAUTEILE", "OTHER_RESOURCE", "RESSOURCEN", "BUILDING_TECHNOLOGY", "GEBÄUDETECHNIK", "MATERIAL", "MATERIALIEN") & " > kbob.admin.ch > KBOB / ecobau / IPB 2009/1:2016" -> Alle > GEBÄUDETECHNIK > kbob.admin.ch > KBOB / ecobau / IPB 2009/1:2016 | AB35: =VLOOKUP(LEFT(A35,6),MepClassificationAndLifecycle!A35:C101,3,false) -> 30
A36: ='Gebäudetechnik Technique'!A48 & " " & 'Gebäudetechnik Technique'!B48 & " (KBOB.2016)" -> 34.002 Elektroanlagen Büro (KBOB.2016) | B36: =A36 -> 34.002 Elektroanlagen Büro (KBOB.2016) | F36: BUILDING_TECHNOLOGY | G36: =IF(LEFT(A36, 2)="31", "BUILDING_TECHNOLOGY_HEATING", IF(LEFT(A36, 2)="32", "BUILDING_TECHNOLOGY_VENTILATION", IF(LEFT(A36, 2)="33", "BUILDING_TECHNOLOGY_SANITARY", IF(LEFT(A36, 2)="34", "BUILDING_TECHNOLOGY_ELECTRICAL")))) -> BUILDING_TECHNOLOGY_ELECTRICAL | H36: =VLOOKUP(LEFT(A36,6),MepClassificationAndLifecycle!A36:C102,2,false) -> electrical | J36: ='Gebäudetechnik Technique'!G48 -> 117000 | K36: ='Gebäudetechnik Technique'!H48 -> 116000 | L36: ='Gebäudetechnik Technique'!I48 -> 900 | M36: ='Gebäudetechnik Technique'!M48 -> 76.2 | N36: ='Gebäudetechnik Technique'!N48 -> 76.1 | O36: ='Gebäudetechnik Technique'!O48 -> 0.0483 | P36: ='Gebäudetechnik Technique'!P48 -> 114 | Q36: ='Gebäudetechnik Technique'!Q48 -> 113 | R36: ='Gebäudetechnik Technique'!R48 -> 0.832 | S36: ='Gebäudetechnik Technique'!S48 -> 23.8 | T36: ='Gebäudetechnik Technique'!T48 -> 22.4 | U36: ='Gebäudetechnik Technique'!U48 -> 1.45 | V36: ='Gebäudetechnik Technique'!F48 -> m2 | W36: =VLOOKUP('Gebäudetechnik Technique'!E48,RefDimensions!A$2:B$15,2,false) -> energyReferenceArea | X36: 0 | Y36: ='Gebäudetechnik Technique'!A48 -> 34.002 | Z36: KBOB 2016 | AA36: ="Alle > " & SWITCH(F36, "COMPONENT","BAUTEILE", "OTHER_RESOURCE", "RESSOURCEN", "BUILDING_TECHNOLOGY", "GEBÄUDETECHNIK", "MATERIAL", "MATERIALIEN") & " > kbob.admin.ch > KBOB / ecobau / IPB 2009/1:2016" -> Alle > GEBÄUDETECHNIK > kbob.admin.ch > KBOB / ecobau / IPB 2009/1:2016 | AB36: =VLOOKUP(LEFT(A36,6),MepClassificationAndLifecycle!A36:C102,3,false) -> 30
A37: ='Gebäudetechnik Technique'!A49 & " " & 'Gebäudetechnik Technique'!B49 & " (KBOB.2016)" -> 34.024 Solarstromanlage (KBOB.2016) | B37: =A37 -> 34.024 Solarstromanlage (KBOB.2016) | F37: BUILDING_TECHNOLOGY | G37: =IF(LEFT(A37, 2)="31", "BUILDING_TECHNOLOGY_HEATING", IF(LEFT(A37, 2)="32", "BUILDING_TECHNOLOGY_VENTILATION", IF(LEFT(A37, 2)="33", "BUILDING_TECHNOLOGY_SANITARY", IF(LEFT(A37, 2)="34", "BUILDING_TECHNOLOGY_ELECTRICAL")))) -> BUILDING_TECHNOLOGY_ELECTRICAL | H37: =VLOOKUP(LEFT(A37,6),MepClassificationAndLifecycle!A37:C103,2,false) -> photovoltaicSystem | J37: ='Gebäudetechnik Technique'!G49 -> 3170000 | K37: ='Gebäudetechnik Technique'!H49 -> 3170000 | M37: ='Gebäudetechnik Technique'!M49 -> 905 | N37: ='Gebäudetechnik Technique'!N49 -> 905 | P37: ='Gebäudetechnik Technique'!P49 -> 7390 | Q37: ='Gebäudetechnik Technique'!Q49 -> 7390 | S37: ='Gebäudetechnik Technique'!S49 -> 2080 | T37: ='Gebäudetechnik Technique'!T49 -> 2080 | V37: ='Gebäudetechnik Technique'!F49 -> kWp | W37: =VLOOKUP('Gebäudetechnik Technique'!E49,RefDimensions!A$2:B$15,2,false) -> maxPower | X37: 0 | Y37: ='Gebäudetechnik Technique'!A49 -> 34.024 | Z37: KBOB 2016 | AA37: ="Alle > " & SWITCH(F37, "COMPONENT","BAUTEILE", "OTHER_RESOURCE", "RESSOURCEN", "BUILDING_TECHNOLOGY", "GEBÄUDETECHNIK", "MATERIAL", "MATERIALIEN") & " > kbob.admin.ch > KBOB / ecobau / IPB 2009/1:2016" -> Alle > GEBÄUDETECHNIK > kbob.admin.ch > KBOB / ecobau / IPB 2009/1:2016 | AB37: =VLOOKUP(LEFT(A37,6),MepClassificationAndLifecycle!A37:C103,3,false) -> 30
A38: ='Gebäudetechnik Technique'!A50 & " " & 'Gebäudetechnik Technique'!B50 & " (KBOB.2016)" -> 34.025 Solarstromanlage Schrägdach (KBOB.2016) | B38: =A38 -> 34.025 Solarstromanlage Schrägdach (KBOB.2016) | F38: BUILDING_TECHNOLOGY | G38: =IF(LEFT(A38, 2)="31", "BUILDING_TECHNOLOGY_HEATING", IF(LEFT(A38, 2)="32", "BUILDING_TECHNOLOGY_VENTILATION", IF(LEFT(A38, 2)="33", "BUILDING_TECHNOLOGY_SANITARY", IF(LEFT(A38, 2)="34", "BUILDING_TECHNOLOGY_ELECTRICAL")))) -> BUILDING_TECHNOLOGY_ELECTRICAL | H38: =VLOOKUP(LEFT(A38,6),MepClassificationAndLifecycle!A38:C104,2,false) -> photovoltaicSystem | J38: ='Gebäudetechnik Technique'!G50 -> 3190000 | K38: ='Gebäudetechnik Technique'!H50 -> 3190000 | M38: ='Gebäudetechnik Technique'!M50 -> 897 | N38: ='Gebäudetechnik Technique'!N50 -> 897 | P38: ='Gebäudetechnik Technique'!P50 -> 7290 | Q38: ='Gebäudetechnik Technique'!Q50 -> 7290 | S38: ='Gebäudetechnik Technique'!S50 -> 2030 | T38: ='Gebäudetechnik Technique'!T50 -> 2030 | V38: ='Gebäudetechnik Technique'!F50 -> kWp | W38: =VLOOKUP('Gebäudetechnik Technique'!E50,RefDimensions!A$2:B$15,2,false) -> maxPower | X38: 0 | Y38: ='Gebäudetechnik Technique'!A50 -> 34.025 | Z38: KBOB 2016 | AA38: ="Alle > " & SWITCH(F38, "COMPONENT","BAUTEILE", "OTHER_RESOURCE", "RESSOURCEN", "BUILDING_TECHNOLOGY", "GEBÄUDETECHNIK", "MATERIAL", "MATERIALIEN") & " > kbob.admin.ch > KBOB / ecobau / IPB 2009/1:2016" -> Alle > GEBÄUDETECHNIK > kbob.admin.ch > KBOB / ecobau / IPB 2009/1:2016 | AB38: =VLOOKUP(LEFT(A38,6),MepClassificationAndLifecycle!A38:C104,3,false) -> 30
A39: ='Gebäudetechnik Technique'!A51 & " " & 'Gebäudetechnik Technique'!B51 & " (KBOB.2016)" -> 34.026 Solarstromanlage Flachdach (KBOB.2016) | B39: =A39 -> 34.026 Solarstromanlage Flachdach (KBOB.2016) | F39: BUILDING_TECHNOLOGY | G39: =IF(LEFT(A39, 2)="31", "BUILDING_TECHNOLOGY_HEATING", IF(LEFT(A39, 2)="32", "BUILDING_TECHNOLOGY_VENTILATION", IF(LEFT(A39, 2)="33", "BUILDING_TECHNOLOGY_SANITARY", IF(LEFT(A39, 2)="34", "BUILDING_TECHNOLOGY_ELECTRICAL")))) -> BUILDING_TECHNOLOGY_ELECTRICAL | H39: =VLOOKUP(LEFT(A39,6),MepClassificationAndLifecycle!A39:C105,2,false) -> photovoltaicSystem | J39: ='Gebäudetechnik Technique'!G51 -> 3070000 | K39: ='Gebäudetechnik Technique'!H51 -> 3070000 | M39: ='Gebäudetechnik Technique'!M51 -> 959 | N39: ='Gebäudetechnik Technique'!N51 -> 959 | P39: ='Gebäudetechnik Technique'!P51 -> 8020 | Q39: ='Gebäudetechnik Technique'!Q51 -> 8020 | S39: ='Gebäudetechnik Technique'!S51 -> 2320 | T39: ='Gebäudetechnik Technique'!T51 -> 2320 | V39: ='Gebäudetechnik Technique'!F51 -> kWp | W39: =VLOOKUP('Gebäudetechnik Technique'!E51,RefDimensions!A$2:B$15,2,false) -> maxPower | X39: 0 | Y39: ='Gebäudetechnik Technique'!A51 -> 34.026 | Z39: KBOB 2016 | AA39: ="Alle > " & SWITCH(F39, "COMPONENT","BAUTEILE", "OTHER_RESOURCE", "RESSOURCEN", "BUILDING_TECHNOLOGY", "GEBÄUDETECHNIK", "MATERIAL", "MATERIALIEN") & " > kbob.admin.ch > KBOB / ecobau / IPB 2009/1:2016" -> Alle > GEBÄUDETECHNIK > kbob.admin.ch > KBOB / ecobau / IPB 2009/1:2016 | AB39: =VLOOKUP(LEFT(A39,6),MepClassificationAndLifecycle!A39:C105,3,false) -> 30
A40: ='Gebäudetechnik Technique'!A52 & " " & 'Gebäudetechnik Technique'!B52 & " (KBOB.2016)" -> 34.027 Solarstromanlage Fassade (KBOB.2016) | B40: =A40 -> 34.027 Solarstromanlage Fassade (KBOB.2016) | F40: BUILDING_TECHNOLOGY | G40: =IF(LEFT(A40, 2)="31", "BUILDING_TECHNOLOGY_HEATING", IF(LEFT(A40, 2)="32", "BUILDING_TECHNOLOGY_VENTILATION", IF(LEFT(A40, 2)="33", "BUILDING_TECHNOLOGY_SANITARY", IF(LEFT(A40, 2)="34", "BUILDING_TECHNOLOGY_ELECTRICAL")))) -> BUILDING_TECHNOLOGY_ELECTRICAL | H40: =VLOOKUP(LEFT(A40,6),MepClassificationAndLifecycle!A40:C106,2,false) -> photovoltaicSystem | J40: ='Gebäudetechnik Technique'!G52 -> 3170000 | K40: ='Gebäudetechnik Technique'!H52 -> 3170000 | M40: ='Gebäudetechnik Technique'!M52 -> 905 | N40: ='Gebäudetechnik Technique'!N52 -> 905 | P40: ='Gebäudetechnik Technique'!P52 -> 7460 | Q40: ='Gebäudetechnik Technique'!Q52 -> 7460 | S40: ='Gebäudetechnik Technique'!S52 -> 2140 | T40: ='Gebäudetechnik Technique'!T52 -> 2140 | V40: ='Gebäudetechnik Technique'!F52 -> kWp | W40: =VLOOKUP('Gebäudetechnik Technique'!E52,RefDimensions!A$2:B$15,2,false) -> maxPower | X40: 0 | Y40: ='Gebäudetechnik Technique'!A52 -> 34.027 | Z40: KBOB 2016 | AA40: ="Alle > " & SWITCH(F40, "COMPONENT","BAUTEILE", "OTHER_RESOURCE", "RESSOURCEN", "BUILDING_TECHNOLOGY", "GEBÄUDETECHNIK", "MATERIAL", "MATERIALIEN") & " > kbob.admin.ch > KBOB / ecobau / IPB 2009/1:2016" -> Alle > GEBÄUDETECHNIK > kbob.admin.ch > KBOB / ecobau / IPB 2009/1:2016 | AB40: =VLOOKUP(LEFT(A40,6),MepClassificationAndLifecycle!A40:C106,3,false) -> 30

Sheet Gebäudetechnik Technique
B1: Ökobilanzdaten im Baubereich | M1: KBOB / eco-bau / IPB 2009/1:2016 | W1: Données des écobilans dans la construction
H3: UBP | I3: UBP | K3: PEF-ges | L3: PEF-ges | N3: PEF-e | O3: PEF-e | Q3: PEF-ne | R3: PEF-ne | T3: THG | U3: THG
A4: ID-Nummer | B4: GEBÄUDETECHNIK [Bibliographie B&H, BfU, treeze, version 2.2:2016] | C4: ID-Nummer Entsorgung | D4: Entsorgung | E4: Bezug Référence | G4: UBP'13 | J4: Primärenergie Energie primaire | S4: Treibhaus- gasemissionen | V4: Référence | W4: TECHNIQUE DU BÂTIMENT [Bibliographie B&H, BfU, treeze, version v2.2:2016]
A5: No d'identi-fication | C5: No d'identification Déchets | G5: UBP | J5: gesamt | M5: erneuerbar | P5: nicht erneuerbar | S5: Emissions de gaz
E6: Grösse | J6: globale | M6: renouvelable | P6: non renouvelable | S6: à effet de serre | V6: Dimension
G7: Total | H7: Herstellung | I7: Entsorgung | J7: Total | K7: Herstellung | L7: Entsorgung | M7: Total | N7: Herstellung | O7: Entsorgung | P7: Total | Q7: Herstellung | R7: Entsorgung | S7: Total | T7: Herstellung | U7: Entsorgung
G8: Total | H8: Fabrication | I8: Elimination | J8: Total | K8: Fabrication | L8: Elimination | M8: Total | N8: Fabrication | O8: Elimination | P8: Total | Q8: Fabrication | R8: Elimination | S8: Total | T8: Fabrication | U8: Elimination
F9: Einheit / Unité | G9: UBP | H9: UBP | I9: UBP | J9: kWh oil-eq | K9: kWh oil-eq | L9: kWh oil-eq | M9: kWh oil-eq | N9: kWh oil-eq | O9: kWh oil-eq | P9: kWh oil-eq | Q9: kWh oil-eq | R9: kWh oil-eq | S9: kg CO2-eq | T9: kg CO2-eq | U9: kg CO2-eq
A10: 31 | B10: Heizungsanlagen | W10: Installations de chauffage
A11: 31.001 | B11: Wärmeerzeuger, spez. Leistungsbedarf 10 W/m2 | C11: 92.006 | D11: Entsorgung, Wärmeerzeuger, spez. Leistungsbedarf 10 W/m2 | E11: EBF | F11: m2 | G11: 1200 | H11: 1190 | I11: 10.6 | J11: 2.51 | K11: 2.5 | L11: 0.0184 | M11: 0.236 | N11: 0.236 | O11: 0.000317 | P11: 2.28 | Q11: 2.26 | R11: 0.0181 | S11: 0.512 | T11: 0.501 | U11: 0.0109 | V11: SRE | W11: Prod. de chaleur, besoins en puissance 10 W/m2
A12: 31.002 | B12: Wärmeerzeuger, spez. Leistungsbedarf 30 W/m2 | C12: 92.007 | D12: Entsorgung, Wärmeerzeuger, spez. Leistungsbedarf 30 W/m2 | E12: EBF | F12: m2 | G12: 3590 | H12: 3560 | I12: 31.8 | J12: 7.54 | K12: 7.49 | L12: 0.0553 | M12: 0.708 | N12: 0.707 | O12: 0.000952 | P12: 6.83 | Q12: 6.78 | R12: 0.0544 | S12: 1.53 | T12: 1.5 | U12: 0.0327 | V12: SRE | W12: Prod.de chaleur, besoins en puissance 30 W/m2
A13: 31.003 | B13: Wärmeerzeuger, spez. Leistungsbedarf 50 W/m2 | C13: 92.008 | D13: Entsorgung, Wärmeerzeuger, spez. Leistungsbedarf 50 W/m2 | E13: EBF | F13: m2 | G13: 5990 | H13: 5930 | I13: 53 | J13: 12.6 | K13: 12.5 | L13: 0.0922 | M13: 1.18 | N13: 1.18 | O13: 0.00159 | P13: 11.4 | Q13: 11.3 | R13: 0.0906 | S13: 2.56 | T13: 2.5 | U13: 0.0545 | V13: SRE | W13: Prod.de chaleur, besoins en puissance 50 W/m2
A14: 31.021 | B14: Wärmeverteilung Wohngebäude | C14: 92.014 | D14: Entsorgung, Verteilung Wohngebäude | E14: EBF | F14: m2 | G14: 5480 | H14: 4670 | I14: 807 | J14: 15.8 | K14: 13.1 | L14: 2.7 | M14: 1.51 | N14: 1.14 | O14: 0.37 | P14: 14.3 | Q14: 12 | R14: 2.33 | S14: 3.07 | T14: 2.39 | U14: 0.674 | V14: SRE | W14: Distribution de chaleur, bâtiment d'habitation
A15: 31.022 | B15: Wärmeverteilung Bürogebäude | C15: 92.015 | D15: Entsorgung, Verteilung Bürogebäude | E15: EBF | F15: m2 | G15: 15000 | H15: 13900 | I15: 1090 | J15: 35.3 | K15: 32.1 | L15: 3.22 | M15: 2.68 | N15: 2.25 | O15: 0.433 | P15: 32.7 | Q15: 29.9 | R15: 2.79 | S15: 7.62 | T15: 6.56 | U15: 1.06 | V15: SRE | W15: Distribution de chaleur, bâtiment administratif
A16: 31.023 | B16: Wärmeabgabe über Heizkörper | C16: 92.016 | D16: Entsorgung, Abgabe über Heizkörper | E16: EBF | F16: m2 | G16: 10200 | H16: 10200 | I16: 17.9 | J16: 24.4 | K16: 24.4 | L16: 0.0371 | M16: 1.63 | N16: 1.62 | O16: 0.00185 | P16: 22.8 | Q16: 22.7 | R16: 0.0352 | S16: 5.46 | T16: 5.44 | U16: 0.0227 | V16: SRE | W16: Diffusion de chaleur par le biais du corps de chauffe
A17: 31.024 | B17: Wärmeabgabe über Fussbodenheizung | C17: 92.017 | D17: Entsorgung, Abgabe über Fussbodenheizung | E17: EBF | F17: m2 | G17: 4040 | H17: 3040 | I17: 997 | J17: 23.7 | K17: 23.6 | L17: 0.0933 | M17: 1.48 | N17: 1.48 | O17: 0.00165 | P17: 22.3 | Q17: 22.2 | R17: 0.0917 | S17: 5.06 | T17: 3.02 | U17: 2.04 | V17: SRE | W17: Diffusion de chaleur par le biais du chauffage au sol
A18: 31.025 | B18: Wärmeabgabe über Heizkühldecke (ohne Gips- oder Metalldecke) | C18: 92.018 | D18: Entsorgung, Abgabe über Heizkühldecke (ohne Gips- oder Metalldecke) | E18: EBF | F18: m2 | G18: 39400 | H18: 39400 | I18: 70.4 | J18: 30.8 | K18: 30.8 | L18: 0.0322 | M18: 4.47 | N18: 4.47 | O18: 0.00159 | P18: 26.4 | Q18: 26.3 | R18: 0.0306 | S18: 5.77 | T18: 5.64 | U18: 0.134 | V18: SRE | W18: Diffusion de chaleur par le biais du système de chauffage et de refroidissement au plafond
A19: 31.015 | B19: Wärmeverteilung und Abgabe, Luftheizung | C19: 92.019 | D19: Entsorgung, Wärmeverteilung und Abgabe, Luftheizung | E19: EBF | F19: m2 | G19: 2940 | H19: 2910 | I19: 33.6 | J19: 8.29 | K19: 8.28 | L19: 0.00656 | M19: 0.325 | N19: 0.325 | O19: 8.3e-05 | P19: 7.96 | Q19: 7.95 | R19: 0.00648 | S19: 1.7 | T19: 1.63 | U19: 0.0672 | V19: SRE | W19: Distribution de chaleur, chauffage à air chaud
A20: 31.016 | B20: Erdsonden, für Sole-Wasser-Wärmepumpe | C20: 92.009 | D20: Entsorgung, Erdsonden, für Sole-Wasser-Wärmepumpe | E20: Sondenlänge | F20: m | G20: 34600 | H20: 30500 | I20: 4100 | J20: 133 | K20: 131 | L20: 1.74 | M20: 2.87 | N20: 2.61 | O20: 0.255 | P20: 130 | Q20: 129 | R20: 1.48 | S20: 28.1 | T20: 25.3 | U20: 2.73 | V20: longueur | W20: Sondes géothermiques, pour la pompe à chaleur saumure-eau
A21: 31.017 | B21: Sole-Wasser Wärmepumpe 8 kW | C21: 92.010 | D21: Entsorgung, Sole-Wasser Wärmepumpe 8 kW | E21: Gerät | F21: Stk. | G21: 4220000 | H21: 3860000 | I21: 367000 | J21: 6030 | K21: 5980 | L21: 49 | M21: 506 | N21: 503 | O21: 3.82 | P21: 5520 | Q21: 5480 | R21: 45.2 | S21: 2180 | T21: 1470 | U21: 706 | V21: appareil | W21: Pompe à chaleur saumure-eau 8 kW
A22: 31.018 | B22: Sole-Wasser Wärmepumpe 8 kW | C22: 92.011 | D22: Entsorgung, Sole-Wasser Wärmepumpe 8 kW | E22: Masse | F22: kg | G22: 22500 | H22: 20600 | I22: 1960 | J22: 32.2 | K22: 31.9 | L22: 0.262 | M22: 2.7 | N22: 2.68 | O22: 0.0204 | P22: 29.5 | Q22: 29.2 | R22: 0.241 | S22: 11.6 | T22: 7.86 | U22: 3.77 | V22: masse | W22: Pompe à chaleur saumure-eau 8 kW
... A24: 31.020 | B24: Luft-Wasser Wärmepumpe 8 kW | C24: 92.013 | D24: Entsorgung, Luft-Wasser Wärmepumpe 8 kW | E24: Masse | F24: kg | G24: 22400 | H24: 20200 | I24: 2240 | J24: 29.1 | K24: 28.8 | L24: 0.268 | M24: 2.63 | N24: 2.61 | O24: 0.0206 | P24: 26.5 | Q24: 26.2 | R24: 0.248 | S24: 12 | T24: 7.62 | U24: 4.33 | V24: masse | W24: Pompe à chaleur air-eau 8 kW
A25: 31.007 | B25: Flachkollektor für Warmwasser EFH | C25: - | D25: Recycling | E25: Kollektorfläche | F25: m2 | G25: 676000 | H25: 676000 | I25: inkl. | J25: 1280 | K25: 1280 | L25: inkl. | M25: 142 | N25: 142 | O25: inkl. | P25: 1140 | Q25: 1140 | R25: inkl. | S25: 256 | T25: 256 | U25: inkl. | V25: Surf. collecteurs | W25: Collecteurs solaires plan, eau chaude maison individuelle
A26: 31.008 | B26: Flachkollektor für Raumheizung und Warmwasser EFH | C26: - | D26: Recycling | E26: Kollektorfläche | F26: m2 | G26: 452000 | H26: 452000 | I26: inkl. | J26: 926 | K26: 926 | L26: inkl. | M26: 102 | N26: 102 | O26: inkl. | P26: 824 | Q26: 824 | R26: inkl. | S26: 184 | T26: 184 | U26: inkl. | V26: Surf. collecteurs | W26: Collecteurs solaires plan, chaleur et eau chaude maison individuelle
A27: 31.009 | B27: Flachkollektor für Warmwasser MFH | C27: - | D27: Recycling | E27: Kollektorfläche | F27: m2 | G27: 394000 | H27: 394000 | I27: inkl. | J27: 774 | K27: 774 | L27: inkl. | M27: 79 | N27: 79 | O27: inkl. | P27: 695 | Q27: 695 | R27: inkl. | S27: 155 | T27: 155 | U27: inkl. | V27: Surf. collecteurs | W27: Collecteurs solaires plan, eau chaude immeuble locatif
A28: 31.010 | B28: Röhrenkollektor für Raumheizung und Warmwasser EFH | C28: - | D28: Recycling | E28: Kollektorfläche | F28: m2 | G28: 465000 | H28: 465000 | I28: inkl. | J28: 1020 | K28: 1020 | L28: inkl. | M28: 101 | N28: 101 | O28: inkl. | P28: 924 | Q28: 924 | R28: inkl. | S28: 208 | T28: 208 | U28: inkl. | V28: Surf. collecteurs | W28: Collecteurs solaires à tubes, chaleur et eau chaude maison individuelle
A29: 32 | B29: Lüftungsanlagen | W29: Ventilation
A30: 32.011 | B30: Lüftungsanlage, spez. Luftmenge 1 m3/hm2 EBF | C30: 92.027 | D30: Entsorgung, Lüftungsanlage, spez. Luftmenge 1 m3/hm2 EBF | E30: EBF | F30: m2 | G30: 31700 | H30: 31400 | I30: 222 | J30: 58.9 | K30: 58.6 | L30: 0.215 | M30: 4.35 | N30: 4.35 | O30: 0.00695 | P30: 54.5 | Q30: 54.3 | R30: 0.208 | S30: 12.7 | T30: 12.3 | U30: 0.345 | V30: SRE | W30: Ventilation bureau, canaux en tôle, besoins en air 1 m3/hm2 EBF
A31: 32.005 | B31: Lüftungsanlage, spez. Luftmenge 2 m3/hm2 EBF | C31: 92.028 | D31: Entsorgung, Lüftungsanlage, spez. Luftmenge 2 m3/hm2 EBF | E31: EBF | F31: m2 | G31: 42700 | H31: 42400 | I31: 311 | J31: 79.5 | K31: 79.2 | L31: 0.296 | M31: 5.85 | N31: 5.84 | O31: 0.00947 | P31: 73.6 | Q31: 73.3 | R31: 0.287 | S31: 17.1 | T31: 16.6 | U31: 0.485 | V31: SRE | W31: Ventilation bureau, canaux en tôle, besoins en air 2 m3/hm2 SRE
A32: 32.006 | B32: Lüftungsanlage, spez. Luftmenge 4 m3/hm2 EBF | C32: 92.029 | D32: Entsorgung, Lüftungsanlage, spez. Luftmenge 4 m3/hm2 EBF | E32: EBF | F32: m2 | G32: 64800 | H32: 64300 | I32: 488 | J32: 121 | K32: 120 | L32: 0.458 | M32: 8.84 | N32: 8.83 | O32: 0.0145 | P32: 112 | Q32: 111 | R32: 0.444 | S32: 25.9 | T32: 25.2 | U32: 0.763 | V32: SRE | W32: Ventilation bureau, canaux en tôle, besoins en air 4 m3/hm2 SRE
A33: 32.007 | B33: Lüftungsanlage, spez. Luftmenge 6 m3/hm2 EBF | C33: 92.030 | D33: Entsorgung, Lüftungsanlage, spez. Luftmenge 6 m3/hm2 EBF | E33: EBF | F33: m2 | G33: 86900 | H33: 86200 | I33: 666 | J33: 162 | K33: 161 | L33: 0.62 | M33: 11.8 | N33: 11.8 | O33: 0.0196 | P33: 150 | Q33: 149 | R33: 0.601 | S33: 34.8 | T33: 33.7 | U33: 1.04 | V33: SRE | W33: Ventilation bureau, canaux en tôle, besoins en air 6 m3/hm2 SRE
A34: 32.012 | B34: Lüftungsanlage, spez. Luftmenge 8 m3/hm2 EBF | C34: 92.031 | D34: Entsorgung, Lüftungsanlage, spez. Luftmenge 8 m3/hm2 EBF | E34: EBF | F34: m2 | G34: 109000 | H34: 108000 | I34: 843 | J34: 203 | K34: 202 | L34: 0.783 | M34: 14.8 | N34: 14.8 | O34: 0.0246 | P34: 188 | Q34: 187 | R34: 0.758 | S34: 43.6 | T34: 42.3 | U34: 1.32 | V34: SRE | W34: Ventilation bureau, canaux en tôle, besoins en air 8 m3/hm2 SRE
A35: 32.001 | B35: Lüftungsanlage Wohnen, Blechkanäle, inkl. Küchenabluft | C35: 92.021 | D35: Entsorgung, Lüftungsanlage Wohnen, Blechkanäle, inkl. Küchenabluft | E35: EBF | F35: m2 | G35: 45200 | H35: 45000 | I35: 182 | J35: 57.3 | K35: 57.2 | L35: 0.087 | M35: 3.99 | N35: 3.99 | O35: 0.00388 | P35: 53.3 | Q35: 53.2 | R35: 0.0831 | S35: 12 | T35: 11.7 | U35: 0.299 | V35: SRE | W35: Ventilation habitation, canaux en tôle, évacuation d'air (cuisine)
A36: 32.002 | B36: Lüftungsanlage Wohnen, PE-Kanäle, inkl. Küchenabluft | C36: 92.022 | D36: Entsorgung, Lüftungsanlage Wohnen, PE-Kanäle, inkl. Küchenabluft | E36: EBF | F36: m2 | G36: 22000 | H36: 21600 | I36: 371 | J36: 35 | K36: 34.9 | L36: 0.0768 | M36: 2.36 | N36: 2.36 | O36: 0.00253 | P36: 32.7 | Q36: 32.6 | R36: 0.0743 | S36: 7.32 | T36: 6.6 | U36: 0.724 | V36: SRE | W36: Ventilation habitation, canaux en HDPE, évacuation d'air (cuisine)
A37: 32.003 | B37: Abluftanlage Küche und Bad | C37: 92.023 | D37: Entsorgung, Abluftanlage Küche und Bad | E37: EBF | F37: m2 | G37: 13300 | H37: 13300 | I37: 65.7 | J37: 16.1 | K37: 16.1 | L37: 0.0167 | M37: 0.981 | N37: 0.98 | O37: 0.000208 | P37: 15.1 | Q37: 15.1 | R37: 0.0165 | S37: 3.4 | T37: 3.28 | U37: 0.126 | V37: SRE | W37: Evacuation d'air cuisine et salle de bain
A38: 32.004 | B38: Erdregister zu Lüftungsanlage Wohnen | C38: 92.024 | D38: Entsorgung, Erdregister zu Lüftungsanlage Wohnen | E38: EBF | F38: m2 | G38: 4550 | H38: 3220 | I38: 1330 | J38: 16.6 | K38: 15.3 | L38: 1.33 | M38: 0.554 | N38: 0.502 | O38: 0.0518 | P38: 16.1 | Q38: 14.8 | R38: 1.28 | S38: 4.55 | T38: 2.92 | U38: 1.63 | V38: SRE | W38: Registre de terre pour ventilation habitation
A39: 32.008 | B39: Erdregister kurz zu Lüftungsanlage Büro (0.27 m/m2 EBF) | C39: 92.025 | D39: Entsorgung, Erdregister kurz zu Lüftungsanlage Büro (0.27 m/m2 EBF) | E39: EBF | F39: m2 | G39: 7890 | H39: 5590 | I39: 2300 | J39: 28.8 | K39: 26.5 | L39: 2.31 | M39: 0.96 | N39: 0.87 | O39: 0.0898 | P39: 27.9 | Q39: 25.7 | R39: 2.22 | S39: 7.89 | T39: 5.06 | U39: 2.82 | V39: SRE | W39: Registre de terre court pour ventilation bureau (0.27 m/m2 SRE)
A40: 32.009 | B40: Erdregister lang zu Lüftungsanlage Büro (0.67 m/m2 EBF) | C40: 92.026 | D40: Entsorgung, Erdregister lang zu Lüftungsanlage Büro (0.67 m/m2 EBF) | E40: EBF | F40: m2 | G40: 19700 | H40: 14000 | I40: 5760 | J40: 72.1 | K40: 66.4 | L40: 5.77 | M40: 2.4 | N40: 2.18 | O40: 0.224 | P40: 69.7 | Q40: 64.2 | R40: 5.54 | S40: 19.7 | T40: 12.7 | U40: 7.05 | V40: SRE | W40: Registre de terre long pour ventilation bureau (0.67 m/m2 SRE)
A41: 32.010 | B41: Einzelraumlüfer Fenstermodell 10-30 m3/h, ohne Montage | C41: 92.020 | D41: Entsorgung, Einzelraumlüfer Fenstermodell 10-30 m3/h, ohne Montage | E41: Gerät | F41: Stk. | G41: 63200 | H41: 59900 | I41: 3260 | J41: 329 | K41: 327 | L41: 1.48 | M41: 109 | N41: 109 | O41: 0.0758 | P41: 220 | Q41: 218 | R41: 1.41 | S41: 43.5 | T41: 38 | U41: 5.48 | V41: appareil | W41: Ventilation pièce individuelle, modèle de fenêtre 10-30 m3/h, sans montage
A42: 33 | B42: Sanitäranlagen | W42: Installations sanitaires
A43: 33.001 | B43: Sanitäranlagen, Büro, einfach, inkl. Apparate und Leitungen | C43: 92.001 | D43: Entsorgung, Büro, einfache Installation, inkl. Apparate und Leitungen | E43: EBF | F43: m2 | G43: 6980 | H43: 6390 | I43: 587 | J43: 20.8 | K43: 20.6 | L43: 0.141 | M43: 1.2 | N43: 1.19 | O43: 0.00458 | P43: 19.6 | Q43: 19.4 | R43: 0.137 | S43: 4.48 | T43: 3.33 | U43: 1.15 | V43: SRE | W43: Bureau, degré de complexité faible, appareils et conduites compris
A44: 33.002 | B44: Sanitäranlagen, Büro, aufwändig, inkl. Apparate und Leitungen | C44: 92.002 | D44: Entsorgung, Büro, aufwändige Installation, inkl. Apparate und Leitungen | E44: EBF | F44: m2 | G44: 18600 | H44: 16700 | I44: 1950 | J44: 50 | K44: 49.5 | L44: 0.493 | M44: 3.37 | N44: 3.35 | O44: 0.0147 | P44: 46.6 | Q44: 46.2 | R44: 0.478 | S44: 11.8 | T44: 8.05 | U44: 3.76 | V44: SRE | W44: Bureau, degré de complexité élevé, appareils et conduites compris
A45: 33.003 | B45: Sanitäranlagen, Wohnen, inkl. Apparate und Leitungen | C45: 92.003 | D45: Entsorgung, Wohnen, inkl. Apparate und Leitungen | E45: EBF | F45: m2 | G45: 24100 | H45: 23200 | I45: 833 | J45: 52.4 | K45: 52.1 | L45: 0.357 | M45: 3.85 | N45: 3.83 | O45: 0.0192 | P45: 48.6 | Q45: 48.2 | R45: 0.337 | S45: 11.4 | T45: 9.81 | U45: 1.55 | V45: SRE | W45: Habitation, appareils et conduites compris
A46: 34 | B46: Elektroanlagen | W46: Installations électriques
A47: 34.001 | B47: Elektroanlagen Wohnen | C47: 92.004 | D47: Entsorgung, Elektroanlagen Wohnen | E47: EBF | F47: m2 | G47: 47200 | H47: 45400 | I47: 1820 | J47: 60.2 | K47: 59.4 | L47: 0.816 | M47: 4.85 | N47: 4.79 | O47: 0.0581 | P47: 55.4 | Q47: 54.6 | R47: 0.757 | S47: 12.7 | T47: 9.3 | U47: 3.4 | V47: SRE | W47: Installations électriques, habitation
A48: 34.002 | B48: Elektroanlagen Büro | C48: 92.005 | D48: Entsorgung, Elektroanlagen Büro | E48: EBF | F48: m2 | G48: 117000 | H48: 116000 | I48: 900 | J48: 190 | K48: 189 | L48: 0.88 | M48: 76.2 | N48: 76.1 | O48: 0.0483 | P48: 114 | Q48: 113 | R48: 0.832 | S48: 23.8 | T48: 22.4 | U48: 1.45 | V48: SRE | W48: Installations électriques, bureau
A49: 34.024 | B49: Solarstromanlage | C49: 92.006 | D49: Entsorgung, Wärmeerzeuger, spez. Leistungsbedarf 10 W/m2 | E49: Max. Leistung | F49: kWp | G49: 3170000 | H49: 3170000 | I49: inkl. | J49: 8300 | K49: 8300 | L49: inkl. | M49: 905 | N49: 905 | O49: inkl. | P49: 7390 | Q49: 7390 | R49: inkl. | S49: 2080 | T49: 2080 | U49: inkl. | V49: Puissance max. | W49: Installations photovoltaïque
A50: 34.025 | B50: Solarstromanlage Schrägdach | C50: 92.007 | D50: Entsorgung, Wärmeerzeuger, spez. Leistungsbedarf 30 W/m2 | E50: Max. Leistung | F50: kWp | G50: 3190000 | H50: 3190000 | I50: inkl. | J50: 8190 | K50: 8190 | L50: inkl. | M50: 897 | N50: 897 | O50: inkl. | P50: 7290 | Q50: 7290 | R50: inkl. | S50: 2030 | T50: 2030 | U50: inkl. | V50: Puissance max. | W50: Installations photovoltaïque toiture inclinée
A51: 34.026 | B51: Solarstromanlage Flachdach | C51: 92.008 | D51: Entsorgung, Wärmeerzeuger, spez. Leistungsbedarf 50 W/m2 | E51: Max. Leistung | F51: kWp | G51: 3070000 | H51: 3070000 | I51: inkl. | J51: 8970 | K51: 8970 | L51: inkl. | M51: 959 | N51: 959 | O51: inkl. | P51: 8020 | Q51: 8020 | R51: inkl. | S51: 2320 | T51: 2320 | U51: inkl. | V51: Puissance max. | W51: Installations photovoltaïque toiture plate
A52: 34.027 | B52: Solarstromanlage Fassade | C52: 92.009 | D52: Entsorgung, Erdsonden, für Sole-Wasser-Wärmepumpe | E52: Max. Leistung | F52: kWp | G52: 3170000 | H52: 3170000 | I52: inkl. | J52: 8360 | K52: 8360 | L52: inkl. | M52: 905 | N52: 905 | O52: inkl. | P52: 7460 | Q52: 7460 | R52: inkl. | S52: 2140 | T52: 2140 | U52: inkl. | V52: Puissance max. | W52: Installations photovoltaïque façade

Sheet ImportEnergie
A1: Name | B1: ProductKey | C1: Description | D1: Picture | E1: Product sections | F1: Type | G1: SubType | H1: vyzn.catalogue.Density | I1: vyzn.catalogue.ch.KBOB2022.UBPTotal | J1: vyzn.catalogue.ch.KBOB2022.UBPProduction | K1: vyzn.catalogue.ch.KBOB2022.UBPDisposal | L1: vyzn.catalogue.ch.KBOB2022.RenewableEnergyTotal | M1: vyzn.catalogue.ch.KBOB2022.RenewableEnergyProduction | N1: vyzn.catalogue.ch.KBOB2022.RenewableEnergyDisposal | O1: vyzn.catalogue.ch.KBOB2022.GreyEnergyTotal | P1: vyzn.catalogue.ch.KBOB2022.GreyEnergyProduction | Q1: vyzn.catalogue.ch.KBOB2022.GreyEnergyDisposal | R1: vyzn.catalogue.ch.KBOB2022.GHGEmissionsTotal | S1: vyzn.catalogue.ch.KBOB2022.GHGEmissionsProduction | T1: vyzn.catalogue.ch.KBOB2022.GHGEmissionsDisposal | U1: vyzn.catalogue.ch.KBOB2022.LCARefUnit | V1: vyzn.catalogue.ch.KBOB2022.LCARefDimension | W1: vyzn.catalogue.ch.KBOB2022.BiogenicCarbon | X1: KBOB REF | Y1: vyzn.catalogue.SourceENV | Z1: vyzn.catalogue.lifeCycle | AA1: categoryPath
A2: 41.001 Heizöl EL (KBOB.2016) | B2: 41.001 Heizöl EL (KBOB.2016) | F2: OTHER_RESOURCE | G2: OTHER_RESOURCE_ENERGY_FUEL | I2: 234 | L2: 0.00902 | O2: 1.23 | R2: 0.301 | U2: kWh | V2: finalEnergy | X2: 41.001 | Y2: KBOB 2016 | Z2: 60 | AA2: Alle > RESSOURCEN > kbob.admin.ch > KBOB / ecobau / IPB 2009/1:2016
A3: 41.002 Erdgas (KBOB.2016) | B3: 41.002 Erdgas (KBOB.2016) | F3: OTHER_RESOURCE | G3: OTHER_RESOURCE_ENERGY_FUEL | I3: 137 | L3: 0.00447 | O3: 1.06 | R3: 0.228 | U3: kWh | V3: finalEnergy | X3: 41.002 | Y3: KBOB 2016 | Z3: 60 | AA3: Alle > RESSOURCEN > kbob.admin.ch > KBOB / ecobau / IPB 2009/1:2016
A4: 41.003 Propan/Butan (KBOB.2016) | B4: 41.003 Propan/Butan (KBOB.2016) | F4: OTHER_RESOURCE | G4: OTHER_RESOURCE_ENERGY_FUEL | I4: 200 | L4: 0.00841 | O4: 1.15 | R4: 0.273 | U4: kWh | V4: finalEnergy | X4: 41.003 | Y4: KBOB 2016 | Z4: 60 | AA4: Alle > RESSOURCEN > kbob.admin.ch > KBOB / ecobau / IPB 2009/1:2016
A5: 41.004 Kohle Koks (KBOB.2016) | B5: 41.004 Kohle Koks (KBOB.2016) | F5: OTHER_RESOURCE | G5: OTHER_RESOURCE_ENERGY_FUEL | I5: 477 | L5: 0.0132 | O5: 1.45 | R5: 0.439 | U5: kWh | V5: finalEnergy | X5: 41.004 | Y5: KBOB 2016 | Z5: 60 | AA5: Alle > RESSOURCEN > kbob.admin.ch > KBOB / ecobau / IPB 2009/1:2016
A6: 41.005 Kohle Brikett (KBOB.2016) | B6: 41.005 Kohle Brikett (KBOB.2016) | F6: OTHER_RESOURCE | G6: OTHER_RESOURCE_ENERGY_FUEL | I6: 456 | L6: 0.00831 | O6: 1.2 | R6: 0.399 | U6: kWh | V6: finalEnergy | X6: 41.005 | Y6: KBOB 2016 | Z6: 60 | AA6: Alle > RESSOURCEN > kbob.admin.ch > KBOB / ecobau / IPB 2009/1:2016
A7: 41.006 Stückholz (KBOB.2016) | B7: 41.006 Stückholz (KBOB.2016) | F7: OTHER_RESOURCE | G7: OTHER_RESOURCE_ENERGY_FUEL | I7: 93.1 | L7: 0.994 | O7: 0.116 | R7: 0.0274 | U7: kWh | V7: finalEnergy | X7: 41.006 | Y7: KBOB 2016 | Z7: 60 | AA7: Alle > RESSOURCEN > kbob.admin.ch > KBOB / ecobau / IPB 2009/1:2016
A8: 41.010 Stückholz mit Partikelfilter (KBOB.2016) | B8: 41.010 Stückholz mit Partikelfilter (KBOB.2016) | F8: OTHER_RESOURCE | G8: OTHER_RESOURCE_ENERGY_FUEL | I8: 88.2 | L8: 0.994 | O8: 0.119 | R8: 0.0275 | U8: kWh | V8: finalEnergy | X8: 41.010 | Y8: KBOB 2016 | Z8: 60 | AA8: Alle > RESSOURCEN > kbob.admin.ch > KBOB / ecobau / IPB 2009/1:2016
A9: 41.007 Holzschnitzel (KBOB.2016) | B9: 41.007 Holzschnitzel (KBOB.2016) | F9: OTHER_RESOURCE | G9: OTHER_RESOURCE_ENERGY_FUEL | I9: 80.8 | L9: 1.05 | O9: 0.0628 | R9: 0.0107 | U9: kWh | V9: finalEnergy | X9: 41.007 | Y9: KBOB 2016 | Z9: 60 | AA9: Alle > RESSOURCEN > kbob.admin.ch > KBOB / ecobau / IPB 2009/1:2016
A10: 41.011 Holzschnitzel mit Partikelfilter (KBOB.2016) | B10: 41.011 Holzschnitzel mit Partikelfilter (KBOB.2016) | F10: OTHER_RESOURCE | G10: OTHER_RESOURCE_ENERGY_FUEL | I10: 73.7 | L10: 1.05 | O10: 0.0651 | R10: 0.0108 | U10: kWh | V10: finalEnergy | X10: 41.011 | Y10: KBOB 2016 | Z10: 60 | AA10: Alle > RESSOURCEN > kbob.admin.ch > KBOB / ecobau / IPB 2009/1:2016
A11: 41.008 Pellets (KBOB.2016) | B11: 41.008 Pellets (KBOB.2016) | F11: OTHER_RESOURCE | G11: OTHER_RESOURCE_ENERGY_FUEL | I11: 81.1 | L11: 1.04 | O11: 0.157 | R11: 0.0272 | U11: kWh | V11: finalEnergy | X11: 41.008 | Y11: KBOB 2016 | Z11: 60 | AA11: Alle > RESSOURCEN > kbob.admin.ch > KBOB / ecobau / IPB 2009/1:2016
A12: 41.012 Pellets mit Partikelfilter (KBOB.2016) | B12: 41.012 Pellets mit Partikelfilter (KBOB.2016) | F12: OTHER_RESOURCE | G12: OTHER_RESOURCE_ENERGY_FUEL | I12: 76.8 | L12: 1.04 | O12: 0.16 | R12: 0.0273 | U12: kWh | V12: finalEnergy | X12: 41.012 | Y12: KBOB 2016 | Z12: 60 | AA12: Alle > RESSOURCEN > kbob.admin.ch > KBOB / ecobau / IPB 2009/1:2016
A13: 41.009 Biogas (KBOB.2016) | B13: 41.009 Biogas (KBOB.2016) | F13: OTHER_RESOURCE | G13: OTHER_RESOURCE_ENERGY_FUEL | I13: 109 | L13: 0.0321 | O13: 0.299 | R13: 0.13 | U13: kWh | V13: finalEnergy | X13: 41.009 | Y13: KBOB 2016 | Z13: 60 | AA13: Alle > RESSOURCEN > kbob.admin.ch > KBOB / ecobau / IPB 2009/1:2016
... A81: 46.008 Kleinblockheizkraftwerk, Erdgas (KBOB.2016) | B81: 46.008 Kleinblockheizkraftwerk, Erdgas (KBOB.2016) | F81: OTHER_RESOURCE | G81: OTHER_RESOURCE_ENERGY_ELECTRICITY_GENERATED_LOCALLY | I81: 447 | L81: 0.00704 | O81: 3.39 | R81: 0.749 | U81: kWh | V81: finalEnergy | X81: 46.008 | Y81: KBOB 2016 | Z81: 60 | AA81: Alle > RESSOURCEN > kbob.admin.ch > KBOB / ecobau / IPB 2009/1:2016

Sheet ConsolidatedEnergie
A1: Name | B1: ProductKey | C1: Description | D1: Picture | E1: Product sections | F1: Type | G1: SubType | H1: vyzn.catalogue.Density | I1: vyzn.catalogue.ch.KBOB2022.UBPTotal | J1: vyzn.catalogue.ch.KBOB2022.UBPProduction | K1: vyzn.catalogue.ch.KBOB2022.UBPDisposal | L1: vyzn.catalogue.ch.KBOB2022.RenewableEnergyTotal | M1: vyzn.catalogue.ch.KBOB2022.RenewableEnergyProduction | N1: vyzn.catalogue.ch.KBOB2022.RenewableEnergyDisposal | O1: vyzn.catalogue.ch.KBOB2022.GreyEnergyTotal | P1: vyzn.catalogue.ch.KBOB2022.GreyEnergyProduction | Q1: vyzn.catalogue.ch.KBOB2022.GreyEnergyDisposal | R1: vyzn.catalogue.ch.KBOB2022.GHGEmissionsTotal | S1: vyzn.catalogue.ch.KBOB2022.GHGEmissionsProduction | T1: vyzn.catalogue.ch.KBOB2022.GHGEmissionsDisposal | U1: vyzn.catalogue.ch.KBOB2022.LCARefUnit | V1: vyzn.catalogue.ch.KBOB2022.LCARefDimension | W1: vyzn.catalogue.ch.KBOB2022.BiogenicCarbon | X1: KBOB REF | Y1: vyzn.catalogue.SourceENV | Z1: vyzn.catalogue.lifeCycle | AA1: categoryPath
A2: ='Energie Énergie'!A9 & " " & 'Energie Énergie'!B9 & " (KBOB.2016)" -> 41.001 Heizöl EL (KBOB.2016) | B2: =A2 -> 41.001 Heizöl EL (KBOB.2016) | F2: OTHER_RESOURCE | G2: =SWITCH(LEFT(A2,2), "41", "OTHER_RESOURCE_ENERGY_FUEL", "42", "OTHER_RESOURCE_ENERGY_DISTRICT_HEAT", "43", "OTHER_RESOURCE_ENERGY_USEFUL_HEAT", "44", "OTHER_RESOURCE_ENERGY_USEFUL_HEAT_GENERATED_LOCALLY", "45", "OTHER_RESOURCE_ENERGY_ELECTRICITY_NET", "46", "OTHER_RESOURCE_ENERGY_ELECTRICITY_GENERATED_LOCALLY") -> OTHER_RESOURCE_ENERGY_FUEL | I2: ='Energie Énergie'!E9 -> 234 | L2: ='Energie Énergie'!G9 -> 0.00902 | O2: ='Energie Énergie'!H9 -> 1.23 | R2: ='Energie Énergie'!J9 -> 0.301 | U2: ='Energie Énergie'!D9 -> kWh | V2: =VLOOKUP('Energie Énergie'!C9,RefDimensions!A$2:B$16,2,false) -> finalEnergy | X2: =LEFT(A2,6) -> 41.001 | Y2: KBOB 2016 | Z2: 60 | AA2: ="Alle > " & SWITCH(F2, "COMPONENT","BAUTEILE", "OTHER_RESOURCE", "RESSOURCEN", "BUILDING_TECHNOLOGY", "GEBÄUDETECHNIK", "MATERIAL", "MATERIALIEN") & " > kbob.admin.ch > KBOB / ecobau / IPB 2009/1:2016" -> Alle > RESSOURCEN > kbob.admin.ch > KBOB / ecobau / IPB 2009/1:2016
A3: ='Energie Énergie'!A10 & " " & 'Energie Énergie'!B10 & " (KBOB.2016)" -> 41.002 Erdgas (KBOB.2016) | B3: =A3 -> 41.002 Erdgas (KBOB.2016) | F3: OTHER_RESOURCE | G3: =SWITCH(LEFT(A3,2), "41", "OTHER_RESOURCE_ENERGY_FUEL", "42", "OTHER_RESOURCE_ENERGY_DISTRICT_HEAT", "43", "OTHER_RESOURCE_ENERGY_USEFUL_HEAT", "44", "OTHER_RESOURCE_ENERGY_USEFUL_HEAT_GENERATED_LOCALLY", "45", "OTHER_RESOURCE_ENERGY_ELECTRICITY_NET", "46", "OTHER_RESOURCE_ENERGY_ELECTRICITY_GENERATED_LOCALLY") -> OTHER_RESOURCE_ENERGY_FUEL | I3: ='Energie Énergie'!E10 -> 137 | L3: ='Energie Énergie'!G10 -> 0.00447 | O3: ='Energie Énergie'!H10 -> 1.06 | R3: ='Energie Énergie'!J10 -> 0.228 | U3: ='Energie Énergie'!D10 -> kWh | V3: =VLOOKUP('Energie Énergie'!C10,RefDimensions!A$2:B$16,2,false) -> finalEnergy | X3: =LEFT(A3,6) -> 41.002 | Y3: KBOB 2016 | Z3: 60 | AA3: ="Alle > " & SWITCH(F3, "COMPONENT","BAUTEILE", "OTHER_RESOURCE", "RESSOURCEN", "BUILDING_TECHNOLOGY", "GEBÄUDETECHNIK", "MATERIAL", "MATERIALIEN") & " > kbob.admin.ch > KBOB / ecobau / IPB 2009/1:2016" -> Alle > RESSOURCEN > kbob.admin.ch > KBOB / ecobau / IPB 2009/1:2016
A4: ='Energie Énergie'!A11 & " " & 'Energie Énergie'!B11 & " (KBOB.2016)" -> 41.003 Propan/Butan (KBOB.2016) | B4: =A4 -> 41.003 Propan/Butan (KBOB.2016) | F4: OTHER_RESOURCE | G4: =SWITCH(LEFT(A4,2), "41", "OTHER_RESOURCE_ENERGY_FUEL", "42", "OTHER_RESOURCE_ENERGY_DISTRICT_HEAT", "43", "OTHER_RESOURCE_ENERGY_USEFUL_HEAT", "44", "OTHER_RESOURCE_ENERGY_USEFUL_HEAT_GENERATED_LOCALLY", "45", "OTHER_RESOURCE_ENERGY_ELECTRICITY_NET", "46", "OTHER_RESOURCE_ENERGY_ELECTRICITY_GENERATED_LOCALLY") -> OTHER_RESOURCE_ENERGY_FUEL | I4: ='Energie Énergie'!E11 -> 200 | L4: ='Energie Énergie'!G11 -> 0.00841 | O4: ='Energie Énergie'!H11 -> 1.15 | R4: ='Energie Énergie'!J11 -> 0.273 | U4: ='Energie Énergie'!D11 -> kWh | V4: =VLOOKUP('Energie Énergie'!C11,RefDimensions!A$2:B$16,2,false) -> finalEnergy | X4: =LEFT(A4,6) -> 41.003 | Y4: KBOB 2016 | Z4: 60 | AA4: ="Alle > " & SWITCH(F4, "COMPONENT","BAUTEILE", "OTHER_RESOURCE", "RESSOURCEN", "BUILDING_TECHNOLOGY", "GEBÄUDETECHNIK", "MATERIAL", "MATERIALIEN") & " > kbob.admin.ch > KBOB / ecobau / IPB 2009/1:2016" -> Alle > RESSOURCEN > kbob.admin.ch > KBOB / ecobau / IPB 2009/1:2016
A5: ='Energie Énergie'!A12 & " " & 'Energie Énergie'!B12 & " (KBOB.2016)" -> 41.004 Kohle Koks (KBOB.2016) | B5: =A5 -> 41.004 Kohle Koks (KBOB.2016) | F5: OTHER_RESOURCE | G5: =SWITCH(LEFT(A5,2), "41", "OTHER_RESOURCE_ENERGY_FUEL", "42", "OTHER_RESOURCE_ENERGY_DISTRICT_HEAT", "43", "OTHER_RESOURCE_ENERGY_USEFUL_HEAT", "44", "OTHER_RESOURCE_ENERGY_USEFUL_HEAT_GENERATED_LOCALLY", "45", "OTHER_RESOURCE_ENERGY_ELECTRICITY_NET", "46", "OTHER_RESOURCE_ENERGY_ELECTRICITY_GENERATED_LOCALLY") -> OTHER_RESOURCE_ENERGY_FUEL | I5: ='Energie Énergie'!E12 -> 477 | L5: ='Energie Énergie'!G12 -> 0.0132 | O5: ='Energie Énergie'!H12 -> 1.45 | R5: ='Energie Énergie'!J12 -> 0.439 | U5: ='Energie Énergie'!D12 -> kWh | V5: =VLOOKUP('Energie Énergie'!C12,RefDimensions!A$2:B$16,2,false) -> finalEnergy | X5: =LEFT(A5,6) -> 41.004 | Y5: KBOB 2016 | Z5: 60 | AA5: ="Alle > " & SWITCH(F5, "COMPONENT","BAUTEILE", "OTHER_RESOURCE", "RESSOURCEN", "BUILDING_TECHNOLOGY", "GEBÄUDETECHNIK", "MATERIAL", "MATERIALIEN") & " > kbob.admin.ch > KBOB / ecobau / IPB 2009/1:2016" -> Alle > RESSOURCEN > kbob.admin.ch > KBOB / ecobau / IPB 2009/1:2016
A6: ='Energie Énergie'!A13 & " " & 'Energie Énergie'!B13 & " (KBOB.2016)" -> 41.005 Kohle Brikett (KBOB.2016) | B6: =A6 -> 41.005 Kohle Brikett (KBOB.2016) | F6: OTHER_RESOURCE | G6: =SWITCH(LEFT(A6,2), "41", "OTHER_RESOURCE_ENERGY_FUEL", "42", "OTHER_RESOURCE_ENERGY_DISTRICT_HEAT", "43", "OTHER_RESOURCE_ENERGY_USEFUL_HEAT", "44", "OTHER_RESOURCE_ENERGY_USEFUL_HEAT_GENERATED_LOCALLY", "45", "OTHER_RESOURCE_ENERGY_ELECTRICITY_NET", "46", "OTHER_RESOURCE_ENERGY_ELECTRICITY_GENERATED_LOCALLY") -> OTHER_RESOURCE_ENERGY_FUEL | I6: ='Energie Énergie'!E13 -> 456 | L6: ='Energie Énergie'!G13 -> 0.00831 | O6: ='Energie Énergie'!H13 -> 1.2 | R6: ='Energie Énergie'!J13 -> 0.399 | U6: ='Energie Énergie'!D13 -> kWh | V6: =VLOOKUP('Energie Énergie'!C13,RefDimensions!A$2:B$16,2,false) -> finalEnergy | X6: =LEFT(A6,6) -> 41.005 | Y6: KBOB 2016 | Z6: 60 | AA6: ="Alle > " & SWITCH(F6, "COMPONENT","BAUTEILE", "OTHER_RESOURCE", "RESSOURCEN", "BUILDING_TECHNOLOGY", "GEBÄUDETECHNIK", "MATERIAL", "MATERIALIEN") & " > kbob.admin.ch > KBOB / ecobau / IPB 2009/1:2016" -> Alle > RESSOURCEN > kbob.admin.ch > KBOB / ecobau / IPB 2009/1:2016
A7: ='Energie Énergie'!A14 & " " & 'Energie Énergie'!B14 & " (KBOB.2016)" -> 41.006 Stückholz (KBOB.2016) | B7: =A7 -> 41.006 Stückholz (KBOB.2016) | F7: OTHER_RESOURCE | G7: =SWITCH(LEFT(A7,2), "41", "OTHER_RESOURCE_ENERGY_FUEL", "42", "OTHER_RESOURCE_ENERGY_DISTRICT_HEAT", "43", "OTHER_RESOURCE_ENERGY_USEFUL_HEAT", "44", "OTHER_RESOURCE_ENERGY_USEFUL_HEAT_GENERATED_LOCALLY", "45", "OTHER_RESOURCE_ENERGY_ELECTRICITY_NET", "46", "OTHER_RESOURCE_ENERGY_ELECTRICITY_GENERATED_LOCALLY") -> OTHER_RESOURCE_ENERGY_FUEL | I7: ='Energie Énergie'!E14 -> 93.1 | L7: ='Energie Énergie'!G14 -> 0.994 | O7: ='Energie Énergie'!H14 -> 0.116 | R7: ='Energie Énergie'!J14 -> 0.0274 | U7: ='Energie Énergie'!D14 -> kWh | V7: =VLOOKUP('Energie Énergie'!C14,RefDimensions!A$2:B$16,2,false) -> finalEnergy | X7: =LEFT(A7,6) -> 41.006 | Y7: KBOB 2016 | Z7: 60 | AA7: ="Alle > " & SWITCH(F7, "COMPONENT","BAUTEILE", "OTHER_RESOURCE", "RESSOURCEN", "BUILDING_TECHNOLOGY", "GEBÄUDETECHNIK", "MATERIAL", "MATERIALIEN") & " > kbob.admin.ch > KBOB / ecobau / IPB 2009/1:2016" -> Alle > RESSOURCEN > kbob.admin.ch > KBOB / ecobau / IPB 2009/1:2016
A8: ='Energie Énergie'!A15 & " " & 'Energie Énergie'!B15 & " (KBOB.2016)" -> 41.010 Stückholz mit Partikelfilter (KBOB.2016) | B8: =A8 -> 41.010 Stückholz mit Partikelfilter (KBOB.2016) | F8: OTHER_RESOURCE | G8: =SWITCH(LEFT(A8,2), "41", "OTHER_RESOURCE_ENERGY_FUEL", "42", "OTHER_RESOURCE_ENERGY_DISTRICT_HEAT", "43", "OTHER_RESOURCE_ENERGY_USEFUL_HEAT", "44", "OTHER_RESOURCE_ENERGY_USEFUL_HEAT_GENERATED_LOCALLY", "45", "OTHER_RESOURCE_ENERGY_ELECTRICITY_NET", "46", "OTHER_RESOURCE_ENERGY_ELECTRICITY_GENERATED_LOCALLY") -> OTHER_RESOURCE_ENERGY_FUEL | I8: ='Energie Énergie'!E15 -> 88.2 | L8: ='Energie Énergie'!G15 -> 0.994 | O8: ='Energie Énergie'!H15 -> 0.119 | R8: ='Energie Énergie'!J15 -> 0.0275 | U8: ='Energie Énergie'!D15 -> kWh | V8: =VLOOKUP('Energie Énergie'!C15,RefDimensions!A$2:B$16,2,false) -> finalEnergy | X8: =LEFT(A8,6) -> 41.010 | Y8: KBOB 2016 | Z8: 60 | AA8: ="Alle > " & SWITCH(F8, "COMPONENT","BAUTEILE", "OTHER_RESOURCE", "RESSOURCEN", "BUILDING_TECHNOLOGY", "GEBÄUDETECHNIK", "MATERIAL", "MATERIALIEN") & " > kbob.admin.ch > KBOB / ecobau / IPB 2009/1:2016" -> Alle > RESSOURCEN > kbob.admin.ch > KBOB / ecobau / IPB 2009/1:2016
A9: ='Energie Énergie'!A16 & " " & 'Energie Énergie'!B16 & " (KBOB.2016)" -> 41.007 Holzschnitzel (KBOB.2016) | B9: =A9 -> 41.007 Holzschnitzel (KBOB.2016) | F9: OTHER_RESOURCE | G9: =SWITCH(LEFT(A9,2), "41", "OTHER_RESOURCE_ENERGY_FUEL", "42", "OTHER_RESOURCE_ENERGY_DISTRICT_HEAT", "43", "OTHER_RESOURCE_ENERGY_USEFUL_HEAT", "44", "OTHER_RESOURCE_ENERGY_USEFUL_HEAT_GENERATED_LOCALLY", "45", "OTHER_RESOURCE_ENERGY_ELECTRICITY_NET", "46", "OTHER_RESOURCE_ENERGY_ELECTRICITY_GENERATED_LOCALLY") -> OTHER_RESOURCE_ENERGY_FUEL | I9: ='Energie Énergie'!E16 -> 80.8 | L9: ='Energie Énergie'!G16 -> 1.05 | O9: ='Energie Énergie'!H16 -> 0.0628 | R9: ='Energie Énergie'!J16 -> 0.0107 | U9: ='Energie Énergie'!D16 -> kWh | V9: =VLOOKUP('Energie Énergie'!C16,RefDimensions!A$2:B$16,2,false) -> finalEnergy | X9: =LEFT(A9,6) -> 41.007 | Y9: KBOB 2016 | Z9: 60 | AA9: ="Alle > " & SWITCH(F9, "COMPONENT","BAUTEILE", "OTHER_RESOURCE", "RESSOURCEN", "BUILDING_TECHNOLOGY", "GEBÄUDETECHNIK", "MATERIAL", "MATERIALIEN") & " > kbob.admin.ch > KBOB / ecobau / IPB 2009/1:2016" -> Alle > RESSOURCEN > kbob.admin.ch > KBOB / ecobau / IPB 2009/1:2016
A10: ='Energie Énergie'!A17 & " " & 'Energie Énergie'!B17 & " (KBOB.2016)" -> 41.011 Holzschnitzel mit Partikelfilter (KBOB.2016) | B10: =A10 -> 41.011 Holzschnitzel mit Partikelfilter (KBOB.2016) | F10: OTHER_RESOURCE | G10: =SWITCH(LEFT(A10,2), "41", "OTHER_RESOURCE_ENERGY_FUEL", "42", "OTHER_RESOURCE_ENERGY_DISTRICT_HEAT", "43", "OTHER_RESOURCE_ENERGY_USEFUL_HEAT", "44", "OTHER_RESOURCE_ENERGY_USEFUL_HEAT_GENERATED_LOCALLY", "45", "OTHER_RESOURCE_ENERGY_ELECTRICITY_NET", "46", "OTHER_RESOURCE_ENERGY_ELECTRICITY_GENERATED_LOCALLY") -> OTHER_RESOURCE_ENERGY_FUEL | I10: ='Energie Énergie'!E17 -> 73.7 | L10: ='Energie Énergie'!G17 -> 1.05 | O10: ='Energie Énergie'!H17 -> 0.0651 | R10: ='Energie Énergie'!J17 -> 0.0108 | U10: ='Energie Énergie'!D17 -> kWh | V10: =VLOOKUP('Energie Énergie'!C17,RefDimensions!A$2:B$16,2,false) -> finalEnergy | X10: =LEFT(A10,6) -> 41.011 | Y10: KBOB 2016 | Z10: 60 | AA10: ="Alle > " & SWITCH(F10, "COMPONENT","BAUTEILE", "OTHER_RESOURCE", "RESSOURCEN", "BUILDING_TECHNOLOGY", "GEBÄUDETECHNIK", "MATERIAL", "MATERIALIEN") & " > kbob.admin.ch > KBOB / ecobau / IPB 2009/1:2016" -> Alle > RESSOURCEN > kbob.admin.ch > KBOB / ecobau / IPB 2009/1:2016
